Workbook
Name Abruzzo: GeoListe!$B2:$B5
Name Basilicata: GeoListe!$C2:$C3
Name Calabria: GeoListe!$D2:$D6
Name Campania: GeoListe!$E2:$E6
Name Emilia_Romagna: GeoListe!$F2:$F10
Name Friuli_Venezia_Giulia: GeoListe!$G2:$G5
Name Lazio: GeoListe!$H2:$H6
Name Liguria: GeoListe!$I2:$I5
Name Lombardia: GeoListe!$J2:$J13
Name Marche: GeoListe!$K2:$K6
Name Molise: GeoListe!$L2:$L3
Name p_Agrigento: GeoDropdown!$A$2:$A$44
Name p_Alessandria: GeoDropdown!$B$2:$B$188
Name p_Ancona: GeoDropdown!$C$2:$C$48
Name p_Arezzo: GeoDropdown!$D$2:$D$37
Name p_Ascoli_Piceno: GeoDropdown!$E$2:$E$34
Name p_Asti: GeoDropdown!$F$2:$F$118
Name p_Avellino: GeoDropdown!$G$2:$G$119
Name p_Bari: GeoDropdown!$H$2:$H$42
Name p_Barletta_Andria_Trani: GeoDropdown!$I$2:$I$11
Name p_Belluno: GeoDropdown!$J$2:$J$61
Name p_Benevento: GeoDropdown!$K$2:$K$79
Name p_Bergamo: GeoDropdown!$L$2:$L$244
Name p_Biella: GeoDropdown!$M$2:$M$75
Name p_Bologna: GeoDropdown!$N$2:$N$56
Name p_Bolzano_Bozen: GeoDropdown!$O$2:$O$117
Name p_Brescia: GeoDropdown!$P$2:$P$206
Name p_Brindisi: GeoDropdown!$Q$2:$Q$21
Name p_Cagliari: GeoDropdown!$R$2:$R$18
Name p_Caltanissetta: GeoDropdown!$S$2:$S$23
Name p_Campobasso: GeoDropdown!$T$2:$T$85
Name p_Caserta: GeoDropdown!$U$2:$U$105
Name p_Catania: GeoDropdown!$V$2:$V$59
Name p_Catanzaro: GeoDropdown!$W$2:$W$81
Name p_Chieti: GeoDropdown!$X$2:$X$105
Name p_Como: GeoDropdown!$Y$2:$Y$148
Name p_Cosenza: GeoDropdown!$Z$2:$Z$151
Name p_Cremona: GeoDropdown!$AA$2:$AA$114
Name p_Crotone: GeoDropdown!$AB$2:$AB$28
Name p_Cuneo: GeoDropdown!$AC$2:$AC$248
Name p_Enna: GeoDropdown!$AD$2:$AD$21
Name p_Fermo: GeoDropdown!$AE$2:$AE$41
Name p_Ferrara: GeoDropdown!$AF$2:$AF$22
Name p_Firenze: GeoDropdown!$AG$2:$AG$42
Name p_Foggia: GeoDropdown!$AH$2:$AH$62
Name p_Forli_Cesena: GeoDropdown!$AI$2:$AI$31
Name p_Frosinone: GeoDropdown!$AJ$2:$AJ$92
Name p_Genova: GeoDropdown!$AK$2:$AK$68
Name p_Gorizia: GeoDropdown!$AL$2:$AL$26
Name p_Grosseto: GeoDropdown!$AM$2:$AM$29
Name p_Imperia: GeoDropdown!$AN$2:$AN$67
Name p_Isernia: GeoDropdown!$AO$2:$AO$53
Name p_L_Aquila: GeoDropdown!$AP$2:$AP$109
Name p_La_Spezia: GeoDropdown!$AQ$2:$AQ$33
Name p_Latina: GeoDropdown!$AR$2:$AR$34
Name p_Lecce: GeoDropdown!$AS$2:$AS$97
Name p_Lecco: GeoDropdown!$AT$2:$AT$85
Name p_Livorno: GeoDropdown!$AU$2:$AU$20
Name p_Lodi: GeoDropdown!$AV$2:$AV$61
Name p_Lucca: GeoDropdown!$AW$2:$AW$34

Sheet Istruzioni
A1: Alayan - Template Filiale Pipeline FV
A2: Compilare questo file direttamente su OneDrive / SharePoint. Nessun invio via email.
A4: Nome filiale | B4: Catania
A5: Area filiale | B5: =IF(OR(B4="Lucca",B4="Firenze",B4="Livorno",B4="Parma",B4="Sassuolo",B4="Bologna",B4="Rimini",B4="Perugia",B4="Cagliari",B4="Sassari"),"Centro",IF(OR(B4="Roma Nomentana",B4="Roma Aurelia",B4="Frosinone",B4="Napoli",B4="Salerno",B4="Bari",B4="Cosenza",B4="Catania"),"Sud",IF(OR(B4="Genova",B4="Albenga",B4="Bergamo",B4="Brescia",B4="Cuneo",B4="Lecco",B4="Milano Est",B4="Milano Ovest",B4="Milano Nord",B4="Milano Sud",B4="Sondrio",B4="Torino"),"Nord Ovest",IF(OR(B4="Bolzano",B4="Brunico",B4="Padova",B4="Trento",B4="Treviso",B4="Udine",B4="Venezia",B4="Verona"),"Nord Est","")))) -> Sud
A6: Anno base Gantt | B6: 2026
A7: Cartella consigliata | B7: /Alayan Pipeline FV/Filiali/
A9: Istruzioni operative
A10: 1. Salvare una copia del template nella cartella OneDrive/SharePoint della propria filiale.
A11: 2. Compilare solo le celle di input nel foglio 'Pipeline' (testo blu).
A12: 3. Il foglio 'Gantt' si aggiorna automaticamente dalle date inserite nel foglio 'Pipeline'.
A13: 4. Aggiornare almeno: Cliente, Cod. Cliente, Progetto, Potenziale, MWp, Fase attuale, Stato progetto, date di fase, Ultimo aggiornamento.
A14: 5. Non modificare intestazioni, formule o struttura colonne: il dashboard nazionale legge questo layout.
A15: 6. Per nuovi progetti usare una riga libera nel foglio 'Pipeline'. Le righe sono predisposte fino a 200 progetti.
A19: Legenda colori
A20: Blu | B20: input utente
A21: Nero | B21: formula / calcolo
A22: Grigio / teal | B22: istruzioni o costanti

Sheet Progetti
A1: Pipeline progetti filiale
A2: Compilare una riga per progetto. Le date alimentano il Gantt.
A4: Filiale | B4: Area | C4: Cliente | D4: Cod. Cliente | E4: Progetto | F4: Regione | G4: Provincia | H4: Comune | I4: Potenza MWp | J4: Probabilità | K4: Potenziale | L4: Fatturaro | M4: Stato progetto | N4: Fase attuale | O4: Responsabile Progetto | P4: Data apertura | Q4: Target commissioning | R4: Ultimo aggiornamento | S4: Ritardo (gg) | T4: Stato scadenza | U4: Note | V4: SdF Inizio | W4: SdF Fine | X4: Prog. Inizio | Y4: Prog. Fine | Z4: Aut. Inizio | AA4: Aut. Fine | AB4: Proc. Inizio | AC4: Proc. Fine | AD4: Costr. Inizio | AE4: Costr. Fine | AF4: Comm. Inizio | AG4: Comm. Fine | AH4: Avanzamento %
A5: =Istruzioni!$B$4 -> Catania | B5: =Istruzioni!$B$5 -> Sud | C5: ALTOBRANDO SRL | E5: Altobrando | F5: Sicilia | G5: Catania | H5: Caltagirone | I5: 45 | M5: In pipeline | N5: Autorizzazioni | R5: 46110 | S5: =IF(OR(Q5="",M5="Completato",M5="Perso"),"",MAX(TODAY()-Q5,0)) | T5: =IF(OR(Q5="",M5="Completato",M5="Perso"),"",IF(Q5<TODAY(),"In ritardo",IF(Q5<=TODAY()+30,"In scadenza","On track"))) | U5: VIA approvata | Z5: 46108 | AA5: 46265 | AH5: =IFERROR(VLOOKUP(N5,Liste!$D$4:$E$10,2,FALSE),"") -> 0.45
A6: =Istruzioni!$B$4 -> Catania | B6: =Istruzioni!$B$5 -> Sud | C6: IBERDROLA RENOVABLES ITALIA SPA | E6: Lentini1 | F6: Sicilia | G6: Siracusa | H6: Lentini | I6: 60 | M6: In pipeline | N6: Autorizzazioni | R6: 46110 | S6: =IF(OR(Q6="",M6="Completato",M6="Perso"),"",MAX(TODAY()-Q6,0)) | T6: =IF(OR(Q6="",M6="Completato",M6="Perso"),"",IF(Q6<TODAY(),"In ritardo",IF(Q6<=TODAY()+30,"In scadenza","On track"))) | U6: Progetto anche a Palagonia (CT) | Z6: 46108 | AA6: 46265 | AH6: =IFERROR(VLOOKUP(N6,Liste!$D$4:$E$10,2,FALSE),"") -> 0.45
A7: =Istruzioni!$B$4 -> Catania | B7: =Istruzioni!$B$5 -> Sud | C7: VARNA SOLAR SRL | E7: Varna Solar | F7: Sicilia | G7: Catania | H7: Belpasso | I7: 45 | M7: In pipeline | N7: Autorizzazioni | R7: 46110 | S7: =IF(OR(Q7="",M7="Completato",M7="Perso"),"",MAX(TODAY()-Q7,0)) | T7: =IF(OR(Q7="",M7="Completato",M7="Perso"),"",IF(Q7<TODAY(),"In ritardo",IF(Q7<=TODAY()+30,"In scadenza","On track"))) | U7: VIA approvata | Z7: 46108 | AA7: 46265 | AH7: =IFERROR(VLOOKUP(N7,Liste!$D$4:$E$10,2,FALSE),"") -> 0.45
A8: =Istruzioni!$B$4 -> Catania | B8: =Istruzioni!$B$5 -> Sud | C8: INE ELIOSMENTA SRL | E8: FV Agrivoltaico Buseto | F8: Sicilia | G8: Trapani | H8: Buseto Palizzolo | I8: 27.65 | M8: In pipeline | N8: Autorizzazioni | R8: 46110 | S8: =IF(OR(Q8="",M8="Completato",M8="Perso"),"",MAX(TODAY()-Q8,0)) | T8: =IF(OR(Q8="",M8="Completato",M8="Perso"),"",IF(Q8<TODAY(),"In ritardo",IF(Q8<=TODAY()+30,"In scadenza","On track"))) | U8: VIA approvata, agrivoltaico | Z8: 46108 | AA8: 46265 | AH8: =IFERROR(VLOOKUP(N8,Liste!$D$4:$E$10,2,FALSE),"") -> 0.45
A9: =Istruzioni!$B$4 -> Catania | B9: =Istruzioni!$B$5 -> Sud | C9: ENGIE GRILLO SRL | E9: Grillo | F9: Sicilia | G9: Trapani | H9: Mazara del Vallo | I9: 54 | M9: In pipeline | N9: Autorizzazioni | R9: 46110 | S9: =IF(OR(Q9="",M9="Completato",M9="Perso"),"",MAX(TODAY()-Q9,0)) | T9: =IF(OR(Q9="",M9="Completato",M9="Perso"),"",IF(Q9<TODAY(),"In ritardo",IF(Q9<=TODAY()+30,"In scadenza","On track"))) | U9: Progetto anche a Marsala (TP) | Z9: 46108 | AA9: 46265 | AH9: =IFERROR(VLOOKUP(N9,Liste!$D$4:$E$10,2,FALSE),"") -> 0.45
A10: =Istruzioni!$B$4 -> Catania | B10: =Istruzioni!$B$5 -> Sud | C10: ARYA SOLAR SRL | E10: Arya Mazara | F10: Sicilia | G10: Trapani | H10: Mazara del Vallo | I10: 42.3 | M10: In pipeline | N10: Autorizzazioni | R10: 46030 | S10: =IF(OR(Q10="",M10="Completato",M10="Perso"),"",MAX(TODAY()-Q10,0)) | T10: =IF(OR(Q10="",M10="Completato",M10="Perso"),"",IF(Q10<TODAY(),"In ritardo",IF(Q10<=TODAY()+30,"In scadenza","On track"))) | U10: VIA approvata | Z10: 46030 | AA10: 46203 | AH10: =IFERROR(VLOOKUP(N10,Liste!$D$4:$E$10,2,FALSE),"") -> 0.45
A11: =Istruzioni!$B$4 -> Catania | B11: =Istruzioni!$B$5 -> Sud | C11: PIROIDE SRL | E11: Progetto Piana degli Albanesi | F11: Sicilia | G11: Palermo | H11: Piana degli Albanesi | I11: 85.1 | M11: In pipeline | N11: Autorizzazioni | R11: 46038 | S11: =IF(OR(Q11="",M11="Completato",M11="Perso"),"",MAX(TODAY()-Q11,0)) | T11: =IF(OR(Q11="",M11="Completato",M11="Perso"),"",IF(Q11<TODAY(),"In ritardo",IF(Q11<=TODAY()+30,"In scadenza","On track"))) | U11: Progetto anche a Monreale (PA) | Z11: 46038 | AA11: 46203 | AH11: =IFERROR(VLOOKUP(N11,Liste!$D$4:$E$10,2,FALSE),"") -> 0.45
A12: =Istruzioni!$B$4 -> Catania | B12: =Istruzioni!$B$5 -> Sud | C12: 11PIU' ENERGIA SRL | E12: Favara 2 | F12: Sicilia | G12: Agrigento | H12: Favara | I12: 65.1 | M12: In pipeline | N12: Autorizzazioni | R12: 46055 | S12: =IF(OR(Q12="",M12="Completato",M12="Perso"),"",MAX(TODAY()-Q12,0)) | T12: =IF(OR(Q12="",M12="Completato",M12="Perso"),"",IF(Q12<TODAY(),"In ritardo",IF(Q12<=TODAY()+30,"In scadenza","On track"))) | U12: Agrivoltaico | Z12: 46055 | AA12: 46234 | AH12: =IFERROR(VLOOKUP(N12,Liste!$D$4:$E$10,2,FALSE),"") -> 0.45
A13: =Istruzioni!$B$4 -> Catania | B13: =Istruzioni!$B$5 -> Sud | C13: NDTHREE SRL | E13: Pecciapertosa | F13: Sicilia | G13: Palermo | H13: Castronovo di Sicilia | I13: 22.57 | M13: In pipeline | N13: Autorizzazioni | R13: 46078 | S13: =IF(OR(Q13="",M13="Completato",M13="Perso"),"",MAX(TODAY()-Q13,0)) | T13: =IF(OR(Q13="",M13="Completato",M13="Perso"),"",IF(Q13<TODAY(),"In ritardo",IF(Q13<=TODAY()+30,"In scadenza","On track"))) | U13: Progetto anche a Lercara Friddi (PA) | Z13: 46078 | AA13: 46234 | AH13: =IFERROR(VLOOKUP(N13,Liste!$D$4:$E$10,2,FALSE),"") -> 0.45
A14: =Istruzioni!$B$4 -> Catania | B14: =Istruzioni!$B$5 -> Sud | C14: IBVI 5 SRL | E14: Castel di Iudica II | F14: Sicilia | G14: Catania | H14: Castel di Iudica | I14: 231.6 | M14: In pipeline | N14: Autorizzazioni | R14: 45923 | S14: =IF(OR(Q14="",M14="Completato",M14="Perso"),"",MAX(TODAY()-Q14,0)) | T14: =IF(OR(Q14="",M14="Completato",M14="Perso"),"",IF(Q14<TODAY(),"In ritardo",IF(Q14<=TODAY()+30,"In scadenza","On track"))) | U14: Progetto anche a Ramacca (CT) | Z14: 45923 | AA14: 46142 | AH14: =IFERROR(VLOOKUP(N14,Liste!$D$4:$E$10,2,FALSE),"") -> 0.45
A15: =Istruzioni!$B$4 -> Catania | B15: =Istruzioni!$B$5 -> Sud | C15: IBVI 22 SRL | E15: Mineo | F15: Sicilia | G15: Enna | H15: Aidone | I15: 263 | M15: In pipeline | N15: Autorizzazioni | R15: 46092 | S15: =IF(OR(Q15="",M15="Completato",M15="Perso"),"",MAX(TODAY()-Q15,0)) | T15: =IF(OR(Q15="",M15="Completato",M15="Perso"),"",IF(Q15<TODAY(),"In ritardo",IF(Q15<=TODAY()+30,"In scadenza","On track"))) | U15: Progetto anche a Mineo e Ramacca (CT) | Z15: 46092 | AA15: 46265 | AH15: =IFERROR(VLOOKUP(N15,Liste!$D$4:$E$10,2,FALSE),"") -> 0.45
A16: =Istruzioni!$B$4 -> Catania | B16: =Istruzioni!$B$5 -> Sud | C16: ENNA 1 PV SRL | E16: Enna 1 | F16: Sicilia | G16: Enna | H16: Enna | I16: 45 | M16: In pipeline | N16: Autorizzazioni | R16: 46086 | S16: =IF(OR(Q16="",M16="Completato",M16="Perso"),"",MAX(TODAY()-Q16,0)) | T16: =IF(OR(Q16="",M16="Completato",M16="Perso"),"",IF(Q16<TODAY(),"In ritardo",IF(Q16<=TODAY()+30,"In scadenza","On track"))) | U16: Agrivoltaico | Z16: 46086 | AA16: 46265 | AH16: =IFERROR(VLOOKUP(N16,Liste!$D$4:$E$10,2,FALSE),"") -> 0.45
... A22: =Istruzioni!$B$4 -> Catania | B22: =Istruzioni!$B$5 -> Sud | C22: CVA EOS SRL | E22: AGV Gatto Corvino | F22: Sicilia | G22: Ragusa | H22: Ragusa | I22: 90.6 | M22: In pipeline | N22: Autorizzazioni | R22: 46114 | S22: =IF(OR(Q22="",M22="Completato",M22="Perso"),"",MAX(TODAY()-Q22,0)) | T22: =IF(OR(Q22="",M22="Completato",M22="Perso"),"",IF(Q22<TODAY(),"In ritardo",IF(Q22<=TODAY()+30,"In scadenza","On track"))) | U22: Agrivoltaico, VIA approvata | Z22: 46114 | AA22: 46295 | AH22: =IFERROR(VLOOKUP(N22,Liste!$D$4:$E$10,2,FALSE),"") -> 0.45
A23: =Istruzioni!$B$4 -> Catania | B23: =Istruzioni!$B$5 -> Sud | C23: PERIDOT SOLAR (ITALY) SRL | E23: PV Monreale e Gibellina | F23: Sicilia | G23: Palermo | H23: Monreale | I23: 137 | M23: In pipeline | N23: Procurement | R23: 46120 | S23: =IF(OR(Q23="",M23="Completato",M23="Perso"),"",MAX(TODAY()-Q23,0)) | T23: =IF(OR(Q23="",M23="Completato",M23="Perso"),"",IF(Q23<TODAY(),"In ritardo",IF(Q23<=TODAY()+30,"In scadenza","On track"))) | U23: Progetto anche a Gibellina(TP) | AB23: 46113 | AC23: 46142 | AH23: =IFERROR(VLOOKUP(N23,Liste!$D$4:$E$10,2,FALSE),"") -> 0.6
A24: =Istruzioni!$B$4 -> Catania | B24: =Istruzioni!$B$5 -> Sud | C24: CCE ITALIA | E24: Smart Island Pantelleria | F24: Sicilia | G24: Trapani | H24: Pantelleria | I24: 0.93 | M24: Attivo | N24: Costruzione | R24: 46125 | S24: =IF(OR(Q24="",M24="Completato",M24="Perso"),"",MAX(TODAY()-Q24,0)) | T24: =IF(OR(Q24="",M24="Completato",M24="Perso"),"",IF(Q24<TODAY(),"In ritardo",IF(Q24<=TODAY()+30,"In scadenza","On track"))) | U24: Lavori in zona Arenella | AD24: 46118 | AE24: 46203 | AH24: =IFERROR(VLOOKUP(N24,Liste!$D$4:$E$10,2,FALSE),"") -> 0.85
A25: =Istruzioni!$B$4 -> Catania | B25: =Istruzioni!$B$5 -> Sud | C25: CAPOBIANCO SRL | E25: Capobianco | F25: Sicilia | G25: Enna | H25: Assoro | I25: 250 | M25: In pipeline | N25: Autorizzazioni | R25: 46125 | S25: =IF(OR(Q25="",M25="Completato",M25="Perso"),"",MAX(TODAY()-Q25,0)) | T25: =IF(OR(Q25="",M25="Completato",M25="Perso"),"",IF(Q25<TODAY(),"In ritardo",IF(Q25<=TODAY()+30,"In scadenza","On track"))) | U25: Progetto anche a Enna e Raddusa (CT) | Z25: 46125 | AA25: 46295 | AH25: =IFERROR(VLOOKUP(N25,Liste!$D$4:$E$10,2,FALSE),"") -> 0.45
A26: =Istruzioni!$B$4 -> Catania | B26: =Istruzioni!$B$5 -> Sud | C26: EDPR SICILIA PV SRL | E26: Zaffarana 38 | F26: Sicilia | G26: Trapani | H26: Trapani | I26: 38.3 | M26: In pipeline | N26: Autorizzazioni | R26: 46125 | S26: =IF(OR(Q26="",M26="Completato",M26="Perso"),"",MAX(TODAY()-Q26,0)) | T26: =IF(OR(Q26="",M26="Completato",M26="Perso"),"",IF(Q26<TODAY(),"In ritardo",IF(Q26<=TODAY()+30,"In scadenza","On track"))) | U26: PUA approvato, agrivoltaico | Z26: 46125 | AA26: 46295 | AH26: =IFERROR(VLOOKUP(N26,Liste!$D$4:$E$10,2,FALSE),"") -> 0.45
A27: =Istruzioni!$B$4 -> Catania | B27: =Istruzioni!$B$5 -> Sud | C27: RENANTIS ITALIA SRL | E27: Biddine | F27: Sicilia | G27: Ragusa | H27: Acate | I27: 35 | M27: In pipeline | N27: Autorizzazioni | R27: 46129 | S27: =IF(OR(Q27="",M27="Completato",M27="Perso"),"",MAX(TODAY()-Q27,0)) | T27: =IF(OR(Q27="",M27="Completato",M27="Perso"),"",IF(Q27<TODAY(),"In ritardo",IF(Q27<=TODAY()+30,"In scadenza","On track"))) | U27: VIA approvata | Z27: 46129 | AA27: 46325 | AH27: =IFERROR(VLOOKUP(N27,Liste!$D$4:$E$10,2,FALSE),"") -> 0.45
A28: =Istruzioni!$B$4 -> Catania | B28: =Istruzioni!$B$5 -> Sud | S28: =IF(OR(Q28="",M28="Completato",M28="Perso"),"",MAX(TODAY()-Q28,0)) | T28: =IF(OR(Q28="",M28="Completato",M28="Perso"),"",IF(Q28<TODAY(),"In ritardo",IF(Q28<=TODAY()+30,"In scadenza","On track"))) | AH28: =IFERROR(VLOOKUP(N28,Liste!$D$4:$E$10,2,FALSE),"")
A29: =Istruzioni!$B$4 -> Catania | B29: =Istruzioni!$B$5 -> Sud | S29: =IF(OR(Q29="",M29="Completato",M29="Perso"),"",MAX(TODAY()-Q29,0)) | T29: =IF(OR(Q29="",M29="Completato",M29="Perso"),"",IF(Q29<TODAY(),"In ritardo",IF(Q29<=TODAY()+30,"In scadenza","On track"))) | AH29: =IFERROR(VLOOKUP(N29,Liste!$D$4:$E$10,2,FALSE),"")
A30: =Istruzioni!$B$4 -> Catania | B30: =Istruzioni!$B$5 -> Sud | S30: =IF(OR(Q30="",M30="Completato",M30="Perso"),"",MAX(TODAY()-Q30,0)) | T30: =IF(OR(Q30="",M30="Completato",M30="Perso"),"",IF(Q30<TODAY(),"In ritardo",IF(Q30<=TODAY()+30,"In scadenza","On track"))) | AH30: =IFERROR(VLOOKUP(N30,Liste!$D$4:$E$10,2,FALSE),"")
A31: =Istruzioni!$B$4 -> Catania | B31: =Istruzioni!$B$5 -> Sud | S31: =IF(OR(Q31="",M31="Completato",M31="Perso"),"",MAX(TODAY()-Q31,0)) | T31: =IF(OR(Q31="",M31="Completato",M31="Perso"),"",IF(Q31<TODAY(),"In ritardo",IF(Q31<=TODAY()+30,"In scadenza","On track"))) | AH31: =IFERROR(VLOOKUP(N31,Liste!$D$4:$E$10,2,FALSE),"")
A32: =Istruzioni!$B$4 -> Catania | B32: =Istruzioni!$B$5 -> Sud | S32: =IF(OR(Q32="",M32="Completato",M32="Perso"),"",MAX(TODAY()-Q32,0)) | T32: =IF(OR(Q32="",M32="Completato",M32="Perso"),"",IF(Q32<TODAY(),"In ritardo",IF(Q32<=TODAY()+30,"In scadenza","On track"))) | AH32: =IFERROR(VLOOKUP(N32,Liste!$D$4:$E$10,2,FALSE),"")
A33: =Istruzioni!$B$4 -> Catania | B33: =Istruzioni!$B$5 -> Sud | S33: =IF(OR(Q33="",M33="Completato",M33="Perso"),"",MAX(TODAY()-Q33,0)) | T33: =IF(OR(Q33="",M33="Completato",M33="Perso"),"",IF(Q33<TODAY(),"In ritardo",IF(Q33<=TODAY()+30,"In scadenza","On track"))) | AH33: =IFERROR(VLOOKUP(N33,Liste!$D$4:$E$10,2,FALSE),"")
A34: =Istruzioni!$B$4 -> Catania | B34: =Istruzioni!$B$5 -> Sud | S34: =IF(OR(Q34="",M34="Completato",M34="Perso"),"",MAX(TODAY()-Q34,0)) | T34: =IF(OR(Q34="",M34="Completato",M34="Perso"),"",IF(Q34<TODAY(),"In ritardo",IF(Q34<=TODAY()+30,"In scadenza","On track"))) | AH34: =IFERROR(VLOOKUP(N34,Liste!$D$4:$E$10,2,FALSE),"")
A35: =Istruzioni!$B$4 -> Catania | B35: =Istruzioni!$B$5 -> Sud | S35: =IF(OR(Q35="",M35="Completato",M35="Perso"),"",MAX(TODAY()-Q35,0)) | T35: =IF(OR(Q35="",M35="Completato",M35="Perso"),"",IF(Q35<TODAY(),"In ritardo",IF(Q35<=TODAY()+30,"In scadenza","On track"))) | AH35: =IFERROR(VLOOKUP(N35,Liste!$D$4:$E$10,2,FALSE),"")
A36: =Istruzioni!$B$4 -> Catania | B36: =Istruzioni!$B$5 -> Sud | S36: =IF(OR(Q36="",M36="Completato",M36="Perso"),"",MAX(TODAY()-Q36,0)) | T36: =IF(OR(Q36="",M36="Completato",M36="Perso"),"",IF(Q36<TODAY(),"In ritardo",IF(Q36<=TODAY()+30,"In scadenza","On track"))) | AH36: =IFERROR(VLOOKUP(N36,Liste!$D$4:$E$10,2,FALSE),"")
A37: =Istruzioni!$B$4 -> Catania | B37: =Istruzioni!$B$5 -> Sud | S37: =IF(OR(Q37="",M37="Completato",M37="Perso"),"",MAX(TODAY()-Q37,0)) | T37: =IF(OR(Q37="",M37="Completato",M37="Perso"),"",IF(Q37<TODAY(),"In ritardo",IF(Q37<=TODAY()+30,"In scadenza","On track"))) | AH37: =IFERROR(VLOOKUP(N37,Liste!$D$4:$E$10,2,FALSE),"")
A38: =Istruzioni!$B$4 -> Catania | B38: =Istruzioni!$B$5 -> Sud | S38: =IF(OR(Q38="",M38="Completato",M38="Perso"),"",MAX(TODAY()-Q38,0)) | T38: =IF(OR(Q38="",M38="Completato",M38="Perso"),"",IF(Q38<TODAY(),"In ritardo",IF(Q38<=TODAY()+30,"In scadenza","On track"))) | AH38: =IFERROR(VLOOKUP(N38,Liste!$D$4:$E$10,2,FALSE),"")
A39: =Istruzioni!$B$4 -> Catania | B39: =Istruzioni!$B$5 -> Sud | S39: =IF(OR(Q39="",M39="Completato",M39="Perso"),"",MAX(TODAY()-Q39,0)) | T39: =IF(OR(Q39="",M39="Completato",M39="Perso"),"",IF(Q39<TODAY(),"In ritardo",IF(Q39<=TODAY()+30,"In scadenza","On track"))) | AH39: =IFERROR(VLOOKUP(N39,Liste!$D$4:$E$10,2,FALSE),"")
... A204: =Istruzioni!$B$4 -> Catania | B204: =Istruzioni!$B$5 -> Sud | S204: =IF(OR(Q204="",M204="Completato",M204="Perso"),"",MAX(TODAY()-Q204,0)) | T204: =IF(OR(Q204="",M204="Completato",M204="Perso"),"",IF(Q204<TODAY(),"In ritardo",IF(Q204<=TODAY()+30,"In scadenza","On track"))) | AH204: =IFERROR(VLOOKUP(N204,Liste!$D$4:$E$10,2,FALSE),"")

Sheet Liste
A1: Liste e mapping
A3: Stato progetto | B3: Albenga | D3: Fase | E3: Avanzamento | G3: Stato scadenza | J3: Legenda Gantt
A4: In pipeline | B4: Bari | D4: Studio di fattibilità | E4: 0.1 | G4: On track | J4: Studio di fattibilità
A5: Attivo | B5: Bergamo | D5: Progettazione | E5: 0.25 | G5: In scadenza | J5: Progettazione
A6: In pausa | B6: Bologna | D6: Autorizzazioni | E6: 0.45 | G6: In ritardo | J6: Autorizzazioni
A7: Completato | B7: Bolzano | D7: Procurement | E7: 0.6 | J7: Procurement
A8: Perso | B8: Brescia | D8: Costruzione | E8: 0.85 | J8: Costruzione
B9: Brunico | D9: Commissioning | E9: 0.95 | J9: Commissioning
B10: Cagliari | D10: Operativo | E10: 1
B11: Catania
B12: Cosenza
B13: Cuneo
B14: Firenze
B15: Frosinone
B16: Genova
B17: Lecco
B18: Livorno
B19: Lucca
B20: Milano Est
B21: Milano Nord
B22: Milano Ovest
... B40: Verona

Sheet Gantt Chart
A1: Gantt chart progetti filiale
A2: Barre colorate per fase. Le date arrivano dal foglio 'Pipeline'.
A3: Nome filiale | C3: =Istruzioni!$B$4 -> Catania | D3: Anno base | E3: =Istruzioni!$B$6 -> 2026
A6: Filiale | B6: Area | C6: Cliente | D6: Cod. Cliente | E6: Progetto | F6: Potenziale | G6: Fatturato | H6: Fase attuale | I6: Stato | J6: MWp | K6: Target COD | L6: Ultimo aggiornamento | M6: SDF I | N6: SDF F | O6: PROG I | P6: PROG F | Q6: AUT I | R6: AUT F | S6: PROC I | T6: PROC F | U6: COSTR I | V6: COSTR F | W6: COMM I | X6: COMM F | Y6: =DATE($E$3,1,1) -> 46023 | Z6: =DATE($E$3,2,1) -> 46054 | AA6: =DATE($E$3,3,1) -> 46082 | AB6: =DATE($E$3,4,1) -> 46113 | AC6: =DATE($E$3,5,1) -> 46143 | AD6: =DATE($E$3,6,1) -> 46174 | AE6: =DATE($E$3,7,1) -> 46204 | AF6: =DATE($E$3,8,1) -> 46235 | AG6: =DATE($E$3,9,1) -> 46266 | AH6: =DATE($E$3,10,1) -> 46296 | AI6: =DATE($E$3,11,1) -> 46327 | AJ6: =DATE($E$3,12,1) -> 46357 | AK6: =DATE($E$3,13,1) -> 46388 | AL6: =DATE($E$3,14,1) -> 46419 | AM6: =DATE($E$3,15,1) -> 46447 | AN6: =DATE($E$3,16,1) -> 46478 | AO6: =DATE($E$3,17,1) -> 46508 | AP6: =DATE($E$3,18,1) -> 46539 | AQ6: =DATE($E$3,19,1) -> 46569 | AR6: =DATE($E$3,20,1) -> 46600 | AS6: =DATE($E$3,21,1) -> 46631 | AT6: =DATE($E$3,22,1) -> 46661 | AU6: =DATE($E$3,23,1) -> 46692 | AV6: =DATE($E$3,24,1) -> 46722 | AW6: =DATE($E$3,25,1) -> 46753 | AX6: =DATE($E$3,26,1) -> 46784 | AY6: =DATE($E$3,27,1) -> 46813 | AZ6: =DATE($E$3,28,1) -> 46844 | BA6: =DATE($E$3,29,1) -> 46874 | BB6: =DATE($E$3,30,1) -> 46905 | BC6: =DATE($E$3,31,1) -> 46935 | BD6: =DATE($E$3,32,1) -> 46966 | BE6: =DATE($E$3,33,1) -> 46997 | BF6: =DATE($E$3,34,1) -> 47027 | BG6: =DATE($E$3,35,1) -> 47058 | BH6: =DATE($E$3,36,1) -> 47088 | BI6: =DATE($E$3,37,1) -> 47119 | BJ6: =DATE($E$3,38,1) -> 47150 | BK6: =DATE($E$3,39,1) -> 47178 | BL6: =DATE($E$3,40,1) -> 47209 | BM6: =DATE($E$3,41,1) -> 47239 | BN6: =DATE($E$3,42,1) -> 47270 | BO6: =DATE($E$3,43,1) -> 47300 | BP6: =DATE($E$3,44,1) -> 47331 | BQ6: =DATE($E$3,45,1) -> 47362 | BR6: =DATE($E$3,46,1) -> 47392 | BS6: =DATE($E$3,47,1) -> 47423 | BT6: =DATE($E$3,48,1) -> 47453 | BU6: =DATE($E$3,49,1) -> 47484 | BV6: =DATE($E$3,50,1) -> 47515 | BW6: =DATE($E$3,51,1) -> 47543 | BX6: =DATE($E$3,52,1) -> 47574 | BY6: =DATE($E$3,53,1) -> 47604 | BZ6: =DATE($E$3,54,1) -> 47635 | CA6: =DATE($E$3,55,1) -> 47665 | CB6: =DATE($E$3,56,1) -> 47696 | CC6: =DATE($E$3,57,1) -> 47727 | CD6: =DATE($E$3,58,1) -> 47757 | CE6: =DATE($E$3,59,1) -> 47788 | CF6: =DATE($E$3,60,1) -> 47818
A7: =IF(Progetti!E5="","",Progetti!A5) -> Catania | B7: =IF(Progetti!F5="","",Progetti!B5) -> Sud | C7: =IF(Progetti!E5="","",Progetti!C5) -> ALTOBRANDO SRL | D7: =IF(Progetti!F5="","",Progetti!D5) -> 0 | E7: =IF(Progetti!E5="","",Progetti!E5) -> Altobrando | F7: =IF(Progetti!K5="","",Progetti!K5) | G7: =IF(Progetti!L5="","",Progetti!L5) | H7: =IF(Progetti!E5="","",Progetti!N5) -> Autorizzazioni | I7: =IF(Progetti!E5="","",Progetti!M5) -> In pipeline | J7: =IF(Progetti!E5="","",Progetti!I5) -> 45 | K7: =IF(OR(Progetti!E5="",Progetti!Q5=""),"",Progetti!Q5) | L7: =IF(OR(Progetti!E5="",Progetti!R5=""),"",Progetti!R5) -> 46110 | M7: =IF(OR(Progetti!E5="",Progetti!V5=""),"",Progetti!V5) | N7: =IF(OR(Progetti!E5="",Progetti!W5=""),"",Progetti!W5) | O7: =IF(OR(Progetti!E5="",Progetti!X5=""),"",Progetti!X5) | P7: =IF(OR(Progetti!E5="",Progetti!Y5=""),"",Progetti!Y5) | Q7: =IF(OR(Progetti!E5="",Progetti!Z5=""),"",Progetti!Z5) -> 46108 | R7: =IF(OR(Progetti!E5="",Progetti!AA5=""),"",Progetti!AA5) -> 46265 | S7: =IF(OR(Progetti!E5="",Progetti!AB5=""),"",Progetti!AB5) | T7: =IF(OR(Progetti!E5="",Progetti!AC5=""),"",Progetti!AC5) | U7: =IF(OR(Progetti!E5="",Progetti!AD5=""),"",Progetti!AD5) | V7: =IF(OR(Progetti!E5="",Progetti!AE5=""),"",Progetti!AE5) | W7: =IF(OR(Progetti!E5="",Progetti!AF5=""),"",Progetti!AF5) | X7: =IF(OR(Progetti!E5="",Progetti!AG5=""),"",Progetti!AG5)
A8: =IF(Progetti!E6="","",Progetti!A6) -> Catania | B8: =IF(Progetti!F6="","",Progetti!B6) -> Sud | C8: =IF(Progetti!E6="","",Progetti!C6) -> IBERDROLA RENOVABLES ITALIA SPA | D8: =IF(Progetti!F6="","",Progetti!D6) -> 0 | E8: =IF(Progetti!E6="","",Progetti!E6) -> Lentini1 | F8: =IF(Progetti!K6="","",Progetti!K6) | G8: =IF(Progetti!L6="","",Progetti!L6) | H8: =IF(Progetti!E6="","",Progetti!N6) -> Autorizzazioni | I8: =IF(Progetti!E6="","",Progetti!M6) -> In pipeline | J8: =IF(Progetti!E6="","",Progetti!I6) -> 60 | K8: =IF(OR(Progetti!E6="",Progetti!Q6=""),"",Progetti!Q6) | L8: =IF(OR(Progetti!E6="",Progetti!R6=""),"",Progetti!R6) -> 46110 | M8: =IF(OR(Progetti!E6="",Progetti!V6=""),"",Progetti!V6) | N8: =IF(OR(Progetti!E6="",Progetti!W6=""),"",Progetti!W6) | O8: =IF(OR(Progetti!E6="",Progetti!X6=""),"",Progetti!X6) | P8: =IF(OR(Progetti!E6="",Progetti!Y6=""),"",Progetti!Y6) | Q8: =IF(OR(Progetti!E6="",Progetti!Z6=""),"",Progetti!Z6) -> 46108 | R8: =IF(OR(Progetti!E6="",Progetti!AA6=""),"",Progetti!AA6) -> 46265 | S8: =IF(OR(Progetti!E6="",Progetti!AB6=""),"",Progetti!AB6) | T8: =IF(OR(Progetti!E6="",Progetti!AC6=""),"",Progetti!AC6) | U8: =IF(OR(Progetti!E6="",Progetti!AD6=""),"",Progetti!AD6) | V8: =IF(OR(Progetti!E6="",Progetti!AE6=""),"",Progetti!AE6) | W8: =IF(OR(Progetti!E6="",Progetti!AF6=""),"",Progetti!AF6) | X8: =IF(OR(Progetti!E6="",Progetti!AG6=""),"",Progetti!AG6)
A9: =IF(Progetti!E7="","",Progetti!A7) -> Catania | B9: =IF(Progetti!F7="","",Progetti!B7) -> Sud | C9: =IF(Progetti!E7="","",Progetti!C7) -> VARNA SOLAR SRL | D9: =IF(Progetti!F7="","",Progetti!D7) -> 0 | E9: =IF(Progetti!E7="","",Progetti!E7) -> Varna Solar | F9: =IF(Progetti!K7="","",Progetti!K7) | G9: =IF(Progetti!L7="","",Progetti!L7) | H9: =IF(Progetti!E7="","",Progetti!N7) -> Autorizzazioni | I9: =IF(Progetti!E7="","",Progetti!M7) -> In pipeline | J9: =IF(Progetti!E7="","",Progetti!I7) -> 45 | K9: =IF(OR(Progetti!E7="",Progetti!Q7=""),"",Progetti!Q7) | L9: =IF(OR(Progetti!E7="",Progetti!R7=""),"",Progetti!R7) -> 46110 | M9: =IF(OR(Progetti!E7="",Progetti!V7=""),"",Progetti!V7) | N9: =IF(OR(Progetti!E7="",Progetti!W7=""),"",Progetti!W7) | O9: =IF(OR(Progetti!E7="",Progetti!X7=""),"",Progetti!X7) | P9: =IF(OR(Progetti!E7="",Progetti!Y7=""),"",Progetti!Y7) | Q9: =IF(OR(Progetti!E7="",Progetti!Z7=""),"",Progetti!Z7) -> 46108 | R9: =IF(OR(Progetti!E7="",Progetti!AA7=""),"",Progetti!AA7) -> 46265 | S9: =IF(OR(Progetti!E7="",Progetti!AB7=""),"",Progetti!AB7) | T9: =IF(OR(Progetti!E7="",Progetti!AC7=""),"",Progetti!AC7) | U9: =IF(OR(Progetti!E7="",Progetti!AD7=""),"",Progetti!AD7) | V9: =IF(OR(Progetti!E7="",Progetti!AE7=""),"",Progetti!AE7) | W9: =IF(OR(Progetti!E7="",Progetti!AF7=""),"",Progetti!AF7) | X9: =IF(OR(Progetti!E7="",Progetti!AG7=""),"",Progetti!AG7)
A10: =IF(Progetti!E8="","",Progetti!A8) -> Catania | B10: =IF(Progetti!F8="","",Progetti!B8) -> Sud | C10: =IF(Progetti!E8="","",Progetti!C8) -> INE ELIOSMENTA SRL | D10: =IF(Progetti!F8="","",Progetti!D8) -> 0 | E10: =IF(Progetti!E8="","",Progetti!E8) -> FV Agrivoltaico Buseto | F10: =IF(Progetti!K8="","",Progetti!K8) | G10: =IF(Progetti!L8="","",Progetti!L8) | H10: =IF(Progetti!E8="","",Progetti!N8) -> Autorizzazioni | I10: =IF(Progetti!E8="","",Progetti!M8) -> In pipeline | J10: =IF(Progetti!E8="","",Progetti!I8) -> 27.65 | K10: =IF(OR(Progetti!E8="",Progetti!Q8=""),"",Progetti!Q8) | L10: =IF(OR(Progetti!E8="",Progetti!R8=""),"",Progetti!R8) -> 46110 | M10: =IF(OR(Progetti!E8="",Progetti!V8=""),"",Progetti!V8) | N10: =IF(OR(Progetti!E8="",Progetti!W8=""),"",Progetti!W8) | O10: =IF(OR(Progetti!E8="",Progetti!X8=""),"",Progetti!X8) | P10: =IF(OR(Progetti!E8="",Progetti!Y8=""),"",Progetti!Y8) | Q10: =IF(OR(Progetti!E8="",Progetti!Z8=""),"",Progetti!Z8) -> 46108 | R10: =IF(OR(Progetti!E8="",Progetti!AA8=""),"",Progetti!AA8) -> 46265 | S10: =IF(OR(Progetti!E8="",Progetti!AB8=""),"",Progetti!AB8) | T10: =IF(OR(Progetti!E8="",Progetti!AC8=""),"",Progetti!AC8) | U10: =IF(OR(Progetti!E8="",Progetti!AD8=""),"",Progetti!AD8) | V10: =IF(OR(Progetti!E8="",Progetti!AE8=""),"",Progetti!AE8) | W10: =IF(OR(Progetti!E8="",Progetti!AF8=""),"",Progetti!AF8) | X10: =IF(OR(Progetti!E8="",Progetti!AG8=""),"",Progetti!AG8)
A11: =IF(Progetti!E9="","",Progetti!A9) -> Catania | B11: =IF(Progetti!F9="","",Progetti!B9) -> Sud | C11: =IF(Progetti!E9="","",Progetti!C9) -> ENGIE GRILLO SRL | D11: =IF(Progetti!F9="","",Progetti!D9) -> 0 | E11: =IF(Progetti!E9="","",Progetti!E9) -> Grillo | F11: =IF(Progetti!K9="","",Progetti!K9) | G11: =IF(Progetti!L9="","",Progetti!L9) | H11: =IF(Progetti!E9="","",Progetti!N9) -> Autorizzazioni | I11: =IF(Progetti!E9="","",Progetti!M9) -> In pipeline | J11: =IF(Progetti!E9="","",Progetti!I9) -> 54 | K11: =IF(OR(Progetti!E9="",Progetti!Q9=""),"",Progetti!Q9) | L11: =IF(OR(Progetti!E9="",Progetti!R9=""),"",Progetti!R9) -> 46110 | M11: =IF(OR(Progetti!E9="",Progetti!V9=""),"",Progetti!V9) | N11: =IF(OR(Progetti!E9="",Progetti!W9=""),"",Progetti!W9) | O11: =IF(OR(Progetti!E9="",Progetti!X9=""),"",Progetti!X9) | P11: =IF(OR(Progetti!E9="",Progetti!Y9=""),"",Progetti!Y9) | Q11: =IF(OR(Progetti!E9="",Progetti!Z9=""),"",Progetti!Z9) -> 46108 | R11: =IF(OR(Progetti!E9="",Progetti!AA9=""),"",Progetti!AA9) -> 46265 | S11: =IF(OR(Progetti!E9="",Progetti!AB9=""),"",Progetti!AB9) | T11: =IF(OR(Progetti!E9="",Progetti!AC9=""),"",Progetti!AC9) | U11: =IF(OR(Progetti!E9="",Progetti!AD9=""),"",Progetti!AD9) | V11: =IF(OR(Progetti!E9="",Progetti!AE9=""),"",Progetti!AE9) | W11: =IF(OR(Progetti!E9="",Progetti!AF9=""),"",Progetti!AF9) | X11: =IF(OR(Progetti!E9="",Progetti!AG9=""),"",Progetti!AG9)
A12: =IF(Progetti!E10="","",Progetti!A10) -> Catania | B12: =IF(Progetti!F10="","",Progetti!B10) -> Sud | C12: =IF(Progetti!E10="","",Progetti!C10) -> ARYA SOLAR SRL | D12: =IF(Progetti!F10="","",Progetti!D10) -> 0 | E12: =IF(Progetti!E10="","",Progetti!E10) -> Arya Mazara | F12: =IF(Progetti!K10="","",Progetti!K10) | G12: =IF(Progetti!L10="","",Progetti!L10) | H12: =IF(Progetti!E10="","",Progetti!N10) -> Autorizzazioni | I12: =IF(Progetti!E10="","",Progetti!M10) -> In pipeline | J12: =IF(Progetti!E10="","",Progetti!I10) -> 42.3 | K12: =IF(OR(Progetti!E10="",Progetti!Q10=""),"",Progetti!Q10) | L12: =IF(OR(Progetti!E10="",Progetti!R10=""),"",Progetti!R10) -> 46030 | M12: =IF(OR(Progetti!E10="",Progetti!V10=""),"",Progetti!V10) | N12: =IF(OR(Progetti!E10="",Progetti!W10=""),"",Progetti!W10) | O12: =IF(OR(Progetti!E10="",Progetti!X10=""),"",Progetti!X10) | P12: =IF(OR(Progetti!E10="",Progetti!Y10=""),"",Progetti!Y10) | Q12: =IF(OR(Progetti!E10="",Progetti!Z10=""),"",Progetti!Z10) -> 46030 | R12: =IF(OR(Progetti!E10="",Progetti!AA10=""),"",Progetti!AA10) -> 46203 | S12: =IF(OR(Progetti!E10="",Progetti!AB10=""),"",Progetti!AB10) | T12: =IF(OR(Progetti!E10="",Progetti!AC10=""),"",Progetti!AC10) | U12: =IF(OR(Progetti!E10="",Progetti!AD10=""),"",Progetti!AD10) | V12: =IF(OR(Progetti!E10="",Progetti!AE10=""),"",Progetti!AE10) | W12: =IF(OR(Progetti!E10="",Progetti!AF10=""),"",Progetti!AF10) | X12: =IF(OR(Progetti!E10="",Progetti!AG10=""),"",Progetti!AG10)
A13: =IF(Progetti!E11="","",Progetti!A11) -> Catania | B13: =IF(Progetti!F11="","",Progetti!B11) -> Sud | C13: =IF(Progetti!E11="","",Progetti!C11) -> PIROIDE SRL | D13: =IF(Progetti!F11="","",Progetti!D11) -> 0 | E13: =IF(Progetti!E11="","",Progetti!E11) -> Progetto Piana degli Albanesi | F13: =IF(Progetti!K11="","",Progetti!K11) | G13: =IF(Progetti!L11="","",Progetti!L11) | H13: =IF(Progetti!E11="","",Progetti!N11) -> Autorizzazioni | I13: =IF(Progetti!E11="","",Progetti!M11) -> In pipeline | J13: =IF(Progetti!E11="","",Progetti!I11) -> 85.1 | K13: =IF(OR(Progetti!E11="",Progetti!Q11=""),"",Progetti!Q11) | L13: =IF(OR(Progetti!E11="",Progetti!R11=""),"",Progetti!R11) -> 46038 | M13: =IF(OR(Progetti!E11="",Progetti!V11=""),"",Progetti!V11) | N13: =IF(OR(Progetti!E11="",Progetti!W11=""),"",Progetti!W11) | O13: =IF(OR(Progetti!E11="",Progetti!X11=""),"",Progetti!X11) | P13: =IF(OR(Progetti!E11="",Progetti!Y11=""),"",Progetti!Y11) | Q13: =IF(OR(Progetti!E11="",Progetti!Z11=""),"",Progetti!Z11) -> 46038 | R13: =IF(OR(Progetti!E11="",Progetti!AA11=""),"",Progetti!AA11) -> 46203 | S13: =IF(OR(Progetti!E11="",Progetti!AB11=""),"",Progetti!AB11) | T13: =IF(OR(Progetti!E11="",Progetti!AC11=""),"",Progetti!AC11) | U13: =IF(OR(Progetti!E11="",Progetti!AD11=""),"",Progetti!AD11) | V13: =IF(OR(Progetti!E11="",Progetti!AE11=""),"",Progetti!AE11) | W13: =IF(OR(Progetti!E11="",Progetti!AF11=""),"",Progetti!AF11) | X13: =IF(OR(Progetti!E11="",Progetti!AG11=""),"",Progetti!AG11)
A14: =IF(Progetti!E12="","",Progetti!A12) -> Catania | B14: =IF(Progetti!F12="","",Progetti!B12) -> Sud | C14: =IF(Progetti!E12="","",Progetti!C12) -> 11PIU' ENERGIA SRL | D14: =IF(Progetti!F12="","",Progetti!D12) -> 0 | E14: =IF(Progetti!E12="","",Progetti!E12) -> Favara 2 | F14: =IF(Progetti!K12="","",Progetti!K12) | G14: =IF(Progetti!L12="","",Progetti!L12) | H14: =IF(Progetti!E12="","",Progetti!N12) -> Autorizzazioni | I14: =IF(Progetti!E12="","",Progetti!M12) -> In pipeline | J14: =IF(Progetti!E12="","",Progetti!I12) -> 65.1 | K14: =IF(OR(Progetti!E12="",Progetti!Q12=""),"",Progetti!Q12) | L14: =IF(OR(Progetti!E12="",Progetti!R12=""),"",Progetti!R12) -> 46055 | M14: =IF(OR(Progetti!E12="",Progetti!V12=""),"",Progetti!V12) | N14: =IF(OR(Progetti!E12="",Progetti!W12=""),"",Progetti!W12) | O14: =IF(OR(Progetti!E12="",Progetti!X12=""),"",Progetti!X12) | P14: =IF(OR(Progetti!E12="",Progetti!Y12=""),"",Progetti!Y12) | Q14: =IF(OR(Progetti!E12="",Progetti!Z12=""),"",Progetti!Z12) -> 46055 | R14: =IF(OR(Progetti!E12="",Progetti!AA12=""),"",Progetti!AA12) -> 46234 | S14: =IF(OR(Progetti!E12="",Progetti!AB12=""),"",Progetti!AB12) | T14: =IF(OR(Progetti!E12="",Progetti!AC12=""),"",Progetti!AC12) | U14: =IF(OR(Progetti!E12="",Progetti!AD12=""),"",Progetti!AD12) | V14: =IF(OR(Progetti!E12="",Progetti!AE12=""),"",Progetti!AE12) | W14: =IF(OR(Progetti!E12="",Progetti!AF12=""),"",Progetti!AF12) | X14: =IF(OR(Progetti!E12="",Progetti!AG12=""),"",Progetti!AG12)
A15: =IF(Progetti!E13="","",Progetti!A13) -> Catania | B15: =IF(Progetti!F13="","",Progetti!B13) -> Sud | C15: =IF(Progetti!E13="","",Progetti!C13) -> NDTHREE SRL | D15: =IF(Progetti!F13="","",Progetti!D13) -> 0 | E15: =IF(Progetti!E13="","",Progetti!E13) -> Pecciapertosa | F15: =IF(Progetti!K13="","",Progetti!K13) | G15: =IF(Progetti!L13="","",Progetti!L13) | H15: =IF(Progetti!E13="","",Progetti!N13) -> Autorizzazioni | I15: =IF(Progetti!E13="","",Progetti!M13) -> In pipeline | J15: =IF(Progetti!E13="","",Progetti!I13) -> 22.57 | K15: =IF(OR(Progetti!E13="",Progetti!Q13=""),"",Progetti!Q13) | L15: =IF(OR(Progetti!E13="",Progetti!R13=""),"",Progetti!R13) -> 46078 | M15: =IF(OR(Progetti!E13="",Progetti!V13=""),"",Progetti!V13) | N15: =IF(OR(Progetti!E13="",Progetti!W13=""),"",Progetti!W13) | O15: =IF(OR(Progetti!E13="",Progetti!X13=""),"",Progetti!X13) | P15: =IF(OR(Progetti!E13="",Progetti!Y13=""),"",Progetti!Y13) | Q15: =IF(OR(Progetti!E13="",Progetti!Z13=""),"",Progetti!Z13) -> 46078 | R15: =IF(OR(Progetti!E13="",Progetti!AA13=""),"",Progetti!AA13) -> 46234 | S15: =IF(OR(Progetti!E13="",Progetti!AB13=""),"",Progetti!AB13) | T15: =IF(OR(Progetti!E13="",Progetti!AC13=""),"",Progetti!AC13) | U15: =IF(OR(Progetti!E13="",Progetti!AD13=""),"",Progetti!AD13) | V15: =IF(OR(Progetti!E13="",Progetti!AE13=""),"",Progetti!AE13) | W15: =IF(OR(Progetti!E13="",Progetti!AF13=""),"",Progetti!AF13) | X15: =IF(OR(Progetti!E13="",Progetti!AG13=""),"",Progetti!AG13)
A16: =IF(Progetti!E14="","",Progetti!A14) -> Catania | B16: =IF(Progetti!F14="","",Progetti!B14) -> Sud | C16: =IF(Progetti!E14="","",Progetti!C14) -> IBVI 5 SRL | D16: =IF(Progetti!F14="","",Progetti!D14) -> 0 | E16: =IF(Progetti!E14="","",Progetti!E14) -> Castel di Iudica II | F16: =IF(Progetti!K14="","",Progetti!K14) | G16: =IF(Progetti!L14="","",Progetti!L14) | H16: =IF(Progetti!E14="","",Progetti!N14) -> Autorizzazioni | I16: =IF(Progetti!E14="","",Progetti!M14) -> In pipeline | J16: =IF(Progetti!E14="","",Progetti!I14) -> 231.6 | K16: =IF(OR(Progetti!E14="",Progetti!Q14=""),"",Progetti!Q14) | L16: =IF(OR(Progetti!E14="",Progetti!R14=""),"",Progetti!R14) -> 45923 | M16: =IF(OR(Progetti!E14="",Progetti!V14=""),"",Progetti!V14) | N16: =IF(OR(Progetti!E14="",Progetti!W14=""),"",Progetti!W14) | O16: =IF(OR(Progetti!E14="",Progetti!X14=""),"",Progetti!X14) | P16: =IF(OR(Progetti!E14="",Progetti!Y14=""),"",Progetti!Y14) | Q16: =IF(OR(Progetti!E14="",Progetti!Z14=""),"",Progetti!Z14) -> 45923 | R16: =IF(OR(Progetti!E14="",Progetti!AA14=""),"",Progetti!AA14) -> 46142 | S16: =IF(OR(Progetti!E14="",Progetti!AB14=""),"",Progetti!AB14) | T16: =IF(OR(Progetti!E14="",Progetti!AC14=""),"",Progetti!AC14) | U16: =IF(OR(Progetti!E14="",Progetti!AD14=""),"",Progetti!AD14) | V16: =IF(OR(Progetti!E14="",Progetti!AE14=""),"",Progetti!AE14) | W16: =IF(OR(Progetti!E14="",Progetti!AF14=""),"",Progetti!AF14) | X16: =IF(OR(Progetti!E14="",Progetti!AG14=""),"",Progetti!AG14)
A17: =IF(Progetti!E15="","",Progetti!A15) -> Catania | B17: =IF(Progetti!F15="","",Progetti!B15) -> Sud | C17: =IF(Progetti!E15="","",Progetti!C15) -> IBVI 22 SRL | D17: =IF(Progetti!F15="","",Progetti!D15) -> 0 | E17: =IF(Progetti!E15="","",Progetti!E15) -> Mineo | F17: =IF(Progetti!K15="","",Progetti!K15) | G17: =IF(Progetti!L15="","",Progetti!L15) | H17: =IF(Progetti!E15="","",Progetti!N15) -> Autorizzazioni | I17: =IF(Progetti!E15="","",Progetti!M15) -> In pipeline | J17: =IF(Progetti!E15="","",Progetti!I15) -> 263 | K17: =IF(OR(Progetti!E15="",Progetti!Q15=""),"",Progetti!Q15) | L17: =IF(OR(Progetti!E15="",Progetti!R15=""),"",Progetti!R15) -> 46092 | M17: =IF(OR(Progetti!E15="",Progetti!V15=""),"",Progetti!V15) | N17: =IF(OR(Progetti!E15="",Progetti!W15=""),"",Progetti!W15) | O17: =IF(OR(Progetti!E15="",Progetti!X15=""),"",Progetti!X15) | P17: =IF(OR(Progetti!E15="",Progetti!Y15=""),"",Progetti!Y15) | Q17: =IF(OR(Progetti!E15="",Progetti!Z15=""),"",Progetti!Z15) -> 46092 | R17: =IF(OR(Progetti!E15="",Progetti!AA15=""),"",Progetti!AA15) -> 46265 | S17: =IF(OR(Progetti!E15="",Progetti!AB15=""),"",Progetti!AB15) | T17: =IF(OR(Progetti!E15="",Progetti!AC15=""),"",Progetti!AC15) | U17: =IF(OR(Progetti!E15="",Progetti!AD15=""),"",Progetti!AD15) | V17: =IF(OR(Progetti!E15="",Progetti!AE15=""),"",Progetti!AE15) | W17: =IF(OR(Progetti!E15="",Progetti!AF15=""),"",Progetti!AF15) | X17: =IF(OR(Progetti!E15="",Progetti!AG15=""),"",Progetti!AG15)
A18: =IF(Progetti!E16="","",Progetti!A16) -> Catania | B18: =IF(Progetti!F16="","",Progetti!B16) -> Sud | C18: =IF(Progetti!E16="","",Progetti!C16) -> ENNA 1 PV SRL | D18: =IF(Progetti!F16="","",Progetti!D16) -> 0 | E18: =IF(Progetti!E16="","",Progetti!E16) -> Enna 1 | F18: =IF(Progetti!K16="","",Progetti!K16) | G18: =IF(Progetti!L16="","",Progetti!L16) | H18: =IF(Progetti!E16="","",Progetti!N16) -> Autorizzazioni | I18: =IF(Progetti!E16="","",Progetti!M16) -> In pipeline | J18: =IF(Progetti!E16="","",Progetti!I16) -> 45 | K18: =IF(OR(Progetti!E16="",Progetti!Q16=""),"",Progetti!Q16) | L18: =IF(OR(Progetti!E16="",Progetti!R16=""),"",Progetti!R16) -> 46086 | M18: =IF(OR(Progetti!E16="",Progetti!V16=""),"",Progetti!V16) | N18: =IF(OR(Progetti!E16="",Progetti!W16=""),"",Progetti!W16) | O18: =IF(OR(Progetti!E16="",Progetti!X16=""),"",Progetti!X16) | P18: =IF(OR(Progetti!E16="",Progetti!Y16=""),"",Progetti!Y16) | Q18: =IF(OR(Progetti!E16="",Progetti!Z16=""),"",Progetti!Z16) -> 46086 | R18: =IF(OR(Progetti!E16="",Progetti!AA16=""),"",Progetti!AA16) -> 46265 | S18: =IF(OR(Progetti!E16="",Progetti!AB16=""),"",Progetti!AB16) | T18: =IF(OR(Progetti!E16="",Progetti!AC16=""),"",Progetti!AC16) | U18: =IF(OR(Progetti!E16="",Progetti!AD16=""),"",Progetti!AD16) | V18: =IF(OR(Progetti!E16="",Progetti!AE16=""),"",Progetti!AE16) | W18: =IF(OR(Progetti!E16="",Progetti!AF16=""),"",Progetti!AF16) | X18: =IF(OR(Progetti!E16="",Progetti!AG16=""),"",Progetti!AG16)
... A206: =IF(Progetti!E204="","",Progetti!A204) | B206: =IF(Progetti!F204="","",Progetti!B204) | C206: =IF(Progetti!E204="","",Progetti!C204) | D206: =IF(Progetti!F204="","",Progetti!D204) | E206: =IF(Progetti!E204="","",Progetti!E204) | F206: =IF(Progetti!K204="","",Progetti!K204) | G206: =IF(Progetti!L204="","",Progetti!L204) | H206: =IF(Progetti!E204="","",Progetti!N204) | I206: =IF(Progetti!E204="","",Progetti!M204) | J206: =IF(Progetti!E204="","",Progetti!I204) | K206: =IF(OR(Progetti!E204="",Progetti!Q204=""),"",Progetti!Q204) | L206: =IF(OR(Progetti!E204="",Progetti!R204=""),"",Progetti!R204) | M206: =IF(OR(Progetti!E204="",Progetti!V204=""),"",Progetti!V204) | N206: =IF(OR(Progetti!E204="",Progetti!W204=""),"",Progetti!W204) | O206: =IF(OR(Progetti!E204="",Progetti!X204=""),"",Progetti!X204) | P206: =IF(OR(Progetti!E204="",Progetti!Y204=""),"",Progetti!Y204) | Q206: =IF(OR(Progetti!E204="",Progetti!Z204=""),"",Progetti!Z204) | R206: =IF(OR(Progetti!E204="",Progetti!AA204=""),"",Progetti!AA204) | S206: =IF(OR(Progetti!E204="",Progetti!AB204=""),"",Progetti!AB204) | T206: =IF(OR(Progetti!E204="",Progetti!AC204=""),"",Progetti!AC204) | U206: =IF(OR(Progetti!E204="",Progetti!AD204=""),"",Progetti!AD204) | V206: =IF(OR(Progetti!E204="",Progetti!AE204=""),"",Progetti!AE204) | W206: =IF(OR(Progetti!E204="",Progetti!AF204=""),"",Progetti!AF204) | X206: =IF(OR(Progetti!E204="",Progetti!AG204=""),"",Progetti!AG204)

Sheet GeoListe
A1: Regioni | B1: Abruzzo | C1: Basilicata | D1: Calabria | E1: Campania | F1: Emilia-Romagna | G1: Friuli-Venezia Giulia | H1: Lazio | I1: Liguria | J1: Lombardia | K1: Marche | L1: Molise | M1: Piemonte | N1: Puglia | O1: Sardegna | P1: Sicilia | Q1: Toscana | R1: Trentino-Alto Adige/Südtirol | S1: Umbria | T1: Valle d'Aosta/Vallée d'Aoste | U1: Veneto
A2: Abruzzo | B2: Chieti | C2: Matera | D2: Catanzaro | E2: Avellino | F2: Bologna | G2: Gorizia | H2: Frosinone | I2: Genova | J2: Bergamo | K2: Ancona | L2: Campobasso | M2: Alessandria | N2: Bari | O2: Cagliari | P2: Agrigento | Q2: Arezzo | R2: Bolzano/Bozen | S2: Perugia | T2: Valle d'Aosta/Vallée d'Aoste | U2: Belluno
A3: Basilicata | B3: L'Aquila | C3: Potenza | D3: Cosenza | E3: Benevento | F3: Ferrara | G3: Pordenone | H3: Latina | I3: Imperia | J3: Brescia | K3: Ascoli Piceno | L3: Isernia | M3: Asti | N3: Barletta-Andria-Trani | O3: Nuoro | P3: Caltanissetta | Q3: Firenze | R3: Trento | S3: Terni | U3: Padova
A4: Calabria | B4: Pescara | D4: Crotone | E4: Caserta | F4: Forlì-Cesena | G4: Trieste | H4: Rieti | I4: La Spezia | J4: Como | K4: Fermo | M4: Biella | N4: Brindisi | O4: Oristano | P4: Catania | Q4: Grosseto | U4: Rovigo
A5: Campania | B5: Teramo | D5: Reggio Calabria | E5: Napoli | F5: Modena | G5: Udine | H5: Roma | I5: Savona | J5: Cremona | K5: Macerata | M5: Cuneo | N5: Foggia | O5: Sassari | P5: Enna | Q5: Livorno | U5: Treviso
A6: Emilia-Romagna | D6: Vibo Valentia | E6: Salerno | F6: Parma | H6: Viterbo | J6: Lecco | K6: Pesaro e Urbino | M6: Novara | N6: Lecce | O6: Sud Sardegna | P6: Messina | Q6: Lucca | U6: Venezia
A7: Friuli-Venezia Giulia | F7: Piacenza | J7: Lodi | M7: Torino | N7: Taranto | P7: Palermo | Q7: Massa-Carrara | U7: Verona
A8: Lazio | F8: Ravenna | J8: Mantova | M8: Verbano-Cusio-Ossola | P8: Ragusa | Q8: Pisa | U8: Vicenza
A9: Liguria | F9: Reggio nell'Emilia | J9: Milano | M9: Vercelli | P9: Siracusa | Q9: Pistoia
A10: Lombardia | F10: Rimini | J10: Monza e della Brianza | P10: Trapani | Q10: Prato
A11: Marche | J11: Pavia | Q11: Siena
A12: Molise | J12: Sondrio
A13: Piemonte | J13: Varese
A14: Puglia
A15: Sardegna
A16: Sicilia
A17: Toscana
A18: Trentino-Alto Adige/Südtirol
A19: Umbria
A20: Valle d'Aosta/Vallée d'Aoste
A21: Veneto

Sheet GeoComuni
A1: Regione | B1: Provincia | C1: Comune | E1: Fonte
A2: Abruzzo | B2: Chieti | C2: Altino | E2: https://www.istat.it/storage/codici-unita-amministrative/Elenco-comuni-italiani.csv
A3: Abruzzo | B3: Chieti | C3: Archi | E3: Scaricato il 2026-03-15
A4: Abruzzo | B4: Chieti | C4: Ari
A5: Abruzzo | B5: Chieti | C5: Arielli
A6: Abruzzo | B6: Chieti | C6: Atessa
A7: Abruzzo | B7: Chieti | C7: Bomba
A8: Abruzzo | B8: Chieti | C8: Borrello
A9: Abruzzo | B9: Chieti | C9: Bucchianico
A10: Abruzzo | B10: Chieti | C10: Canosa Sannita
A11: Abruzzo | B11: Chieti | C11: Carpineto Sinello
A12: Abruzzo | B12: Chieti | C12: Carunchio
A13: Abruzzo | B13: Chieti | C13: Casacanditella
A14: Abruzzo | B14: Chieti | C14: Casalanguida
A15: Abruzzo | B15: Chieti | C15: Casalbordino
... A7896: Veneto | B7896: Vicenza | C7896: Zugliano

Sheet GeoDropdown
A1: Agrigento | B1: Alessandria | C1: Ancona | D1: Arezzo | E1: Ascoli Piceno | F1: Asti | G1: Avellino | H1: Bari | I1: Barletta-Andria-Trani | J1: Belluno | K1: Benevento | L1: Bergamo | M1: Biella | N1: Bologna | O1: Bolzano/Bozen | P1: Brescia | Q1: Brindisi | R1: Cagliari | S1: Caltanissetta | T1: Campobasso | U1: Caserta | V1: Catania | W1: Catanzaro | X1: Chieti | Y1: Como | Z1: Cosenza | AA1: Cremona | AB1: Crotone | AC1: Cuneo | AD1: Enna | AE1: Fermo | AF1: Ferrara | AG1: Firenze | AH1: Foggia | AI1: Forlì-Cesena | AJ1: Frosinone | AK1: Genova | AL1: Gorizia | AM1: Grosseto | AN1: Imperia | AO1: Isernia | AP1: L'Aquila | AQ1: La Spezia | AR1: Latina | AS1: Lecce | AT1: Lecco | AU1: Livorno | AV1: Lodi | AW1: Lucca | AX1: Macerata | AY1: Mantova | AZ1: Massa-Carrara | BA1: Matera | BB1: Messina | BC1: Milano | BD1: Modena | BE1: Monza e della Brianza | BF1: Napoli | BG1: Novara | BH1: Nuoro | BI1: Oristano | BJ1: Padova | BK1: Palermo | BL1: Parma | BM1: Pavia | BN1: Perugia | BO1: Pesaro e Urbino | BP1: Pescara | BQ1: Piacenza | BR1: Pisa | BS1: Pistoia | BT1: Pordenone | BU1: Potenza | BV1: Prato | BW1: Ragusa | BX1: Ravenna | BY1: Reggio Calabria | BZ1: Reggio nell'Emilia | CA1: Rieti | CB1: Rimini | CC1: Roma | CD1: Rovigo | CE1: Salerno | CF1: Sassari | CG1: Savona | CH1: Siena | CI1: Siracusa | CJ1: Sondrio | CK1: Sud Sardegna | CL1: Taranto | CM1: Teramo | CN1: Terni | CO1: Torino | CP1: Trapani | CQ1: Trento | CR1: Treviso | CS1: Trieste | CT1: Udine | CU1: Valle d'Aosta/Vallée d'Aoste | CV1: Varese | CW1: Venezia | CX1: Verbano-Cusio-Ossola | CY1: Vercelli | CZ1: Verona | DA1: Vibo Valentia | DB1: Vicenza | DC1: Viterbo
A2: Agrigento | B2: Acqui Terme | C2: Agugliano | D2: Anghiari | E2: Acquasanta Terme | F2: Agliano Terme | G2: Aiello del Sabato | H2: Acquaviva delle Fonti | I2: Andria | J2: Agordo | K2: Airola | L2: Adrara San Martino | M2: Ailoche | N2: Alto Reno Terme | O2: Aldino/Aldein | P2: Acquafredda | Q2: Brindisi | R2: Assemini | S2: Acquaviva Platani | T2: Acquaviva Collecroce | U2: Ailano | V2: Aci Bonaccorsi | W2: Albi | X2: Altino | Y2: Albavilla | Z2: Acquaformosa | AA2: Acquanegra Cremonese | AB2: Belvedere di Spinello | AC2: Acceglio | AD2: Agira | AE2: Altidona | AF2: Argenta | AG2: Bagno a Ripoli | AH2: Accadia | AI2: Bagno di Romagna | AJ2: Acquafondata | AK2: Arenzano | AL2: Capriva del Friuli | AM2: Arcidosso | AN2: Airole | AO2: Acquaviva d'Isernia | AP2: Acciano | AQ2: Ameglia | AR2: Aprilia | AS2: Alessano | AT2: Abbadia Lariana | AU2: Bibbona | AV2: Abbadia Cerreto | AW2: Altopascio | AX2: Apiro | AY2: Acquanegra sul Chiese | AZ2: Aulla | BA2: Accettura | BB2: Acquedolci | BC2: Abbiategrasso | BD2: Bastiglia | BE2: Agrate Brianza | BF2: Acerra | BG2: Agrate Conturbia | BH2: Aritzo | BI2: Abbasanta | BJ2: Abano Terme | BK2: Alia | BL2: Albareto | BM2: Alagna | BN2: Assisi | BO2: Acqualagna | BP2: Abbateggio | BQ2: Agazzano | BR2: Bientina | BS2: Abetone Cutigliano | BT2: Andreis | BU2: Abriola | BV2: Cantagallo | BW2: Acate | BX2: Alfonsine | BY2: Africo | BZ2: Albinea | CA2: Accumoli | CB2: Bellaria-Igea Marina | CC2: Affile | CD2: Adria | CE2: Acerno | CF2: Aggius | CG2: Alassio | CH2: Abbadia San Salvatore | CI2: Augusta | CJ2: Albaredo per San Marco | CK2: Arbus | CL2: Avetrana | CM2: Alba Adriatica | CN2: Acquasparta | CO2: Agliè | CP2: Alcamo | CQ2: Ala | CR2: Altivole | CS2: Duino Aurisina-Devin Nabreina | CT2: Aiello del Friuli | CU2: Allein | CV2: Agra | CW2: Annone Veneto | CX2: Antrona Schieranco | CY2: Alagna Valsesia | CZ2: Affi | DA2: Acquaro | DB2: Agugliaro | DC2: Acquapendente
A3: Alessandria della Rocca | B3: Albera Ligure | C3: Ancona | D3: Arezzo | E3: Acquaviva Picena | F3: Albugnano | G3: Altavilla Irpina | H3: Adelfia | I3: Barletta | J3: Alleghe | K3: Amorosi | L3: Adrara San Rocco | M3: Andorno Micca | N3: Anzola dell'Emilia | O3: Andriano/Andrian | P3: Adro | Q3: Carovigno | R3: Cagliari | S3: Bompensiere | T3: Baranello | U3: Alife | V3: Aci Castello | W3: Amaroni | X3: Archi | Y3: Albese con Cassano | Z3: Acquappesa | AA3: Agnadello | AB3: Caccuri | AC3: Aisone | AD3: Aidone | AE3: Amandola | AF3: Bondeno | AG3: Barberino Tavarnelle | AH3: Alberona | AI3: Bertinoro | AJ3: Acuto | AK3: Avegno | AL3: Cormons | AM3: Campagnatico | AN3: Apricale | AO3: Agnone | AP3: Aielli | AQ3: Arcola | AR3: Bassiano | AS3: Alezio | AT3: Airuno | AU3: Campiglia Marittima | AV3: Bertonico | AW3: Bagni di Lucca | AX3: Appignano | AY3: Asola | AZ3: Bagnone | BA3: Aliano | BB3: Alcara li Fusi | BC3: Albairate | BD3: Bomporto | BE3: Aicurzio | BF3: Afragola | BG3: Ameno | BH3: Arzana | BI3: Aidomaggiore | BJ3: Agna | BK3: Alimena | BL3: Bardi | BM3: Albonese | BN3: Bastia Umbra | BO3: Apecchio | BP3: Alanno | BQ3: Alseno | BR3: Buti | BS3: Agliana | BT3: Arba | BU3: Acerenza | BV3: Carmignano | BW3: Chiaramonte Gulfi | BX3: Bagnacavallo | BY3: Agnana Calabra | BZ3: Bagnolo in Piano | CA3: Amatrice | CB3: Casteldelci | CC3: Agosta | CD3: Ariano nel Polesine | CE3: Agropoli | CF3: Aglientu | CG3: Albenga | CH3: Asciano | CI3: Avola | CJ3: Albosaggia | CK3: Armungia | CL3: Carosino | CM3: Ancarano | CN3: Allerona | CO3: Airasca | CP3: Buseto Palizzolo | CQ3: Albiano | CR3: Arcade | CS3: Monrupino-Repentabor | CT3: Amaro | CU3: Antey-Saint-André | CV3: Albizzate | CW3: Campagna Lupia | CX3: Anzola d'Ossola | CY3: Albano Vercellese | CZ3: Albaredo d'Adige | DA3: Arena | DB3: Albettone | DC3: Arlena di Castro
A4: Aragona | B4: Alessandria | C4: Arcevia | D4: Badia Tedalda | E4: Appignano del Tronto | F4: Antignano | G4: Andretta | H4: Alberobello | I4: Bisceglie | J4: Alpago | K4: Apice | L4: Albano Sant'Alessandro | M4: Benna | N4: Argelato | O4: Anterivo/Altrei | P4: Agnosine | Q4: Ceglie Messapica | R4: Capoterra | S4: Butera | T4: Bojano | U4: Alvignano | V4: Aci Catena | W4: Amato | X4: Ari | Y4: Albiolo | Z4: Acri | AA4: Annicco | AB4: Carfizzi | AC4: Alba | AD4: Assoro | AE4: Belmonte Piceno | AF4: Cento | AG4: Barberino di Mugello | AH4: Anzano di Puglia | AI4: Borghi | AJ4: Alatri | AK4: Bargagli | AL4: Doberdò del Lago-Doberdob | AM4: Capalbio | AN4: Aquila d'Arroscia | AO4: Bagnoli del Trigno | AP4: Alfedena | AQ4: Beverino | AR4: Campodimele | AS4: Alliste | AT4: Annone di Brianza | AU4: Campo nell'Elba | AV4: Boffalora d'Adda | AW4: Barga | AX4: Belforte del Chienti | AY4: Bagnolo San Vito | AZ4: Carrara | BA4: Bernalda | BB4: Alì | BC4: Arconate | BD4: Campogalliano | BE4: Albiate | BF4: Agerola | BG4: Armeno | BH4: Atzara | BI4: Albagiara | BJ4: Albignasego | BK4: Aliminusa | BL4: Bedonia | BM4: Albuzzano | BN4: Bettona | BO4: Belforte all'Isauro | BP4: Bolognano | BQ4: Alta Val Tidone | BR4: Calci | BS4: Buggiano | BT4: Aviano | BU4: Albano di Lucania | BV4: Montemurlo | BW4: Comiso | BX4: Bagnara di Romagna | BY4: Anoia | BZ4: Baiso | CA4: Antrodoco | CB4: Cattolica | CC4: Albano Laziale | CD4: Arquà Polesine | CE4: Albanella | CF4: Alghero | CG4: Albisola Superiore | CH4: Buonconvento | CI4: Buccheri | CJ4: Andalo Valtellino | CK4: Ballao | CL4: Castellaneta | CM4: Arsita | CN4: Alviano | CO4: Ala di Stura | CP4: Calatafimi-Segesta | CQ4: Aldeno | CR4: Asolo | CS4: Muggia | CT4: Ampezzo | CU4: Aosta | CV4: Angera | CW4: Campolongo Maggiore | CX4: Arizzano | CY4: Alice Castello | CZ4: Angiari | DA4: Briatico | DB4: Alonte | DC4: Bagnoregio
A5: Bivona | B5: Alfiano Natta | C5: Barbara | D5: Bibbiena | E5: Arquata del Tronto | F5: Aramengo | G5: Aquilonia | H5: Altamura | I5: Canosa di Puglia | J5: Arsiè | K5: Apollosa | L5: Albino | M5: Biella | N5: Baricella | O5: Appiano sulla strada del vino/Eppan an der Weinstraße | P5: Alfianello | Q5: Cellino San Marco | R5: Decimomannu | S5: Caltanissetta | T5: Bonefro | U5: Arienzo | V5: Aci Sant'Antonio | W5: Andali | X5: Arielli | Y5: Alserio | Z5: Aiello Calabro | AA5: Azzanello | AB5: Casabona | AC5: Albaretto della Torre | AD5: Barrafranca | AE5: Campofilone | AF5: Codigoro | AG5: Borgo San Lorenzo | AH5: Apricena | AI5: Castrocaro Terme e Terra del Sole | AJ5: Alvito | AK5: Bogliasco | AL5: Dolegna del Collio | AM5: Castel del Piano | AN5: Armo | AO5: Belmonte del Sannio | AP5: Anversa degli Abruzzi | AQ5: Bolano | AR5: Castelforte | AS5: Andrano | AT5: Ballabio | AU5: Capoliveri | AV5: Borghetto Lodigiano | AW5: Borgo a Mozzano | AX5: Bolognola | AY5: Borgo Mantovano | AZ5: Casola in Lunigiana | BA5: Calciano | BB5: Alì Terme | BC5: Arese | BD5: Camposanto | BE5: Arcore | BF5: Anacapri | BG5: Arona | BH5: Austis | BI5: Ales | BJ5: Anguillara Veneta | BK5: Altavilla Milicia | BL5: Berceto | BM5: Arena Po | BN5: Bevagna | BO5: Borgo Pace | BP5: Brittoli | BQ5: Besenzone | BR5: Calcinaia | BS5: Chiesina Uzzanese | BT5: Azzano Decimo | BU5: Anzi | BV5: Poggio a Caiano | BW5: Giarratana | BX5: Brisighella | BY5: Antonimina | BZ5: Bibbiano | CA5: Ascrea | CB5: Coriano | CC5: Allumiere | CD5: Badia Polesine | CE5: Alfano | CF5: Alà dei Sardi | CG5: Albissola Marina | CH5: Casole d'Elsa | CI5: Buscemi | CJ5: Aprica | CK5: Barrali | CL5: Crispiano | CM5: Atri | CN5: Amelia | CO5: Albiano d'Ivrea | CP5: Campobello di Mazara | CQ5: Altavalle | CR5: Borso del Grappa | CS5: San Dorligo della Valle-Dolina | CT5: Aquileia | CU5: Arnad | CV5: Arcisate | CW5: Camponogara | CX5: Arola | CY5: Alto Sermenza | CZ5: Arcole | DA5: Brognaturo | DB5: Altavilla Vicentina | DC5: Barbarano Romano
A6: Burgio | B6: Alice Bel Colle | C6: Belvedere Ostrense | D6: Bucine | E6: Ascoli Piceno | F6: Asti | G6: Ariano Irpino | H6: Bari | I6: Margherita di Savoia | J6: Auronzo di Cadore | K6: Arpaia | L6: Algua | M6: Bioglio | N6: Bentivoglio | O6: Avelengo/Hafling | P6: Anfo | Q6: Cisternino | R6: Elmas | S6: Campofranco | T6: Busso | U6: Aversa | V6: Acireale | W6: Argusto | X6: Atessa | Y6: Alta Valle Intelvi | Z6: Aieta | AA6: Bagnolo Cremasco | AB6: Castelsilano | AC6: Alto | AD6: Calascibetta | AE6: Falerone | AF6: Comacchio | AG6: Calenzano | AH6: Ascoli Satriano | AI6: Cesena | AJ6: Amaseno | AK6: Borzonasca | AL6: Farra d'Isonzo | AM6: Castell'Azzara | AN6: Aurigo | AO6: Cantalupo nel Sannio | AP6: Ateleta | AQ6: Bonassola | AR6: Cisterna di Latina | AS6: Aradeo | AT6: Barzago | AU6: Capraia Isola | AV6: Borgo San Giovanni | AW6: Camaiore | AX6: Caldarola | AY6: Borgo Virgilio | AZ6: Comano | BA6: Cirigliano | BB6: Antillo | BC6: Arluno | BD6: Carpi | BE6: Barlassina | BF6: Arzano | BG6: Barengo | BH6: Bari Sardo | BI6: Allai | BJ6: Arquà Petrarca | BK6: Altofonte | BL6: Bore | BM6: Badia Pavese | BN6: Campello sul Clitunno | BO6: Cagli | BP6: Bussi sul Tirino | BQ6: Bettola | BR6: Capannoli | BS6: Lamporecchio | BT6: Barcis | BU6: Armento | BV6: Prato | BW6: Ispica | BX6: Casola Valsenio | BY6: Ardore | BZ6: Boretto | CA6: Belmonte in Sabina | CB6: Gemmano | CC6: Anguillara Sabazia | CD6: Bagnolo di Po | CE6: Altavilla Silentina | CF6: Anela | CG6: Altare | CH6: Castellina in Chianti | CI6: Canicattini Bagni | CJ6: Ardenno | CK6: Barumini | CL6: Faggiano | CM6: Basciano | CN6: Arrone | CO6: Almese | CP6: Castellammare del Golfo | CQ6: Altopiano della Vigolana | CR6: Breda di Piave | CS6: Sgonico-Zgonik | CT6: Arta Terme | CU6: Arvier | CV6: Arsago Seprio | CW6: Caorle | CX6: Aurano | CY6: Arborio | CZ6: Badia Calavena | DA6: Capistrano | DB6: Altissimo | DC6: Bassano Romano
A7: Calamonaci | B7: Alluvioni Piovera | C7: Camerano | D7: Capolona | E7: Carassai | F7: Azzano d'Asti | G7: Atripalda | H7: Binetto | I7: Minervino Murge | J7: Belluno | K7: Arpaise | L7: Almenno San Bartolomeo | M7: Borriana | N7: Bologna | O7: Badia/Abtei | P7: Angolo Terme | Q7: Erchie | R7: Maracalagonis | S7: Delia | T7: Campobasso | U7: Baia e Latina | V7: Adrano | W7: Badolato | X7: Bomba | Y7: Alzate Brianza | Z7: Albidona | AA7: Bonemerse | AB7: Cerenzia | AC7: Argentera | AD7: Catenanuova | AE7: Fermo | AF7: Copparo | AG7: Campi Bisenzio | AH7: Biccari | AI7: Cesenatico | AJ7: Anagni | AK7: Busalla | AL7: Fogliano Redipuglia | AM7: Castiglione della Pescaia | AN7: Badalucco | AO7: Capracotta | AP7: Avezzano | AQ7: Borghetto di Vara | AR7: Cori | AS7: Arnesano | AT7: Barzanò | AU7: Castagneto Carducci | AV7: Brembio | AW7: Camporgiano | AX7: Camerino | AY7: Borgocarbonara | AZ7: Filattiera | BA7: Colobraro | BB7: Barcellona Pozzo di Gotto | BC7: Assago | BD7: Castelfranco Emilia | BE7: Bellusco | BF7: Bacoli | BG7: Bellinzago Novarese | BH7: Baunei | BI7: Arborea | BJ7: Arre | BK7: Bagheria | BL7: Borgo Val di Taro | BM7: Bagnaria | BN7: Cannara | BO7: Cantiano | BP7: Cappelle sul Tavo | BQ7: Bobbio | BR7: Casale Marittimo | BS7: Larciano | BT7: Brugnera | BU7: Atella | BV7: Vaiano | BW7: Modica | BX7: Castel Bolognese | BY7: Bagaladi | BZ7: Brescello | CA7: Borbona | CB7: Maiolo | CC7: Anticoli Corrado | CD7: Bergantino | CE7: Amalfi | CF7: Ardara | CG7: Andora | CH7: Castelnuovo Berardenga | CI7: Carlentini | CJ7: Bema | CK7: Buggerru | CL7: Fragagnano | CM7: Bellante | CN7: Attigliano | CO7: Alpette | CP7: Castelvetrano | CQ7: Amblar-Don | CR7: Caerano di San Marco | CS7: Trieste | CT7: Artegna | CU7: Avise | CV7: Azzate | CW7: Cavallino-Treporti | CX7: Baceno | CY7: Asigliano Vercellese | CZ7: Bardolino | DA7: Cessaniti | DB7: Arcugnano | DC7: Bassano in Teverina
A8: Caltabellotta | B8: Altavilla Monferrato | C8: Camerata Picena | D8: Caprese Michelangelo | E8: Castel di Lama | F8: Baldichieri d'Asti | G8: Avella | H8: Bitetto | I8: San Ferdinando di Puglia | J8: Borca di Cadore | K8: Baselice | L8: Almenno San Salvatore | M8: Brusnengo | N8: Borgo Tossignano | O8: Barbiano/Barbian | P8: Artogne | Q8: Fasano | R8: Monserrato | S8: Gela | T8: Campochiaro | U8: Bellona | V8: Belpasso | W8: Belcastro | X8: Borrello | Y8: Anzano del Parco | Z8: Alessandria del Carretto | AA8: Bordolano | AB8: Cirò | AC8: Arguello | AD8: Centuripe | AE8: Francavilla d'Ete | AF8: Ferrara | AG8: Capraia e Limite | AH8: Bovino | AI8: Civitella di Romagna | AJ8: Aquino | AK8: Camogli | AL8: Gorizia | AM8: Cinigiano | AN8: Bajardo | AO8: Carovilli | AP8: Balsorano | AQ8: Brugnato | AR8: Fondi | AS8: Bagnolo del Salento | AT8: Barzio | AU8: Cecina | AV8: Casaletto Lodigiano | AW8: Capannori | AX8: Camporotondo di Fiastrone | AY8: Bozzolo | AZ8: Fivizzano | BA8: Craco | BB8: Basicò | BC8: Baranzate | BD8: Castelnuovo Rangone | BE8: Bernareggio | BF8: Barano d'Ischia | BG8: Biandrate | BH8: Belvì | BI8: Ardauli | BJ8: Arzergrande | BK8: Balestrate | BL8: Busseto | BM8: Barbianello | BN8: Cascia | BO8: Carpegna | BP8: Caramanico Terme | BQ8: Borgonovo Val Tidone | BR8: Casciana Terme Lari | BS8: Marliana | BT8: Budoia | BU8: Avigliano | BV8: Vernio | BW8: Monterosso Almo | BX8: Cervia | BY8: Bagnara Calabra | BZ8: Cadelbosco di Sopra | CA8: Borgo Velino | CB8: Misano Adriatico | CC8: Anzio | CD8: Bosaro | CE8: Angri | CF8: Arzachena | CG8: Arnasco | CH8: Castiglione d'Orcia | CI8: Cassaro | CJ8: Berbenno di Valtellina | CK8: Burcei | CL8: Ginosa | CM8: Bisenti | CN8: Avigliano Umbro | CO8: Alpignano | CP8: Custonaci | CQ8: Andalo | CR8: Cappella Maggiore | CT8: Attimis | CU8: Ayas | CV8: Azzio | CW8: Cavarzere | CX8: Bannio Anzino | CY8: Balmuccia | CZ8: Belfiore | DA8: Dasà | DB8: Arsiero | DC8: Blera
A9: Camastra | B9: Alzano Scrivia | C9: Castelbellino | D9: Castel Focognano | E9: Castignano | F9: Belveglio | G9: Avellino | H9: Bitonto | I9: Spinazzola | J9: Borgo Valbelluna | K9: Benevento | L9: Almè | M9: Callabiana | N9: Budrio | O9: Bolzano/Bozen | P9: Azzano Mella | Q9: Francavilla Fontana | R9: Pula | S9: Marianopoli | T9: Campodipietra | U9: Caianello | V9: Biancavilla | W9: Borgia | X9: Bucchianico | Y9: Appiano Gentile | Z9: Altilia | AA9: Calvatone | AB9: Cirò Marina | AC9: Bagnasco | AD9: Cerami | AE9: Grottazzolina | AF9: Fiscaglia | AG9: Castelfiorentino | AH9: Cagnano Varano | AI9: Dovadola | AJ9: Arce | AK9: Campo Ligure | AL9: Gradisca d'Isonzo | AM9: Civitella Paganico | AN9: Bordighera | AO9: Carpinone | AP9: Barete | AQ9: Calice al Cornoviglio | AR9: Formia | AS9: Botrugno | AT9: Bellano | AU9: Collesalvetti | AV9: Casalmaiocco | AW9: Careggine | AX9: Castelraimondo | AY9: Canneto sull'Oglio | AZ9: Fosdinovo | BA9: Ferrandina | BB9: Brolo | BC9: Bareggio | BD9: Castelvetro di Modena | BE9: Besana in Brianza | BF9: Boscoreale | BG9: Boca | BH9: Birori | BI9: Assolo | BJ9: Bagnoli di Sopra | BK9: Baucina | BL9: Calestano | BM9: Bascapè | BN9: Castel Ritaldi | BO9: Cartoceto | BP9: Carpineto della Nora | BQ9: Cadeo | BR9: Cascina | BS9: Massa e Cozzile | BT9: Caneva | BU9: Balvano | BW9: Pozzallo | BX9: Conselice | BY9: Benestare | BZ9: Campagnola Emilia | CA9: Borgorose | CB9: Mondaino | CC9: Arcinazzo Romano | CD9: Calto | CE9: Aquara | CF9: Badesi | CG9: Balestrino | CH9: Cetona | CI9: Ferla | CJ9: Bianzone | CK9: Calasetta | CL9: Grottaglie | CM9: Campli | CN9: Baschi | CO9: Andezeno | CP9: Erice | CQ9: Arco | CR9: Carbonera | CT9: Bagnaria Arsa | CU9: Aymavilles | CV9: Barasso | CW9: Ceggia | CX9: Baveno | CY9: Balocco | CZ9: Bevilacqua | DA9: Dinami | DB9: Arzignano | DC9: Bolsena
A10: Cammarata | B10: Arquata Scrivia | C10: Castelfidardo | D10: Castel San Niccolò | E10: Castorano | F10: Berzano di San Pietro | G10: Bagnoli Irpino | H10: Bitritto | I10: Trani | J10: Calalzo di Cadore | K10: Bonea | L10: Alzano Lombardo | M10: Camandona | N10: Calderara di Reno | O10: Braies/Prags | P10: Bagnolo Mella | Q10: Latiano | R10: Quartu Sant'Elena | S10: Mazzarino | T10: Campolieto | U10: Caiazzo | V10: Bronte | W10: Botricello | X10: Canosa Sannita | Y10: Argegno | Z10: Altomonte | AA10: Camisano | AB10: Cotronei | AC10: Bagnolo Piemonte | AD10: Enna | AE10: Lapedona | AF10: Goro | AG10: Cerreto Guidi | AH10: Candela | AI10: Forlimpopoli | AJ10: Arnara | AK10: Campomorone | AL10: Grado | AM10: Follonica | AN10: Borghetto d'Arroscia | AO10: Castel San Vincenzo | AP10: Barisciano | AQ10: Carro | AR10: Gaeta | AS10: Calimera | AT10: Bosisio Parini | AU10: Livorno | AV10: Casalpusterlengo | AW10: Castelnuovo di Garfagnana | AX10: Castelsantangelo sul Nera | AY10: Casalmoro | AZ10: Licciana Nardi | BA10: Garaguso | BB10: Capizzi | BC10: Basiano | BD10: Cavezzo | BE10: Biassono | BF10: Boscotrecase | BG10: Bogogno | BH10: Bitti | BI10: Asuni | BJ10: Baone | BK10: Belmonte Mezzagno | BL10: Collecchio | BM10: Bastida Pancarana | BN10: Castiglione del Lago | BO10: Colli al Metauro | BP10: Castiglione a Casauria | BQ10: Calendasco | BR10: Castelfranco di Sotto | BS10: Monsummano Terme | BT10: Casarsa della Delizia | BU10: Banzi | BW10: Ragusa | BX10: Cotignola | BY10: Bianco | BZ10: Campegine | CA10: Cantalice | CB10: Montecopiolo | CC10: Ardea | CD10: Canaro | CE10: Ascea | CF10: Banari | CG10: Bardineto | CH10: Chianciano Terme | CI10: Floridia | CJ10: Bormio | CK10: Carbonia | CL10: Laterza | CM10: Canzano | CN10: Calvi dell'Umbria | CO10: Andrate | CP10: Favignana | CQ10: Avio | CR10: Casale sul Sile | CT10: Basiliano | CU10: Bard | CV10: Bardello con Malgesso e Bregano | CW10: Chioggia | CX10: Bee | CY10: Bianzè | CZ10: Bonavigo | DA10: Drapia | DB10: Asiago | DC10: Bomarzo
A11: Campobello di Licata | B11: Avolasca | C11: Castelleone di Suasa | D11: Castelfranco Piandiscò | E11: Colli del Tronto | F11: Bruno | G11: Baiano | H11: Capurso | I11: Trinitapoli | J11: Canale d'Agordo | K11: Bucciano | L11: Ambivere | M11: Camburzano | N11: Camugnano | O11: Brennero/Brenner | P11: Bagolino | Q11: Mesagne | R11: Quartucciu | S11: Milena | T11: Campomarino | U11: Calvi Risorta | V11: Calatabiano | W11: Caraffa di Catanzaro | X11: Carpineto Sinello | Y11: Arosio | Z11: Amantea | AA11: Campagnola Cremasca | AB11: Crotone | AC11: Baldissero d'Alba | AD11: Gagliano Castelferrato | AE11: Magliano di Tenna | AF11: Jolanda di Savoia | AG11: Certaldo | AH11: Carapelle | AI11: Forlì | AJ11: Arpino | AK11: Carasco | AL11: Mariano del Friuli | AM11: Gavorrano | AN11: Borgomaro | AO11: Castel del Giudice | AP11: Barrea | AQ11: Carrodano | AR11: Itri | AS11: Campi Salentina | AT11: Brivio | AU11: Marciana | AV11: Caselle Landi | AW11: Castiglione di Garfagnana | AX11: Cessapalombo | AY11: Casaloldo | AZ11: Massa | BA11: Gorgoglione | BB11: Capo d'Orlando | BC11: Basiglio | BD11: Concordia sulla Secchia | BE11: Bovisio-Masciago | BF11: Brusciano | BG11: Bolzano Novarese | BH11: Bolotana | BI11: Baradili | BJ11: Barbona | BK11: Bisacquino | BL11: Colorno | BM11: Battuda | BN11: Cerreto di Spoleto | BO11: Fano | BP11: Catignano | BQ11: Caorso | BR11: Castellina Marittima | BS11: Montale | BT11: Castelnovo del Friuli | BU11: Baragiano | BW11: Santa Croce Camerina | BX11: Faenza | BY11: Bivongi | BZ11: Canossa | CA11: Cantalupo in Sabina | CB11: Montefiore Conca | CC11: Ariccia | CD11: Canda | CE11: Atena Lucana | CF11: Benetutti | CG11: Bergeggi | CH11: Chiusdino | CI11: Francofonte | CJ11: Buglio in Monte | CK11: Carloforte | CL11: Leporano | CM11: Castel Castagna | CN11: Castel Giorgio | CO11: Angrogna | CP11: Gibellina | CQ11: Baselga di Pinè | CR11: Casier | CT11: Bertiolo | CU11: Bionaz | CV11: Bedero Valcuvia | CW11: Cinto Caomaggiore | CX11: Belgirate | CY11: Boccioleto | CZ11: Boschi Sant'Anna | DA11: Fabrizia | DB11: Asigliano Veneto | DC11: Calcata
A12: Canicattì | B12: Balzola | C12: Castelplanio | D12: Castiglion Fibocchi | E12: Comunanza | F12: Bubbio | G12: Bisaccia | H12: Casamassima | J12: Cencenighe Agordino | K12: Buonalbergo | L12: Antegnate | M12: Campiglia Cervo | N12: Casalecchio di Reno | O12: Bressanone/Brixen | P12: Barbariga | Q12: Oria | R12: Sarroch | S12: Montedoro | T12: Casacalenda | U12: Camigliano | V12: Caltagirone | W12: Cardinale | X12: Carunchio | Y12: Asso | Z12: Amendolara | AA12: Capergnanica | AB12: Crucoli | AC12: Barbaresco | AD12: Leonforte | AE12: Massa Fermana | AF12: Lagosanto | AG12: Dicomano | AH12: Carlantino | AI12: Galeata | AJ12: Atina | AK12: Casarza Ligure | AL12: Medea | AM12: Grosseto | AN12: Camporosso | AO12: Castelpetroso | AP12: Bisegna | AQ12: Castelnuovo Magra | AR12: Latina | AS12: Cannole | AT12: Bulciago | AU12: Marciana Marina | AV12: Caselle Lurani | AW12: Coreglia Antelminelli | AX12: Cingoli | AY12: Casalromano | AZ12: Montignoso | BA12: Grassano | BB12: Capri Leone | BC12: Bellinzago Lombardo | BD12: Fanano | BE12: Briosco | BF12: Caivano | BG12: Borgo Ticino | BH12: Borore | BI12: Baratili San Pietro | BJ12: Battaglia Terme | BK12: Blufi | BL12: Compiano | BM12: Belgioioso | BN12: Citerna | BO12: Fermignano | BP12: Cepagatti | BQ12: Carpaneto Piacentino | BR12: Castelnuovo di Val di Cecina | BS12: Montecatini-Terme | BT12: Cavasso Nuovo | BU12: Barile | BW12: Scicli | BX12: Fusignano | BY12: Bova | BZ12: Carpineti | CA12: Casaprota | CB12: Montegridolfo | CC12: Arsoli | CD12: Castelguglielmo | CE12: Atrani | CF12: Berchidda | CG12: Boissano | CH12: Chiusi | CI12: Lentini | CJ12: Caiolo | CK12: Castiadas | CL12: Lizzano | CM12: Castellalto | CN12: Castel Viscardo | CO12: Arignano | CP12: Marsala | CQ12: Bedollo | CR12: Castelcucco | CT12: Bicinicco | CU12: Brissogne | CV12: Besano | CW12: Cona | CX12: Beura-Cardezza | CY12: Borgo Vercelli | CZ12: Bosco Chiesanuova | DA12: Filadelfia | DB12: Barbarano Mossano | DC12: Canepina
A13: Casteltermini | B13: Basaluzzo | C13: Cerreto d'Esi | D13: Castiglion Fiorentino | E13: Cossignano | F13: Buttigliera d'Asti | G13: Bonito | H13: Cassano delle Murge | J13: Cesiomaggiore | K13: Calvi | L13: Arcene | M13: Candelo | N13: Casalfiumanese | O13: Bronzolo/Branzoll | P13: Barghe | Q13: Ostuni | R13: Selargius | S13: Mussomeli | T13: Casalciprano | U13: Cancello ed Arnone | V13: Camporotondo Etneo | W13: Carlopoli | X13: Casacanditella | Y13: Barni | Z13: Aprigliano | AA13: Cappella Cantone | AB13: Cutro | AC13: Barge | AD13: Nicosia | AE13: Monsampietro Morico | AF13: Masi Torello | AG13: Empoli | AH13: Carpino | AI13: Gambettola | AJ13: Ausonia | AK13: Casella | AL13: Monfalcone | AM13: Isola del Giglio | AN13: Caravonica | AO13: Castelpizzuto | AP13: Bugnara | AQ13: Deiva Marina | AR13: Lenola | AS13: Caprarica di Lecce | AT13: Calco | AU13: Piombino | AV13: Castelgerundo | AW13: Fabbriche di Vergemoli | AX13: Civitanova Marche | AY13: Castel Goffredo | AZ13: Mulazzo | BA13: Grottole | BB13: Caronia | BC13: Bernate Ticino | BD13: Finale Emilia | BE13: Brugherio | BF13: Calvizzano | BG13: Borgolavezzaro | BH13: Bortigali | BI13: Baressa | BJ13: Boara Pisani | BK13: Bolognetta | BL13: Corniglio | BM13: Bereguardo | BN13: Città della Pieve | BO13: Fossombrone | BP13: Città Sant'Angelo | BQ13: Castel San Giovanni | BR13: Chianni | BS13: Pescia | BT13: Chions | BU13: Bella | BW13: Vittoria | BX13: Lugo | BY13: Bova Marina | BZ13: Casalgrande | CA13: Casperia | CB13: Montescudo-Monte Colombo | CC13: Artena | CD13: Castelmassa | CE13: Auletta | CF13: Bessude | CG13: Borghetto Santo Spirito | CH13: Colle di Val d'Elsa | CI13: Melilli | CJ13: Campodolcino | CK13: Collinas | CL13: Manduria | CM13: Castelli | CN13: Fabro | CO13: Avigliana | CP13: Mazara del Vallo | CQ13: Besenello | CR13: Castelfranco Veneto | CT13: Bordano | CU13: Brusson | CV13: Besnate | CW13: Concordia Sagittaria | CX13: Bognanco | CY13: Borgo d'Ale | CZ13: Bovolone | DA13: Filandari | DB13: Bassano del Grappa | DC13: Canino
A14: Castrofilippo | B14: Bassignana | C14: Chiaravalle | D14: Cavriglia | E14: Cupra Marittima | F14: Calamandrana | G14: Cairano | H14: Castellana Grotte | J14: Chies d'Alpago | K14: Campolattaro | L14: Ardesio | M14: Caprile | N14: Castel Guelfo di Bologna | O14: Brunico/Bruneck | P14: Bassano Bresciano | Q14: San Donaci | R14: Sestu | S14: Niscemi | T14: Castelbottaccio | U14: Capodrise | V14: Castel di Iudica | W14: Catanzaro | X14: Casalanguida | Y14: Bellagio | Z14: Belmonte Calabro | AA14: Cappella de' Picenardi | AB14: Isola di Capo Rizzuto | AC14: Barolo | AD14: Nissoria | AE14: Montappone | AF14: Mesola | AG14: Fiesole | AH14: Casalnuovo Monterotaro | AI14: Gatteo | AJ14: Belmonte Castello | AK14: Castiglione Chiavarese | AL14: Moraro | AM14: Magliano in Toscana | AN14: Castel Vittorio | AO14: Castelverrino | AP14: Cagnano Amiterno | AQ14: Follo | AR14: Maenza | AS14: Carmiano | AT14: Calolziocorte | AU14: Porto Azzurro | AV14: Castelnuovo Bocca d'Adda | AW14: Forte dei Marmi | AX14: Colmurano | AY14: Castel d'Ario | AZ14: Podenzana | BA14: Irsina | BB14: Casalvecchio Siculo | BC14: Besate | BD14: Fiorano Modenese | BE14: Burago di Molgora | BF14: Camposano | BG14: Borgomanero | BH14: Cardedu | BI14: Bauladu | BJ14: Borgo Veneto | BK14: Bompietro | BL14: Felino | BM14: Borgarello | BN14: Città di Castello | BO14: Fratte Rosa | BP14: Civitaquana | BQ14: Castell'Arquato | BR14: Crespina Lorenzana | BS14: Pieve a Nievole | BT14: Cimolais | BU14: Brienza | BX14: Massa Lombarda | BY14: Bovalino | BZ14: Casina | CA14: Castel Sant'Angelo | CB14: Morciano di Romagna | CC14: Bellegra | CD14: Castelnovo Bariano | CE14: Baronissi | CF14: Bonnanaro | CG14: Borgio Verezzi | CH14: Gaiole in Chianti | CI14: Noto | CJ14: Caspoggio | CK14: Decimoputzu | CL14: Martina Franca | CM14: Castiglione Messer Raimondo | CN14: Ferentillo | CO14: Azeglio | CP14: Misiliscemi | CQ14: Bieno | CR14: Castello di Godego | CT14: Buja | CU14: Challand-Saint-Anselme | CV14: Besozzo | CW14: Dolo | CX14: Borgomezzavalle | CY14: Borgosesia | CZ14: Brentino Belluno | DA14: Filogaso | DB14: Bolzano Vicentino | DC14: Capodimonte
A15: Cattolica Eraclea | B15: Belforte Monferrato | C15: Corinaldo | D15: Chitignano | E15: Folignano | F15: Calliano Monferrato | G15: Calabritto | H15: Cellamare | J15: Cibiana di Cadore | K15: Campoli del Monte Taburno | L15: Arzago d'Adda | M15: Casapinta | N15: Castel Maggiore | O15: Caines/Kuens | P15: Bedizzole | Q15: San Michele Salentino | R15: Settimo San Pietro | S15: Resuttano | T15: Castellino del Biferno | U15: Capriati a Volturno | V15: Castiglione di Sicilia | W15: Cenadi | X15: Casalbordino | Y15: Bene Lario | Z15: Belsito | AA15: Capralba | AB15: Melissa | AC15: Bastia Mondovì | AD15: Piazza Armerina | AE15: Monte Giberto | AF15: Ostellato | AG15: Figline e Incisa Valdarno | AH15: Casalvecchio di Puglia | AI15: Longiano | AJ15: Boville Ernica | AK15: Ceranesi | AL15: Mossa | AM15: Manciano | AN15: Castellaro | AO15: Cerro al Volturno | AP15: Calascio | AQ15: Framura | AR15: Minturno | AS15: Carpignano Salentino | AT15: Carenno | AU15: Portoferraio | AV15: Castiglione d'Adda | AW15: Fosciandora | AX15: Corridonia | AY15: Castelbelforte | AZ15: Pontremoli | BA15: Matera | BB15: Castel di Lucio | BC15: Binasco | BD15: Fiumalbo | BE15: Busnago | BF15: Capri | BG15: Briga Novarese | BH15: Desulo | BI15: Bidonì | BJ15: Borgoricco | BK15: Borgetto | BL15: Fidenza | BM15: Borgo Priolo | BN15: Collazzone | BO15: Frontino | BP15: Civitella Casanova | BQ15: Castelvetro Piacentino | BR15: Fauglia | BS15: Pistoia | BT15: Claut | BU15: Brindisi Montagna | BX15: Ravenna | BY15: Brancaleone | BZ15: Castellarano | CA15: Castel di Tora | CB15: Novafeltria | CC15: Bracciano | CD15: Ceneselli | CE15: Battipaglia | CF15: Bono | CG15: Bormida | CH15: Montalcino | CI15: Pachino | CJ15: Castello dell'Acqua | CK15: Dolianova | CL15: Maruggio | CM15: Castilenti | CN15: Ficulle | CO15: Bairo | CP15: Paceco | CQ15: Bleggio Superiore | CR15: Cavaso del Tomba | CT15: Buttrio | CU15: Challand-Saint-Victor | CV15: Biandronno | CW15: Eraclea | CX15: Brovello-Carpugnino | CY15: Buronzo | CZ15: Brenzone sul Garda | DA15: Francavilla Angitola | DB15: Breganze | DC15: Capranica
A16: Cianciana | B16: Bergamasco | C16: Cupramontana | D16: Chiusi della Verna | E16: Force | F16: Calosso | G16: Calitri | H16: Conversano | J16: Colle Santa Lucia | K16: Casalduni | L16: Averara | M16: Castelletto Cervo | N16: Castel San Pietro Terme | O16: Caldaro sulla strada del vino/Kaltern an der Weinstraße | P16: Berlingo | Q16: San Pancrazio Salentino | R16: Sinnai | S16: Riesi | T16: Castelmauro | U16: Capua | V16: Catania | W16: Centrache | X16: Casalincontrada | Y16: Beregazzo con Figliaro | Z16: Belvedere Marittimo | AA16: Casalbuttano ed Uniti | AB16: Mesoraca | AC16: Battifollo | AD16: Pietraperzia | AE16: Monte Rinaldo | AF16: Poggio Renatico | AG16: Firenze | AH16: Castelluccio Valmaggiore | AI16: Meldola | AJ16: Broccostella | AK16: Chiavari | AL16: Romans d'Isonzo | AM16: Massa Marittima | AN16: Ceriana | AO16: Chiauci | AP16: Campo di Giove | AQ16: La Spezia | AR16: Monte San Biagio | AS16: Casarano | AT16: Casargo | AU16: Rio | AV16: Castiraga Vidardo | AW16: Gallicano | AX16: Esanatoglia | AY16: Castellucchio | AZ16: Tresana | BA16: Miglionico | BB16: Castell'Umberto | BC16: Boffalora sopra Ticino | BD16: Formigine | BE16: Camparada | BF16: Carbonara di Nola | BG16: Briona | BH16: Dorgali | BI16: Bonarcado | BJ16: Bovolenta | BK16: Caccamo | BL16: Fontanellato | BM16: Borgo San Siro | BN16: Corciano | BO16: Frontone | BP16: Collecorvino | BQ16: Cerignale | BR16: Guardistallo | BS16: Ponte Buggianese | BT16: Clauzetto | BU16: Calvello | BX16: Riolo Terme | BY16: Bruzzano Zeffirio | BZ16: Castelnovo di Sotto | CA16: Castelnuovo di Farfa | CB16: Pennabilli | CC16: Camerata Nuova | CD16: Ceregnano | CE16: Bellizzi | CF16: Bonorva | CG16: Cairo Montenotte | CH16: Montepulciano | CI16: Palazzolo Acreide | CJ16: Castione Andevenno | CK16: Domus de Maria | CL16: Massafra | CM16: Cellino Attanasio | CN16: Giove | CO16: Balangero | CP16: Pantelleria | CQ16: Bocenago | CR16: Cessalto | CT16: Camino al Tagliamento | CU16: Chambave | CV16: Bisuschio | CW16: Fiesso d'Artico | CX16: Calasca-Castiglione | CY16: Campertogno | CZ16: Bussolengo | DA16: Francica | DB16: Brendola | DC16: Caprarola
A17: Comitini | B17: Berzano di Tortona | C17: Fabriano | D17: Civitella in Val di Chiana | E17: Grottammare | F17: Camerano Casasco | G17: Candida | H17: Corato | J17: Comelico Superiore | K17: Castelfranco in Miscano | L17: Aviatico | M17: Cavaglià | N17: Castel d'Aiano | O17: Campo Tures/Sand in Taufers | P17: Berzo Demo | Q17: San Pietro Vernotico | R17: Uta | S17: San Cataldo | T17: Castropignano | U17: Carinaro | V17: Fiumefreddo di Sicilia | W17: Cerva | X17: Casoli | Y17: Binago | Z17: Bianchi | AA17: Casale Cremasco-Vidolasco | AB17: Pallagorio | AC17: Beinette | AD17: Regalbuto | AE17: Monte San Pietrangeli | AF17: Portomaggiore | AG17: Firenzuola | AH17: Castelluccio dei Sauri | AI17: Mercato Saraceno | AJ17: Campoli Appennino | AK17: Cicagna | AL17: Ronchi dei Legionari | AM17: Monte Argentario | AN17: Cervo | AO17: Civitanova del Sannio | AP17: Campotosto | AQ17: Lerici | AR17: Norma | AS17: Castri di Lecce | AT17: Casatenovo | AU17: Rosignano Marittimo | AV17: Cavenago d'Adda | AW17: Lucca | AX17: Fiastra | AY17: Castiglione delle Stiviere | AZ17: Villafranca in Lunigiana | BA17: Montalbano Jonico | BB17: Castelmola | BC17: Bollate | BD17: Frassinoro | BE17: Caponago | BF17: Cardito | BG17: Caltignaga | BH17: Dualchi | BI17: Boroneddu | BJ17: Brugine | BK17: Caltavuturo | BL17: Fontevivo | BM17: Borgoratto Mormorolo | BN17: Costacciaro | BO17: Gabicce Mare | BP17: Corvara | BQ17: Coli | BR17: Lajatico | BS17: Quarrata | BT17: Cordenons | BU17: Calvera | BX17: Russi | BY17: Calanna | BZ17: Castelnovo ne' Monti | CA17: Cittaducale | CB17: Poggio Torriana | CC17: Campagnano di Roma | CD17: Corbola | CE17: Bellosguardo | CF17: Bortigiadas | CG17: Calice Ligure | CH17: Monteriggioni | CI17: Portopalo di Capo Passero | CJ17: Cedrasco | CK17: Domusnovas | CL17: Monteiasi | CM17: Cermignano | CN17: Guardea | CO17: Baldissero Canavese | CP17: Partanna | CQ17: Bondone | CR17: Chiarano | CT17: Campoformido | CU17: Chamois | CV17: Bodio Lomnago | CW17: Fossalta di Piave | CX17: Cambiasca | CY17: Carcoforo | CZ17: Buttapietra | DA17: Gerocarne | DB17: Bressanvido | DC17: Carbognano
A18: Favara | B18: Bistagno | C18: Falconara Marittima | D18: Cortona | E18: Maltignano | F18: Canelli | G18: Caposele | H18: Gioia del Colle | J18: Cortina d'Ampezzo | K18: Castelpagano | L18: Azzano San Paolo | M18: Cerrione | N18: Castel del Rio | O18: Campo di Trens/Freienfeld | P18: Berzo Inferiore | Q18: San Vito dei Normanni | R18: Villa San Pietro | S18: Santa Caterina Villarmosa | T18: Cercemaggiore | U18: Carinola | V18: Giarre | W18: Chiaravalle Centrale | X18: Castel Frentano | Y18: Bizzarone | Z18: Bisignano | AA18: Casaletto Ceredano | AB18: Petilia Policastro | AC18: Bellino | AD18: Sperlinga | AE18: Monte Urano | AF18: Riva del Po | AG18: Fucecchio | AH18: Castelnuovo della Daunia | AI18: Modigliana | AJ18: Casalattico | AK18: Cogoleto | AL18: Sagrado | AM18: Monterotondo Marittimo | AN18: Cesio | AO18: Colli a Volturno | AP18: Canistro | AQ18: Levanto | AR18: Pontinia | AS18: Castrignano de' Greci | AT18: Cassago Brianza | AU18: San Vincenzo | AV18: Cervignano d'Adda | AW18: Massarosa | AX18: Fiuminata | AY18: Cavriana | AZ18: Zeri | BA18: Montescaglioso | BB18: Castroreale | BC18: Bresso | BD18: Guiglia | BE18: Carate Brianza | BF18: Casalnuovo di Napoli | BG18: Cameri | BH18: Elini | BI18: Bosa | BJ18: Cadoneghe | BK18: Campofelice di Fitalia | BL18: Fornovo di Taro | BM18: Bornasco | BN18: Deruta | BO18: Gradara | BP18: Cugnoli | BQ18: Corte Brugnatella | BR18: Montecatini Val di Cecina | BS18: Sambuca Pistoiese | BT18: Cordovado | BU18: Campomaggiore | BX18: Sant'Agata sul Santerno | BY18: Camini | BZ18: Cavriago | CA18: Cittareale | CB18: Riccione | CC18: Canale Monterano | CD18: Costa di Rovigo | CE18: Bracigliano | CF18: Borutta | CG18: Calizzano | CH18: Monteroni d'Arbia | CI18: Priolo Gargallo | CJ18: Cercino | CK18: Donori | CL18: Montemesola | CM18: Civitella del Tronto | CN18: Lugnano in Teverina | CO18: Baldissero Torinese | CP18: Petrosino | CQ18: Borgo Chiese | CR18: Cimadolmo | CT18: Campolongo Tapogliano | CU18: Champdepraz | CV18: Brebbia | CW18: Fossalta di Portogruaro | CX18: Cannero Riviera | CY18: Caresana | CZ18: Caldiero | DA18: Ionadi | DB18: Brogliano | DC18: Castel Sant'Elia
A19: Grotte | B19: Borghetto di Borbera | C19: Filottrano | D19: Foiano della Chiana | E19: Massignano | F19: Cantarana | G19: Capriglia Irpina | H19: Giovinazzo | J19: Danta di Cadore | K19: Castelpoto | L19: Azzone | M19: Coggiola | N19: Castel di Casio | O19: Castelbello-Ciardes/Kastelbell-Tschars | P19: Bienno | Q19: Torchiarolo | S19: Serradifalco | T19: Cercepiccola | U19: Casagiove | V19: Grammichele | W19: Cicala | X19: Castelguidone | Y19: Blessagno | Z19: Bocchigliero | AA19: Casaletto Vaprio | AB19: Rocca di Neto | AC19: Belvedere Langhe | AD19: Troina | AE19: Monte Vidon Combatte | AF19: Terre del Reno | AG19: Gambassi Terme | AH19: Celenza Valfortore | AI19: Montiano | AJ19: Casalvieri | AK19: Cogorno | AL19: San Canzian d'Isonzo | AM19: Montieri | AN19: Chiusanico | AO19: Conca Casale | AP19: Cansano | AQ19: Luni | AR19: Ponza | AS19: Castrignano del Capo | AT19: Cassina Valsassina | AU19: Sassetta | AV19: Codogno | AW19: Minucciano | AX19: Gagliole | AY19: Ceresara | BA19: Nova Siri | BB19: Cesarò | BC19: Bubbiano | BD19: Lama Mocogno | BE19: Carnate | BF19: Casamarciano | BG19: Carpignano Sesia | BH19: Fonni | BI19: Busachi | BJ19: Campo San Martino | BK19: Campofelice di Roccella | BL19: Langhirano | BM19: Bosnasco | BN19: Foligno | BO19: Isola del Piano | BP19: Elice | BQ19: Cortemaggiore | BR19: Montescudaio | BS19: San Marcello Piteglio | BT19: Erto e Casso | BU19: Cancellara | BX19: Solarolo | BY19: Campo Calabro | BZ19: Correggio | CA19: Collalto Sabino | CB19: Rimini | CC19: Canterano | CD19: Crespino | CE19: Buccino | CF19: Bottidda | CG19: Carcare | CH19: Monticiano | CI19: Rosolini | CJ19: Chiavenna | CK19: Escalaplano | CL19: Monteparano | CM19: Colledara | CN19: Montecastrilli | CO19: Balme | CP19: Poggioreale | CQ19: Borgo Lares | CR19: Cison di Valmarino | CT19: Carlino | CU19: Champorcher | CV19: Brenta | CW19: Fossò | CX19: Cannobio | CY19: Caresanablot | CZ19: Caprino Veronese | DA19: Joppolo | DB19: Caldogno | DC19: Castiglione in Teverina
A20: Joppolo Giancaxio | B20: Borgo San Martino | C20: Genga | D20: Laterina Pergine Valdarno | E20: Monsampolo del Tronto | F20: Capriglio | G20: Carife | H20: Gravina in Puglia | J20: Domegge di Cadore | K20: Castelvenere | L20: Bagnatica | M20: Cossato | N20: Castello d'Argile | O20: Castelrotto/Kastelruth | P20: Bione | Q20: Torre Santa Susanna | S20: Sommatino | T20: Civitacampomarano | U20: Casal di Principe | V20: Gravina di Catania | W20: Conflenti | X20: Castiglione Messer Marino | Y20: Blevio | Z20: Bonifati | AA20: Casaletto di Sopra | AB20: Roccabernarda | AC20: Bene Vagienna | AD20: Valguarnera Caropepe | AE20: Monte Vidon Corrado | AF20: Tresignana | AG20: Greve in Chianti | AH20: Celle di San Vito | AI20: Portico e San Benedetto | AJ20: Cassino | AK20: Coreglia Ligure | AL20: San Floriano del Collio-teverjan | AM20: Orbetello | AN20: Chiusavecchia | AO20: Filignano | AP20: Capestrano | AQ20: Maissana | AR20: Priverno | AS20: Castro | AT20: Castello di Brianza | AU20: Suvereto | AV20: Comazzo | AW20: Molazzana | AX20: Gualdo | AY20: Commessaggio | BA20: Oliveto Lucano | BB20: Condrò | BC20: Buccinasco | BD20: Maranello | BE20: Cavenago di Brianza | BF20: Casamicciola Terme | BG20: Casalbeltrame | BH20: Gadoni | BI20: Cabras | BJ20: Campodarsego | BK20: Campofiorito | BL20: Lesignano de' Bagni | BM20: Brallo di Pregola | BN20: Fossato di Vico | BO20: Lunano | BP20: Farindola | BQ20: Farini | BR20: Monteverdi Marittimo | BS20: Serravalle Pistoiese | BT20: Fanna | BU20: Carbone | BY20: Candidoni | BZ20: Fabbrico | CA20: Colle di Tora | CB20: Saludecio | CC20: Capena | CD20: Ficarolo | CE20: Buonabitacolo | CF20: Buddusò | CG20: Casanova Lerrone | CH20: Murlo | CI20: Siracusa | CJ20: Chiesa in Valmalenco | CK20: Escolca | CL20: Mottola | CM20: Colonnella | CN20: Montecchio | CO20: Banchette | CP20: Salaparuta | CQ20: Borgo Valsugana | CR20: Codognè | CT20: Cassacco | CU20: Charvensod | CV20: Brezzo di Bedero | CW20: Gruaro | CX20: Caprezzo | CY20: Carisio | CZ20: Casaleone | DA20: Limbadi | DB20: Caltrano | DC20: Celleno
A21: Lampedusa e Linosa | B21: Borgoratto Alessandrino | C21: Jesi | D21: Loro Ciuffenna | E21: Montalto delle Marche | F21: Casorzo Monferrato | G21: Casalbore | H21: Grumo Appula | J21: Falcade | K21: Castelvetere in Val Fortore | L21: Barbata | M21: Crevacuore | N21: Castenaso | O21: Cermes/Tscherms | P21: Borgo San Giacomo | Q21: Villa Castelli | S21: Sutera | T21: Colle d'Anchise | U21: Casaluce | V21: Licodia Eubea | W21: Cortale | X21: Celenza sul Trigno | Y21: Bregnano | Z21: Buonvicino | AA21: Casalmaggiore | AB21: San Mauro Marchesato | AC21: Benevello | AD21: Villarosa | AE21: Montefalcone Appennino | AF21: Vigarano Mainarda | AG21: Impruneta | AH21: Cerignola | AI21: Predappio | AJ21: Castelliri | AK21: Crocefieschi | AL21: San Lorenzo Isontino | AM21: Pitigliano | AN21: Cipressa | AO21: Forlì del Sannio | AP21: Capistrello | AQ21: Monterosso al Mare | AR21: Prossedi | AS21: Cavallino | AT21: Cernusco Lombardone | AV21: Cornegliano Laudense | AW21: Montecarlo | AX21: Loro Piceno | AY21: Curtatone | BA21: Pisticci | BB21: Falcone | BC21: Buscate | BD21: Marano sul Panaro | BE21: Ceriano Laghetto | BF21: Casandrino | BG21: Casaleggio Novara | BH21: Gairo | BI21: Cuglieri | BJ21: Campodoro | BK21: Camporeale | BL21: Medesano | BM21: Breme | BN21: Fratta Todina | BO21: Macerata Feltria | BP21: Lettomanoppello | BQ21: Ferriere | BR21: Montopoli in Val d'Arno | BS21: Uzzano | BT21: Fiume Veneto | BU21: Castelgrande | BY21: Canolo | BZ21: Gattatico | CA21: Collegiove | CB21: San Clemente | CC21: Capranica Prenestina | CD21: Fiesso Umbertiano | CE21: Caggiano | CF21: Budoni | CG21: Castelbianco | CH21: Piancastagnaio | CI21: Solarino | CJ21: Chiuro | CK21: Esterzili | CL21: Palagianello | CM21: Controguerra | CN21: Montefranco | CO21: Barbania | CP21: Salemi | CQ21: Borgo d'Anaunia | CR21: Colle Umberto | CT21: Castions di Strada | CU21: Châtillon | CV21: Brinzio | CW21: Jesolo | CX21: Casale Corte Cerro | CY21: Casanova Elvo | CZ21: Castagnaro | DA21: Maierato | DB21: Calvene | DC21: Cellere
A22: Licata | B22: Bosco Marengo | C22: Loreto | D22: Lucignano | E22: Montedinove | F22: Cassinasco | G22: Cassano Irpino | H22: Locorotondo | J22: Feltre | K22: Cautano | L22: Bariano | M22: Curino | N22: Castiglione dei Pepoli | O22: Chienes/Kiens | P22: Borgosatollo | S22: Vallelunga Pratameno | T22: Colletorto | U22: Casapesenna | V22: Linguaglossa | W22: Cropani | X22: Chieti | Y22: Brenna | Z22: Calopezzati | AA22: Casalmorano | AB22: San Nicola dell'Alto | AC22: Bergolo | AE22: Montefortino | AF22: Voghiera | AG22: Lastra a Signa | AH22: Chieuti | AI22: Premilcuore | AJ22: Castelnuovo Parano | AK22: Davagna | AL22: San Pier d'Isonzo | AM22: Roccalbegna | AN22: Civezza | AO22: Fornelli | AP22: Capitignano | AQ22: Pignone | AR22: Rocca Massima | AS22: Collepasso | AT22: Cesana Brianza | AV22: Corno Giovine | AW22: Pescaglia | AX22: Macerata | AY22: Dosolo | BA22: Policoro | BB22: Ficarra | BC22: Bussero | BD22: Medolla | BE22: Cesano Maderno | BF22: Casavatore | BG22: Casalino | BH22: Galtellì | BI22: Curcuris | BJ22: Camposampiero | BK22: Capaci | BL22: Monchio delle Corti | BM22: Bressana Bottarone | BN22: Giano dell'Umbria | BO22: Mercatello sul Metauro | BP22: Loreto Aprutino | BQ22: Fiorenzuola d'Arda | BR22: Orciano Pisano | BT22: Fontanafredda | BU22: Castelluccio Inferiore | BY22: Caraffa del Bianco | BZ22: Gualtieri | CA22: Collevecchio | CB22: San Giovanni in Marignano | CC22: Carpineto Romano | CD22: Frassinelle Polesine | CE22: Calvanico | CF22: Bultei | CG22: Castelvecchio di Rocca Barbena | CH22: Pienza | CI22: Sortino | CJ22: Cino | CK22: Fluminimaggiore | CL22: Palagiano | CM22: Corropoli | CN22: Montegabbione | CO22: Bardonecchia | CP22: San Vito Lo Capo | CQ22: Brentonico | CR22: Conegliano | CT22: Cavazzo Carnico | CU22: Cogne | CV22: Brissago-Valtravaglia | CW22: Marcon | CX22: Ceppo Morelli | CY22: Cellio con Breia | CZ22: Castel d'Azzano | DA22: Mileto | DB22: Camisano Vicentino | DC22: Civita Castellana
A23: Lucca Sicula | B23: Bosio | C23: Maiolati Spontini | D23: Marciano della Chiana | E23: Montefiore dell'Aso | F23: Castagnole Monferrato | G23: Castel Baronia | H23: Modugno | J23: Fonzaso | K23: Ceppaloni | L23: Barzana | M23: Donato | N23: Crevalcore | O23: Chiusa/Klausen | P23: Borno | S23: Villalba | T23: Duronia | U23: Casapulla | V23: Maletto | W23: Curinga | X23: Civitaluparella | Y23: Brienno | Z23: Caloveto | AA23: Castel Gabbiano | AB23: Santa Severina | AC23: Bernezzo | AE23: Montegiorgio | AG23: Londa | AH23: Deliceto | AI23: Rocca San Casciano | AJ23: Castro dei Volsci | AK23: Fascia | AL23: Savogna d'Isonzo-Sovodnje ob So?i | AM23: Roccastrada | AN23: Cosio d'Arroscia | AO23: Frosolone | AP23: Caporciano | AQ23: Portovenere | AR23: Roccagorga | AS23: Copertino | AT23: Civate | AV23: Cornovecchio | AW23: Piazza al Serchio | AX23: Matelica | AY23: Gazoldo degli Ippoliti | BA23: Pomarico | BB23: Fiumedinisi | BC23: Busto Garolfo | BD23: Mirandola | BE23: Cogliate | BF23: Casola di Napoli | BG23: Casalvolone | BH23: Gavoi | BI23: Flussio | BJ23: Candiana | BK23: Carini | BL23: Montechiarugolo | BM23: Broni | BN23: Gualdo Cattaneo | BO23: Mercatino Conca | BP23: Manoppello | BQ23: Gazzola | BR23: Palaia | BT23: Frisanco | BU23: Castelluccio Superiore | BY23: Cardeto | BZ23: Guastalla | CA23: Colli sul Velino | CB23: San Leo | CC23: Casape | CD23: Fratta Polesine | CE23: Camerota | CF23: Bulzi | CG23: Celle Ligure | CH23: Poggibonsi | CJ23: Civo | CK23: Furtei | CL23: Pulsano | CM23: Cortino | CN23: Monteleone d'Orvieto | CO23: Barone Canavese | CP23: Santa Ninfa | CQ23: Bresimo | CR23: Cordignano | CT23: Cercivento | CU23: Courmayeur | CV23: Brunello | CW23: Martellago | CX23: Cesara | CY23: Cervatto | CZ23: Castelnuovo del Garda | DA23: Mongiana | DB23: Campiglia dei Berici | DC23: Civitella d'Agliano
A24: Menfi | B24: Bozzole | C24: Mergo | D24: Monte San Savino | E24: Montegallo | F24: Castagnole delle Lanze | G24: Castelfranci | H24: Mola di Bari | J24: Gosaldo | K24: Cerreto Sannita | L24: Bedulita | M24: Dorzano | N24: Dozza | O24: Cornedo all'Isarco/Karneid | P24: Botticino | T24: Ferrazzano | U24: Caserta | V24: Maniace | W24: Davoli | X24: Civitella Messer Raimondo | Y24: Brunate | Z24: Campana | AA24: Casteldidone | AB24: Savelli | AC24: Bonvicino | AE24: Montegranaro | AG24: Marradi | AH24: Faeto | AI24: Roncofreddo | AJ24: Castrocielo | AK24: Favale di Malvaro | AL24: Staranzano | AM24: Santa Fiora | AN24: Costarainera | AO24: Isernia | AP24: Cappadocia | AQ24: Riccò del Golfo di Spezia | AR24: Roccasecca dei Volsci | AS24: Corigliano d'Otranto | AT24: Colico | AV24: Corte Palasio | AW24: Pietrasanta | AX24: Mogliano | AY24: Gazzuolo | BA24: Rotondella | BB24: Floresta | BC24: Calvignasco | BD24: Modena | BE24: Concorezzo | BF24: Casoria | BG24: Castellazzo Novarese | BH24: Girasole | BI24: Fordongianus | BJ24: Carmignano di Brenta | BK24: Castelbuono | BL24: Neviano degli Arduini | BM24: Calvignano | BN24: Gualdo Tadino | BO24: Mombaroccio | BP24: Montebello di Bertona | BQ24: Gossolengo | BR24: Peccioli | BT24: Maniago | BU24: Castelmezzano | BY24: Careri | BZ24: Luzzara | CA24: Concerviano | CB24: Sant'Agata Feltria | CC24: Castel Gandolfo | CD24: Gaiba | CE24: Campagna | CF24: Burgos | CG24: Cengio | CH24: Radda in Chianti | CJ24: Colorina | CK24: Genoni | CL24: Roccaforzata | CM24: Crognaleto | CN24: Narni | CO24: Beinasco | CP24: Trapani | CQ24: Caderzone Terme | CR24: Cornuda | CT24: Cervignano del Friuli | CU24: Donnas | CV24: Brusimpiano | CW24: Meolo | CX24: Cossogno | CY24: Cigliano | CZ24: Cavaion Veronese | DA24: Monterosso Calabro | DB24: Carrè | DC24: Corchiano
A25: Montallegro | B25: Brignano-Frascata | C25: Monsano | D25: Montemignaio | E25: Montemonaco | F25: Castel Boglione | G25: Castelvetere sul Calore | H25: Molfetta | J25: La Valle Agordina | K25: Circello | L25: Berbenno | M25: Gaglianico | N25: Fontanelice | O25: Cortaccia sulla strada del vino/Kurtatsch an der Weinstraße | P25: Bovegno | T25: Fossalto | U25: Castel Campagnano | V25: Mascali | W25: Decollatura | X25: Colledimacine | Y25: Bulgarograsso | Z25: Canna | AA25: Castelleone | AB25: Scandale | AC25: Borgo San Dalmazzo | AE25: Monteleone di Fermo | AG25: Montaione | AH25: Foggia | AI25: San Mauro Pascoli | AJ25: Ceccano | AK25: Fontanigorda | AL25: Turriaco | AM25: Scansano | AN25: Diano Arentino | AO25: Longano | AP25: Carapelle Calvisio | AQ25: Riomaggiore | AR25: Sabaudia | AS25: Corsano | AT25: Colle Brianza | AV25: Crespiatica | AW25: Pieve Fosciana | AX25: Monte Cavallo | AY25: Goito | BA25: Salandra | BB25: Fondachelli-Fantina | BC25: Cambiago | BD25: Montecreto | BE25: Cornate d'Adda | BF25: Castellammare di Stabia | BG25: Castelletto sopra Ticino | BH25: Ilbono | BI25: Ghilarza | BJ25: Cartura | BK25: Casteldaccia | BL25: Noceto | BM25: Campospinoso Albaredo | BN25: Gubbio | BO25: Mondavio | BP25: Montesilvano | BQ25: Gragnano Trebbiense | BR25: Pisa | BT25: Meduno | BU25: Castelsaraceno | BY25: Casignana | BZ25: Montecchio Emilia | CA25: Configni | CB25: Santarcangelo di Romagna | CC25: Castel Madama | CD25: Gavello | CE25: Campora | CF25: Calangianus | CG25: Ceriale | CH25: Radicofani | CJ25: Cosio Valtellino | CK25: Genuri | CL25: San Giorgio Ionico | CM25: Fano Adriano | CN25: Orvieto | CO25: Bibiana | CP25: Valderice | CQ25: Calceranica al Lago | CR25: Crocetta del Montello | CT25: Chiopris-Viscone | CU25: Doues | CV25: Buguggiate | CW25: Mira | CX25: Craveggia | CY25: Civiasco | CZ25: Cazzano di Tramigna | DA25: Nardodipace | DB25: Cartigliano | DC25: Fabrica di Roma
A26: Montevago | B26: Cabella Ligure | C26: Monte Roberto | D26: Monterchi | E26: Monteprandone | F26: Castel Rocchero | G26: Cervinara | H26: Monopoli | J26: Lamon | K26: Colle Sannita | L26: Bergamo | M26: Gifflenga | N26: Gaggio Montano | O26: Cortina sulla strada del vino/Kurtinig an der Weinstraße | P26: Bovezzo | T26: Gambatesa | U26: Castel Morrone | V26: Mascalucia | W26: Falerna | X26: Colledimezzo | Y26: Cabiate | Z26: Cariati | AA26: Castelverde | AB26: Strongoli | AC26: Borgomale | AE26: Montelparo | AG26: Montelupo Fiorentino | AH26: Ischitella | AI26: Santa Sofia | AJ26: Ceprano | AK26: Genova | AL26: Villesse | AM26: Scarlino | AN26: Diano Castello | AO26: Macchia d'Isernia | AP26: Carsoli | AQ26: Rocchetta di Vara | AR26: San Felice Circeo | AS26: Cursi | AT26: Cortenova | AV26: Fombio | AW26: Porcari | AX26: Monte San Giusto | AY26: Gonzaga | BA26: San Giorgio Lucano | BB26: Forza d'Agrò | BC26: Canegrate | BD26: Montefiorino | BE26: Correzzana | BF26: Castello di Cisterna | BG26: Cavaglietto | BH26: Irgoli | BI26: Gonnoscodina | BJ26: Casale di Scodosia | BK26: Castellana Sicula | BL26: Palanzano | BM26: Candia Lomellina | BN26: Lisciano Niccone | BO26: Mondolfo | BP26: Moscufo | BQ26: Gropparello | BR26: Pomarance | BT26: Montereale Valcellina | BU26: Castronuovo di Sant'Andrea | BY26: Caulonia | BZ26: Novellara | CA26: Contigliano | CB26: Sassofeltrio | CC26: Castel San Pietro Romano | CD26: Giacciano con Baruchella | CE26: Cannalonga | CF26: Cargeghe | CG26: Cisano sul Neva | CH26: Radicondoli | CJ26: Dazio | CK26: Gergei | CL26: San Marzano di San Giuseppe | CM26: Giulianova | CN26: Otricoli | CO26: Bobbio Pellice | CP26: Vita | CQ26: Caldes | CR26: Farra di Soligo | CT26: Chiusaforte | CU26: Emarèse | CV26: Busto Arsizio | CW26: Mirano | CX26: Crevoladossola | CY26: Collobiano | CZ26: Cerea | DA26: Nicotera | DB26: Cassola | DC26: Faleria
A27: Naro | B27: Camagna Monferrato | C27: Monte San Vito | D27: Montevarchi | E27: Offida | F27: Castell'Alfero | G27: Cesinali | H27: Noci | J27: Limana | K27: Cusano Mutri | L27: Berzo San Fermo | M27: Graglia | N27: Galliera | O27: Corvara in Badia/Corvara | P27: Brandico | T27: Gildone | U27: Castel Volturno | V27: Mazzarrone | W27: Feroleto Antico | X27: Crecchio | Y27: Cadorago | Z27: Carolei | AA27: Castelvisconti | AB27: Umbriatico | AC27: Bosia | AE27: Monterubbiano | AG27: Montespertoli | AH27: Isole Tremiti | AI27: Sarsina | AJ27: Cervaro | AK27: Gorreto | AM27: Seggiano | AN27: Diano Marina | AO27: Macchiagodena | AP27: Castel del Monte | AQ27: Santo Stefano di Magra | AR27: Santi Cosma e Damiano | AS27: Cutrofiano | AT27: Costa Masnaga | AV27: Galgagnano | AW27: San Romano in Garfagnana | AX27: Monte San Martino | AY27: Guidizzolo | BA27: San Mauro Forte | BB27: Francavilla di Sicilia | BC27: Carpiano | BD27: Montese | BE27: Desio | BF27: Cercola | BG27: Cavaglio d'Agogna | BH27: Jerzu | BI27: Gonnosnò | BJ27: Casalserugo | BK27: Castronovo di Sicilia | BL27: Parma | BM27: Canneto Pavese | BN27: Magione | BO27: Monte Cerignone | BP27: Nocciano | BQ27: Lugagnano Val d'Arda | BR27: Ponsacco | BT27: Morsano al Tagliamento | BU27: Cersosimo | BY27: Ciminà | BZ27: Poviglio | CA27: Cottanello | CB27: Talamello | CC27: Castelnuovo di Porto | CD27: Guarda Veneta | CE27: Capaccio Paestum | CF27: Castelsardo | CG27: Cosseria | CH27: Rapolano Terme | CJ27: Delebio | CK27: Gesico | CL27: Sava | CM27: Isola del Gran Sasso d'Italia | CN27: Parrano | CO27: Bollengo | CQ27: Caldonazzo | CR27: Follina | CT27: Cividale del Friuli | CU27: Etroubles | CV27: Cadegliano-Viconago | CW27: Musile di Piave | CX27: Crodo | CY27: Costanzana | CZ27: Cerro Veronese | DA27: Parghelia | DB27: Castegnero | DC27: Farnese
A28: Palma di Montechiaro | B28: Camino | C28: Montecarotto | D28: Ortignano Raggiolo | E28: Palmiano | F28: Castellero | G28: Chianche | H28: Noicattaro | J28: Livinallongo del Col di Lana | K28: Dugenta | L28: Bianzano | M28: Lessona | N28: Granarolo dell'Emilia | O28: Curon Venosta/Graun im Vinschgau | P28: Braone | T28: Guardialfiera | U28: Castel di Sasso | V28: Militello in Val di Catania | W28: Fossato Serralta | X28: Cupello | Y28: Caglio | Z28: Carpanzano | AA28: Cella Dati | AB28: Verzino | AC28: Bossolasco | AE28: Montottone | AG28: Palazzuolo sul Senio | AH28: Lesina | AI28: Savignano sul Rubicone | AJ28: Colfelice | AK28: Isola del Cantone | AM28: Semproniano | AN28: Diano San Pietro | AO28: Miranda | AP28: Castel di Ieri | AQ28: Sarzana | AR28: Sermoneta | AS28: Diso | AT28: Crandola Valsassina | AV28: Graffignana | AW28: Seravezza | AX28: Montecassiano | AY28: Magnacavallo | BA28: Scanzano Jonico | BB28: Frazzanò | BC28: Carugate | BD28: Nonantola | BE28: Giussano | BF28: Cicciano | BG28: Cavallirio | BH28: Lanusei | BI28: Gonnostramatza | BJ28: Castelbaldo | BK28: Cefalà Diana | BL28: Pellegrino Parmense | BM28: Carbonara al Ticino | BN28: Marsciano | BO28: Monte Grimano Terme | BP28: Penne | BQ28: Monticelli d'Ongina | BR28: Pontedera | BT28: Pasiano di Pordenone | BU28: Chiaromonte | BY28: Cinquefrondi | BZ28: Quattro Castella | CA28: Fara in Sabina | CB28: Verucchio | CC28: Cave | CD28: Lendinara | CE28: Casal Velino | CF28: Cheremule | CG28: Dego | CH28: San Casciano dei Bagni | CJ28: Dubino | CK28: Gesturi | CL28: Statte | CM28: Martinsicuro | CN28: Penna in Teverina | CO28: Borgaro Torinese | CQ28: Calliano | CR28: Fontanelle | CT28: Codroipo | CU28: Fontainemore | CV28: Cadrezzate con Osmate | CW28: Noale | CX28: Domodossola | CY28: Cravagliana | CZ28: Cologna Veneta | DA28: Pizzo | DB28: Castelgomberto | DC28: Gallese
A29: Porto Empedocle | B29: Cantalupo Ligure | C29: Montemarciano | D29: Pieve Santo Stefano | E29: Ripatransone | F29: Castelletto Molina | G29: Chiusano di San Domenico | H29: Palo del Colle | J29: Longarone | K29: Durazzano | L29: Blello | M29: Magnano | N29: Grizzana Morandi | O29: Dobbiaco/Toblach | P29: Breno | T29: Guardiaregia | U29: Castello del Matese | V29: Milo | W29: Gagliato | X29: Dogliola | Y29: Campione d'Italia | Z29: Casali del Manco | AA29: Chieve | AC29: Boves | AE29: Moresco | AG29: Pelago | AH29: Lucera | AI29: Sogliano al Rubicone | AJ29: Colle San Magno | AK29: Lavagna | AM29: Sorano | AN29: Dolceacqua | AO29: Montaquila | AP29: Castel di Sangro | AQ29: Sesta Godano | AR29: Sezze | AS29: Gagliano del Capo | AT29: Cremella | AV29: Guardamiglio | AW29: Sillano Giuncugnano | AX29: Montecosaro | AY29: Mantova | BA29: Stigliano | BB29: Furci Siculo | BC29: Casarile | BD29: Novi di Modena | BE29: Lazzate | BF29: Cimitile | BG29: Cerano | BH29: Lei | BI29: Laconi | BJ29: Cervarese Santa Croce | BK29: Cefalù | BL29: Polesine Zibello | BM29: Casanova Lonati | BN29: Massa Martana | BO29: Monte Porzio | BP29: Pescara | BQ29: Morfasso | BR29: Riparbella | BT29: Pinzano al Tagliamento | BU29: Corleto Perticara | BY29: Cittanova | BZ29: Reggio nell'Emilia | CA29: Fiamignano | CC29: Cerreto Laziale | CD29: Loreo | CE29: Casalbuono | CF29: Chiaramonti | CG29: Erli | CH29: San Gimignano | CJ29: Faedo Valtellino | CK29: Giba | CL29: Taranto | CM29: Montefino | CN29: Polino | CO29: Borgiallo | CQ29: Campitello di Fassa | CR29: Fonte | CT29: Colloredo di Monte Albano | CU29: Fénis | CV29: Cairate | CW29: Noventa di Piave | CX29: Druogno | CY29: Crescentino | CZ29: Colognola ai Colli | DA29: Pizzoni | DB29: Chiampo | DC29: Gradoli
A30: Racalmuto | B30: Capriata d'Orba | C30: Morro d'Alba | D30: Poppi | E30: Roccafluvione | F30: Castello di Annone | G30: Contrada | H30: Poggiorsini | J30: Lorenzago di Cadore | K30: Faicchio | L30: Bolgare | M30: Massazza | N30: Imola | O30: Egna/Neumarkt | P30: Brescia | T30: Guglionesi | U30: Cellole | V30: Mineo | W30: Gasperina | X30: Fallo | Y30: Cantù | Z30: Cassano all'Ionio | AA30: Cicognolo | AC30: Bra | AE30: Ortezzano | AG30: Pontassieve | AH30: Manfredonia | AI30: Tredozio | AJ30: Collepardo | AK30: Leivi | AN30: Dolcedo | AO30: Montenero Val Cocchiara | AP30: Castellafiume | AQ30: Varese Ligure | AR30: Sonnino | AS30: Galatina | AT30: Cremeno | AV30: Livraga | AW30: Stazzema | AX30: Montefano | AY30: Marcaria | BA30: Tricarico | BB30: Furnari | BC30: Casorezzo | BD30: Palagano | BE30: Lentate sul Seveso | BF30: Comiziano | BG30: Colazza | BH30: Loceri | BI30: Magomadas | BJ30: Cinto Euganeo | BK30: Cerda | BL30: Roccabianca | BM30: Casatisma | BN30: Monte Castello di Vibio | BO30: Montecalvo in Foglia | BP30: Pescosansonesco | BQ30: Ottone | BR30: San Giuliano Terme | BT30: Polcenigo | BU30: Episcopia | BY30: Condofuri | BZ30: Reggiolo | CA30: Forano | CC30: Cervara di Roma | CD30: Lusia | CE30: Casaletto Spartano | CF30: Codrongianos | CG30: Finale Ligure | CH30: San Quirico d'Orcia | CJ30: Forcola | CK30: Goni | CL30: Torricella | CM30: Montorio al Vomano | CN30: Porano | CO30: Borgofranco d'Ivrea | CQ30: Campodenno | CR30: Fregona | CT30: Comeglians | CU30: Gaby | CV30: Cantello | CW30: Pianiga | CX30: Formazza | CY30: Crova | CZ30: Concamarise | DA30: Polia | DB30: Chiuppano | DC30: Graffignano
A31: Raffadali | B31: Carbonara Scrivia | C31: Numana | D31: Pratovecchio Stia | E31: Rotella | F31: Castelnuovo Belbo | G31: Conza della Campania | H31: Polignano a Mare | J31: Lozzo di Cadore | K31: Foglianise | L31: Boltiere | M31: Masserano | N31: Lizzano in Belvedere | O31: Falzes/Pfalzen | P31: Brione | T31: Jelsi | U31: Cervino | V31: Mirabella Imbaccari | W31: Gimigliano | X31: Fara Filiorum Petri | Y31: Canzo | Z31: Castiglione Cosentino | AA31: Cingia de' Botti | AC31: Briaglia | AE31: Pedaso | AG31: Reggello | AH31: Mattinata | AI31: Verghereto | AJ31: Coreno Ausonio | AK31: Lorsica | AN31: Imperia | AO31: Monteroduni | AP31: Castelvecchio Calvisio | AQ31: Vernazza | AR31: Sperlonga | AS31: Galatone | AT31: Dervio | AV31: Lodi | AW31: Vagli Sotto | AX31: Montelupone | AY31: Mariana Mantovana | BA31: Tursi | BB31: Gaggi | BC31: Cassano d'Adda | BD31: Pavullo nel Frignano | BE31: Lesmo | BF31: Crispano | BG31: Comignago | BH31: Loculi | BI31: Marrubiu | BJ31: Cittadella | BK31: Chiusa Sclafani | BL31: Sala Baganza | BM31: Casei Gerola | BN31: Monte Santa Maria Tiberina | BO31: Montefelcino | BP31: Pianella | BQ31: Piacenza | BR31: San Miniato | BT31: Porcia | BU31: Fardella | BY31: Cosoleto | BZ31: Rio Saliceto | CA31: Frasso Sabino | CC31: Cerveteri | CD31: Melara | CE31: Caselle in Pittari | CF31: Cossoine | CG31: Garlenda | CH31: Sarteano | CJ31: Fusine | CK31: Gonnesa | CM31: Morro d'Oro | CN31: San Gemini | CO31: Borgomasino | CQ31: Canal San Bovo | CR31: Gaiarine | CT31: Corno di Rosazzo | CU31: Gignod | CV31: Caravate | CW31: Portogruaro | CX31: Germagno | CY31: Desana | CZ31: Costermano sul Garda | DA31: Ricadi | DB31: Cogollo del Cengio | DC31: Grotte di Castro
A32: Ravanusa | B32: Carentino | C32: Offagna | D32: San Giovanni Valdarno | E32: San Benedetto del Tronto | F32: Castelnuovo Calcea | G32: Domicella | H32: Putignano | J32: Ospitale di Cadore | K32: Foiano di Val Fortore | L32: Bonate Sopra | M32: Mezzana Mortigliengo | N32: Loiano | O32: Fiè allo Sciliar/Völs am Schlern | P32: Caino | T32: Larino | U32: Cesa | V32: Misterbianco | W32: Girifalco | X32: Fara San Martino | Y32: Capiago Intimiano | Z32: Castrolibero | AA32: Corte de' Cortesi con Cignone | AC32: Briga Alta | AE32: Petritoli | AG32: Rignano sull'Arno | AH32: Monte Sant'Angelo | AJ32: Esperia | AK32: Lumarzo | AN32: Isolabona | AO32: Pesche | AP32: Castelvecchio Subequo | AQ32: Vezzano Ligure | AR32: Spigno Saturnia | AS32: Gallipoli | AT32: Dolzago | AV32: Lodi Vecchio | AW32: Viareggio | AX32: Morrovalle | AY32: Marmirolo | BA32: Valsinni | BB32: Galati Mamertino | BC32: Cassina de' Pecchi | BD32: Pievepelago | BE32: Limbiate | BF32: Ercolano | BG32: Cressa | BH32: Lodine | BI32: Masullas | BJ32: Codevigo | BK32: Ciminna | BL32: Salsomaggiore Terme | BM32: Casorate Primo | BN32: Montefalco | BO32: Montelabbate | BP32: Picciano | BQ32: Pianello Val Tidone | BR32: Santa Croce sull'Arno | BT32: Pordenone | BU32: Filiano | BY32: Delianuova | BZ32: Rolo | CA32: Greccio | CC32: Ciampino | CD32: Occhiobello | CE32: Castel San Giorgio | CF32: Erula | CG32: Giustenice | CH32: Siena | CJ32: Gerola Alta | CK32: Gonnosfanadiga | CM32: Mosciano Sant'Angelo | CN32: San Venanzo | CO32: Borgone Susa | CQ32: Canazei | CR32: Giavera del Montello | CT32: Coseano | CU32: Gressan | CV32: Cardano al Campo | CW32: Pramaggiore | CX32: Ghiffa | CY32: Fobello | CZ32: Dolcè | DA32: Rombiolo | DB32: Colceresa | DC32: Ischia di Castro
A33: Realmonte | B33: Carezzano | C33: Osimo | D33: Sansepolcro | E33: Spinetoli | F33: Castelnuovo Don Bosco | G33: Flumeri | H33: Rutigliano | J33: Pedavena | K33: Forchia | L33: Bonate Sotto | M33: Miagliano | N33: Malalbergo | O33: Fortezza/Franzensfeste | P33: Calcinato | T33: Limosano | U33: Ciorlano | V33: Motta Sant'Anastasia | W33: Gizzeria | X33: Filetto | Y33: Carate Urio | Z33: Castroregio | AA33: Corte de' Frati | AC33: Brondello | AE33: Ponzano di Fermo | AG33: Rufina | AH33: Monteleone di Puglia | AJ33: Falvaterra | AK33: Masone | AN33: Lucinasco | AO33: Pescolanciano | AP33: Celano | AQ33: Zignago | AR33: Terracina | AS33: Giuggianello | AT33: Dorio | AV33: Maccastorna | AW33: Villa Basilica | AX33: Muccia | AY33: Medole | BB33: Gallodoro | BC33: Cassinetta di Lugagnano | BD33: Polinago | BE33: Lissone | BF33: Forio | BG33: Cureggio | BH33: Lodè | BI33: Milis | BJ33: Conselve | BK33: Cinisi | BL33: San Secondo Parmense | BM33: Cassolnovo | BN33: Monteleone di Spoleto | BO33: Peglio | BP33: Pietranico | BQ33: Piozzano | BR33: Santa Luce | BT33: Prata di Pordenone | BU33: Forenza | BY33: Feroleto della Chiesa | BZ33: Rubiera | CA33: Labro | CC33: Ciciliano | CD33: Papozze | CE33: Castel San Lorenzo | CF33: Esporlatu | CG33: Giusvalla | CH33: Sinalunga | CJ33: Gordona | CK33: Guamaggiore | CM33: Nereto | CN33: Stroncone | CO33: Bosconero | CQ33: Capriana | CR33: Godega di Sant'Urbano | CT33: Dignano | CU33: Gressoney-La-Trinité | CV33: Carnago | CW33: Quarto d'Altino | CX33: Gignese | CY33: Fontanetto Po | CZ33: Erbezzo | DA33: San Calogero | DB33: Cornedo Vicentino | DC33: Latera
A34: Ribera | B34: Carpeneto | C34: Ostra | D34: Sestino | E34: Venarotta | F34: Cellarengo | G34: Fontanarosa | H34: Ruvo di Puglia | J34: Perarolo di Cadore | K34: Fragneto Monforte | L34: Borgo di Terzo | M34: Mongrando | N34: Marzabotto | O34: Funes/Villnöß | P34: Calvagese della Riviera | T34: Lucito | U34: Conca della Campania | V34: Nicolosi | W34: Guardavalle | X34: Fossacesia | Y34: Carbonate | Z34: Castrovillari | AA34: Credera Rubbiano | AC34: Brossasco | AE34: Porto San Giorgio | AG34: San Casciano in Val di Pesa | AH34: Motta Montecorvino | AJ34: Ferentino | AK34: Mele | AN34: Mendatica | AO34: Pescopennataro | AP34: Cerchio | AR34: Ventotene | AS34: Giurdignano | AT34: Ello | AV34: Mairago | AW34: Villa Collemandina | AX34: Penna San Giovanni | AY34: Moglia | BB34: Giardini-Naxos | BC34: Castano Primo | BD34: Prignano sulla Secchia | BE34: Macherio | BF34: Frattamaggiore | BG34: Divignano | BH34: Lotzorai | BI34: Modolo | BJ34: Correzzola | BK34: Collesano | BL34: Sissa Trecasali | BM34: Castana | BN34: Montone | BO34: Pergola | BP34: Popoli Terme | BQ34: Podenzano | BR34: Santa Maria a Monte | BT34: Pravisdomini | BU34: Francavilla in Sinni | BY34: Ferruzzano | BZ34: San Martino in Rio | CA34: Leonessa | CC34: Cineto Romano | CD34: Pettorazza Grimani | CE34: Castelcivita | CF34: Florinas | CG34: Laigueglia | CH34: Sovicille | CJ34: Grosio | CK34: Guasila | CM34: Notaresco | CN34: Terni | CO34: Brandizzo | CQ34: Carisolo | CR34: Gorgo al Monticano | CT34: Dogna | CU34: Gressoney-Saint-Jean | CV34: Caronno Pertusella | CW34: Salzano | CX34: Gravellona Toce | CY34: Formigliana | CZ34: Erbè | DA34: San Costantino Calabro | DB34: Costabissara | DC34: Lubriano
A35: Sambuca di Sicilia | B35: Carrega Ligure | C35: Ostra Vetere | D35: Subbiano | F35: Celle Enomondo | G35: Forino | H35: Sammichele di Bari | J35: Pieve di Cadore | K35: Fragneto l'Abate | L35: Bossico | M35: Mottalciata | N35: Medicina | O35: Gais/Gais | P35: Calvisano | T35: Lupara | U35: Curti | V35: Palagonia | W35: Isca sullo Ionio | X35: Fraine | Y35: Carimate | Z35: Celico | AA35: Crema | AC35: Busca | AE35: Porto Sant'Elpidio | AG35: San Godenzo | AH35: Ordona | AJ35: Filettino | AK35: Mezzanego | AN35: Molini di Triora | AO35: Pettoranello del Molise | AP35: Civita d'Antino | AS35: Guagnano | AT35: Erve | AV35: Maleo | AX35: Petriolo | AY35: Monzambano | BB35: Gioiosa Marea | BC35: Cernusco sul Naviglio | BD35: Ravarino | BE35: Meda | BF35: Frattaminore | BG35: Dormelletto | BH35: Lula | BI35: Mogorella | BJ35: Curtarolo | BK35: Contessa Entellina | BL35: Solignano | BM35: Casteggio | BN35: Nocera Umbra | BO35: Pesaro | BP35: Roccamorice | BQ35: Ponte dell'Olio | BR35: Terricciola | BT35: Roveredo in Piano | BU35: Gallicchio | BY35: Fiumara | BZ35: San Polo d'Enza | CA35: Longone Sabino | CC35: Civitavecchia | CD35: Pincara | CE35: Castellabate | CF35: Giave | CG35: Loano | CH35: Torrita di Siena | CJ35: Grosotto | CK35: Guspini | CM35: Penna Sant'Andrea | CO35: Bricherasio | CQ35: Carzano | CR35: Istrana | CT35: Drenchia | CU35: Hône | CV35: Caronno Varesino | CW35: San Donà di Piave | CX35: Gurro | CY35: Gattinara | CZ35: Ferrara di Monte Baldo | DA35: San Gregorio d'Ippona | DB35: Creazzo | DC35: Marta
A36: San Biagio Platani | B36: Carrosio | C36: Poggio San Marcello | D36: Talla | F36: Cerreto d'Asti | G36: Frigento | H36: Sannicandro di Bari | J36: Ponte nelle Alpi | K36: Frasso Telesino | L36: Bottanuco | M36: Muzzano | N36: Minerbio | O36: Gargazzone/Gargazon | P36: Capo di Ponte | T36: Macchia Valfortore | U36: Dragoni | V36: Paternò | W36: Jacurso | X36: Francavilla al Mare | Y36: Carlazzo | Z36: Cellara | AA36: Cremona | AC36: Camerana | AE36: Rapagnano | AG36: Scandicci | AH36: Orsara di Puglia | AJ36: Fiuggi | AK36: Mignanego | AN36: Montalto Carpasio | AO36: Pietrabbondante | AP36: Civitella Alfedena | AS36: Lecce | AT36: Esino Lario | AV36: Marudo | AX36: Pieve Torina | AY36: Motteggiana | BB36: Graniti | BC36: Cerro Maggiore | BD36: Riolunato | BE36: Mezzago | BF36: Giugliano in Campania | BG36: Fara Novarese | BH36: Macomer | BI36: Mogoro | BJ36: Due Carrare | BK36: Corleone | BL36: Soragna | BM36: Castelletto di Branduzzo | BN36: Norcia | BO36: Petriano | BP36: Rosciano | BQ36: Pontenure | BR36: Vecchiano | BT36: Sacile | BU36: Genzano di Lucania | BY36: Galatro | BZ36: Sant'Ilario d'Enza | CA36: Magliano Sabina | CC36: Civitella San Paolo | CD36: Polesella | CE36: Castelnuovo Cilento | CF36: Golfo Aranci | CG36: Magliolo | CH36: Trequanda | CJ36: Lanzada | CK36: Iglesias | CM36: Pietracamela | CO36: Brosso | CQ36: Castel Condino | CR36: Loria | CT36: Enemonzo | CU36: Introd | CV36: Casale Litta | CW36: San Michele al Tagliamento | CX36: Intragna | CY36: Ghislarengo | CZ36: Fumane | DA36: San Nicola da Crissa | DB36: Crespadoro | DC36: Montalto di Castro
A37: San Giovanni Gemini | B37: Cartosio | C37: Polverigi | D37: Terranuova Bracciolini | F37: Cerro Tanaro | G37: Gesualdo | H37: Santeramo in Colle | J37: Rivamonte Agordino | K37: Ginestra degli Schiavoni | L37: Bracca | M37: Netro | N37: Molinella | O37: Glorenza/Glurns | P37: Capovalle | T37: Mafalda | U37: Falciano del Massico | V37: Pedara | W37: Lamezia Terme | X37: Fresagrandinaria | Y37: Carugo | Z37: Cerchiara di Calabria | AA37: Cremosano | AC37: Canale | AE37: Sant'Elpidio a Mare | AG37: Scarperia e San Piero | AH37: Orta Nova | AJ37: Fontana Liri | AK37: Moconesi | AN37: Montegrosso Pian Latte | AO37: Pizzone | AP37: Civitella Roveto | AS37: Lequile | AT37: Galbiate | AV37: Massalengo | AX37: Pioraco | AY37: Ostiglia | BB37: Gualtieri Sicaminò | BC37: Cerro al Lambro | BD37: San Cesario sul Panaro | BE37: Misinto | BF37: Gragnano | BG37: Fontaneto d'Agogna | BH37: Mamoiada | BI37: Montresta | BJ37: Este | BK37: Ficarazzi | BL37: Sorbolo Mezzani | BM37: Castello d'Agogna | BN37: Paciano | BO37: Piandimeleto | BP37: Salle | BQ37: Rivergaro | BR37: Vicopisano | BT37: San Giorgio della Richinvelda | BU37: Ginestra | BY37: Gerace | BZ37: Scandiano | CA37: Marcetelli | CC37: Colleferro | CD37: Pontecchio Polesine | CE37: Castelnuovo di Conza | CF37: Illorai | CG37: Mallare | CJ37: Livigno | CK37: Isili | CM37: Pineto | CO37: Brozolo | CQ37: Castel Ivano | CR37: Mansuè | CT37: Faedis | CU37: Issime | CV37: Casalzuigno | CW37: San Stino di Livenza | CX37: Loreglia | CY37: Greggio | CZ37: Garda | DA37: Sant'Onofrio | DB37: Dueville | DC37: Monte Romano
A38: Sant'Angelo Muxaro | B38: Casal Cermelli | C38: Rosora | F38: Cessole | G38: Greci | H38: Terlizzi | J38: Rocca Pietore | K38: Guardia Sanframondi | L38: Branzi | M38: Occhieppo Inferiore | N38: Monghidoro | O38: La Valle/Wengen | P38: Capriano del Colle | T38: Matrice | U38: Fontegreca | V38: Piedimonte Etneo | W38: Magisano | X38: Frisa | Y38: Caslino d'Erba | Z38: Cerisano | AA38: Crotta d'Adda | AC38: Canosio | AE38: Santa Vittoria in Matenano | AG38: Sesto Fiorentino | AH38: Panni | AJ38: Fontechiari | AK38: Moneglia | AN38: Olivetta San Michele | AO38: Poggio Sannita | AP38: Cocullo | AS38: Leverano | AT38: Garbagnate Monastero | AV38: Meleti | AX38: Poggio San Vicino | AY38: Pegognaga | BB38: Itala | BC38: Cesano Boscone | BD38: San Felice sul Panaro | BE38: Monza | BF38: Grumo Nevano | BG38: Galliate | BH38: Meana Sardo | BI38: Morgongiori | BJ38: Fontaniva | BK38: Gangi | BL38: Terenzo | BM38: Castelnovetto | BN38: Panicale | BO38: Pietrarubbia | BP38: San Valentino in Abruzzo Citeriore | BQ38: Rottofreno | BR38: Volterra | BT38: San Martino al Tagliamento | BU38: Grumento Nova | BY38: Giffone | BZ38: Toano | CA38: Micigliano | CC38: Colonna | CD38: Porto Tolle | CE38: Castiglione del Genovesi | CF38: Ittireddu | CG38: Massimino | CJ38: Lovero | CK38: Las Plassas | CM38: Rocca Santa Maria | CO38: Bruino | CQ38: Castello Tesino | CR38: Mareno di Piave | CT38: Fagagna | CU38: Issogne | CV38: Casciago | CW38: Santa Maria di Sala | CX38: Macugnaga | CY38: Guardabosone | CZ38: Gazzo Veronese | DA38: Serra San Bruno | DB38: Enego | DC38: Montefiascone
A39: Santa Elisabetta | B39: Casale Monferrato | C39: San Marcello | F39: Chiusano d'Asti | G39: Grottaminarda | H39: Toritto | J39: San Gregorio nelle Alpi | K39: Limatola | L39: Brembate | M39: Occhieppo Superiore | N39: Monte San Pietro | O39: Laces/Latsch | P39: Capriolo | T39: Mirabello Sannitico | U39: Formicola | V39: Raddusa | W39: Maida | X39: Furci | Y39: Casnate con Bernate | Z39: Cervicati | AA39: Cumignano sul Naviglio | AC39: Caprauna | AE39: Servigliano | AG39: Signa | AH39: Peschici | AJ39: Frosinone | AK39: Montebruno | AN39: Ospedaletti | AO39: Pozzilli | AP39: Collarmele | AS39: Lizzanello | AT39: Garlate | AV39: Merlino | AX39: Pollenza | AY39: Piubega | BB39: Leni | BC39: Cesate | BD39: San Possidonio | BE39: Muggiò | BF39: Ischia | BG39: Garbagna Novarese | BH39: Noragugume | BI39: Narbolia | BJ39: Galliera Veneta | BK39: Geraci Siculo | BL39: Tizzano Val Parma | BM39: Cava Manara | BN39: Passignano sul Trasimeno | BO39: Piobbico | BP39: Sant'Eufemia a Maiella | BQ39: San Giorgio Piacentino | BT39: San Quirino | BU39: Guardia Perticara | BY39: Gioia Tauro | BZ39: Ventasso | CA39: Mompeo | CC39: Fiano Romano | CD39: Porto Viro | CE39: Cava de' Tirreni | CF39: Ittiri | CG39: Millesimo | CJ39: Madesimo | CK39: Lunamatrona | CM39: Roseto degli Abruzzi | CO39: Brusasco | CQ39: Castello-Molina di Fiemme | CR39: Maser | CT39: Fiumicello Villa Vicentina | CU39: Jovençan | CV39: Casorate Sempione | CW39: Scorzè | CX39: Madonna del Sasso | CY39: Lamporo | CZ39: Grezzana | DA39: Simbario | DB39: Fara Vicentino | DC39: Monterosi
A40: Santa Margherita di Belice | B40: Casaleggio Boiro | C40: San Paolo di Jesi | F40: Cinaglio | G40: Grottolella | H40: Triggiano | J40: San Nicolò di Comelico | K40: Melizzano | L40: Brembate di Sopra | M40: Pettinengo | N40: Monterenzio | O40: Lagundo/Algund | P40: Carpenedolo | T40: Molise | U40: Francolise | V40: Ragalna | W40: Marcedusa | X40: Gamberale | Y40: Cassina Rizzardi | Z40: Cerzeto | AA40: Derovere | AC40: Caraglio | AE40: Smerillo | AG40: Vaglia | AH40: Pietramontecorvino | AJ40: Fumone | AK40: Montoggio | AN40: Perinaldo | AO40: Rionero Sannitico | AP40: Collelongo | AS40: Maglie | AT40: Imbersago | AV40: Montanaso Lombardo | AX40: Porto Recanati | AY40: Poggio Rusco | BB40: Letojanni | BC40: Cinisello Balsamo | BD40: San Prospero | BE40: Nova Milanese | BF40: Lacco Ameno | BG40: Gargallo | BH40: Nuoro | BI40: Neoneli | BJ40: Galzignano Terme | BK40: Giardinello | BL40: Tornolo | BM40: Cecima | BN40: Perugia | BO40: San Costanzo | BP40: Scafa | BQ40: San Pietro in Cerro | BT40: San Vito al Tagliamento | BU40: Lagonegro | BY40: Gioiosa Ionica | BZ40: Vetto | CA40: Montasola | CC40: Filacciano | CD40: Rosolina | CE40: Celle di Bulgheria | CF40: La Maddalena | CG40: Mioglia | CJ40: Mantello | CK40: Mandas | CM40: Sant'Egidio alla Vibrata | CO40: Bruzolo | CQ40: Castelnuovo | CR40: Maserada sul Piave | CT40: Flaibano | CU40: La Magdeleine | CV40: Cassano Magnago | CW40: Spinea | CX40: Malesco | CY40: Lenta | CZ40: Illasi | DA40: Sorianello | DB40: Foza | DC40: Nepi
A41: Santo Stefano Quisquina | B41: Casalnoceto | C41: Santa Maria Nuova | F41: Cisterna d'Asti | G41: Guardia Lombardi | H41: Turi | J41: San Pietro di Cadore | K41: Moiano | L41: Brignano Gera d'Adda | M41: Piatto | N41: Monzuno | O41: Laion/Lajen | P41: Castegnato | T41: Monacilioni | U41: Frignano | V41: Ramacca | W41: Marcellinara | X41: Gessopalena | Y41: Castelmarte | Z41: Cetraro | AA41: Dovera | AC41: Caramagna Piemonte | AE41: Torre San Patrizio | AG41: Vicchio | AH41: Poggio Imperiale | AJ41: Gallinaro | AK41: Ne | AN41: Pietrabruna | AO41: Roccamandolfi | AP41: Collepietro | AS41: Martano | AT41: Introbio | AV41: Mulazzano | AX41: Potenza Picena | AY41: Pomponesco | BB41: Librizzi | BC41: Cisliano | BD41: Sassuolo | BE41: Ornago | BF41: Lettere | BG41: Gattico-Veruno | BH41: Oliena | BI41: Norbello | BJ41: Gazzo | BK41: Giuliana | BL41: Torrile | BM41: Ceranova | BN41: Piegaro | BO41: San Lorenzo in Campo | BP41: Serramonacesca | BQ41: Sarmato | BT41: Sequals | BU41: Latronico | BY41: Grotteria | BZ41: Vezzano sul Crostolo | CA41: Monte San Giovanni in Sabina | CC41: Fiumicino | CD41: Rovigo | CE41: Centola | CF41: Laerru | CG41: Murialdo | CJ41: Mazzo di Valtellina | CK41: Masainas | CM41: Sant'Omero | CO41: Buriasco | CQ41: Cavalese | CR41: Meduna di Livenza | CT41: Forgaria nel Friuli | CU41: La Salle | CV41: Cassano Valcuvia | CW41: Stra | CX41: Masera | CY41: Lignana | CZ41: Isola Rizza | DA41: Soriano Calabro | DB41: Gallio | DC41: Onano
A42: Sciacca | B42: Casasco | C42: Sassoferrato | F42: Coazzolo | G42: Lacedonia | H42: Valenzano | J42: San Tomaso Agordino | K42: Molinara | L42: Brumano | M42: Piedicavallo | N42: Mordano | O42: Laives/Leifers | P42: Castel Mella | T42: Montagano | U42: Gallo Matese | V42: Randazzo | W42: Martirano | X42: Gissi | Y42: Castelnuovo Bozzente | Z42: Civita | AA42: Fiesco | AC42: Cardè | AG42: Vinci | AH42: Rignano Garganico | AJ42: Giuliano di Roma | AK42: Neirone | AN42: Pieve di Teco | AO42: Roccasicura | AP42: Corfinio | AS42: Martignano | AT42: La Valletta Brianza | AV42: Orio Litta | AX42: Recanati | AY42: Ponti sul Mincio | BB42: Limina | BC42: Cologno Monzese | BD42: Savignano sul Panaro | BE42: Renate | BF42: Liveri | BG42: Ghemme | BH42: Ollolai | BI42: Nughedu Santa Vittoria | BJ42: Grantorto | BK42: Godrano | BL42: Traversetolo | BM42: Ceretto Lomellina | BN42: Pietralunga | BO42: Sant'Angelo in Vado | BP42: Spoltore | BQ42: Travo | BT42: Sesto al Reghena | BU42: Laurenzana | BY42: Laganadi | BZ42: Viano | CA42: Montebuono | CC42: Fonte Nuova | CD42: Salara | CE42: Ceraso | CF42: Loiri Porto San Paolo | CG42: Nasino | CJ42: Mello | CK42: Monastir | CM42: Silvi | CO42: Burolo | CQ42: Cavareno | CR42: Miane | CT42: Forni Avoltri | CU42: La Thuile | CV42: Castellanza | CW42: Teglio Veneto | CX42: Massiola | CY42: Livorno Ferraris | CZ42: Isola della Scala | DA42: Spadola | DB42: Gambellara | DC42: Oriolo Romano
A43: Siculiana | B43: Cassano Spinola | C43: Senigallia | F43: Cocconato | G43: Lapio | J43: San Vito di Cadore | K43: Montefalcone di Val Fortore | L43: Brusaporto | M43: Pollone | N43: Ozzano dell'Emilia | O43: Lana/Lana | P43: Castelcovati | T43: Montecilfone | U43: Galluccio | V43: Riposto | W43: Martirano Lombardo | X43: Giuliano Teatino | Y43: Cavargna | Z43: Cleto | AA43: Formigara | AC43: Carrù | AH43: Rocchetta Sant'Antonio | AJ43: Guarcino | AK43: Orero | AN43: Pigna | AO43: Rocchetta a Volturno | AP43: Fagnano Alto | AS43: Matino | AT43: Lecco | AV43: Ospedaletto Lodigiano | AX43: Ripe San Ginesio | AY43: Porto Mantovano | BB43: Lipari | BC43: Colturano | BD43: Serramazzoni | BE43: Roncello | BF43: Marano di Napoli | BG43: Gozzano | BH43: Olzai | BI43: Nurachi | BJ43: Granze | BK43: Gratteri | BL43: Valmozzola | BM43: Cergnago | BN43: Poggiodomo | BO43: Sant'Ippolito | BP43: Tocco da Casauria | BQ43: Vernasca | BT43: Spilimbergo | BU43: Lauria | BY43: Laureana di Borrello | BZ43: Villa Minozzo | CA43: Monteleone Sabino | CC43: Formello | CD43: San Bellino | CE43: Cetara | CF43: Luogosanto | CG43: Noli | CJ43: Mese | CK43: Muravera | CM43: Teramo | CO43: Busano | CQ43: Cavedago | CR43: Mogliano Veneto | CT43: Forni di Sopra | CU43: Lillianes | CV43: Castello Cabiaglio | CW43: Torre di Mosto | CX43: Mergozzo | CY43: Lozzolo | CZ43: Lavagno | DA43: Spilinga | DB43: Grisignano di Zocco | DC43: Orte
A44: Villafranca Sicula | B44: Cassine | C44: Serra San Quirico | F44: Corsione | G44: Lauro | J44: Santa Giustina | K44: Montesarchio | L44: Calcinate | M44: Ponderano | N44: Pianoro | O44: Lasa/Laas | P44: Castenedolo | T44: Montefalcone nel Sannio | U44: Giano Vetusto | V44: San Cono | W44: Miglierina | X44: Guardiagrele | Y44: Centro Valle Intelvi | Z44: Colosimi | AA44: Gabbioneta-Binanuova | AC44: Cartignano | AH44: Rodi Garganico | AJ44: Isola del Liri | AK44: Pieve Ligure | AN44: Pompeiana | AO44: San Pietro Avellana | AP44: Fontecchio | AS44: Melendugno | AT44: Lierna | AV44: Ossago Lodigiano | AX44: San Ginesio | AY44: Quingentole | BB44: Longi | BC44: Corbetta | BD44: Sestola | BE44: Ronco Briantino | BF44: Mariglianella | BG44: Granozzo con Monticello | BH44: Onanì | BI44: Nureci | BJ44: Legnaro | BK44: Isnello | BL44: Varano de' Melegari | BM44: Certosa di Pavia | BN44: Preci | BO44: Sassocorvaro Auditore | BP44: Torre de' Passeri | BQ44: Vigolzone | BT44: Tramonti di Sopra | BU44: Lavello | BY44: Locri | CA44: Montenero Sabino | CC44: Frascati | CD44: San Martino di Venezze | CE44: Cicerale | CF44: Luras | CG44: Onzo | CJ44: Montagna in Valtellina | CK44: Musei | CM44: Torano Nuovo | CO44: Bussoleno | CQ44: Cavedine | CR44: Monastier di Treviso | CT44: Forni di Sotto | CU44: Montjovet | CV44: Castelseprio | CW44: Venezia | CX44: Miazzina | CY44: Mollia | CZ44: Lazise | DA44: Stefanaconi | DB44: Grumolo delle Abbadesse | DC44: Piansano
B45: Cassinelle | C45: Serra de' Conti | F45: Cortandone | G45: Lioni | J45: Santo Stefano di Cadore | K45: Morcone | L45: Calcio | M45: Portula | N45: Pieve di Cento | O45: Lauregno/Laurein | P45: Casto | T45: Montelongo | U45: Gioia Sannitica | V45: San Giovanni la Punta | W45: Montauro | X45: Guilmi | Y45: Cerano d'Intelvi | Z45: Corigliano-Rossano | AA45: Gadesco-Pieve Delmona | AC45: Casalgrasso | AH45: Roseto Valfortore | AJ45: Monte San Giovanni Campano | AK45: Portofino | AN45: Pontedassio | AO45: Sant'Agapito | AP45: Fossa | AS45: Melissano | AT45: Lomagna | AV45: Pieve Fissiraga | AX45: San Severino Marche | AY45: Quistello | BB45: Malfa | BC45: Cormano | BD45: Soliera | BE45: Seregno | BF45: Marigliano | BG45: Grignasco | BH45: Onifai | BI45: Ollastra | BJ45: Limena | BK45: Isola delle Femmine | BL45: Varsi | BM45: Cervesina | BN45: San Giustino | BO45: Serra Sant'Abbondio | BP45: Turrivalignani | BQ45: Villanova sull'Arda | BT45: Tramonti di Sotto | BU45: Maratea | BY45: Mammola | CA45: Montopoli di Sabina | CC45: Gallicano nel Lazio | CD45: Stienta | CE45: Colliano | CF45: Mara | CG45: Orco Feglino | CJ45: Morbegno | CK45: Narcao | CM45: Torricella Sicura | CO45: Buttigliera Alta | CQ45: Cavizzana | CR45: Monfumo | CT45: Gemona del Friuli | CU45: Morgex | CV45: Castelveccana | CW45: Vigonovo | CX45: Montecrestese | CY45: Moncrivello | CZ45: Legnago | DA45: Tropea | DB45: Isola Vicentina | DC45: Proceno
B46: Castellania Coppi | C46: Sirolo | F46: Cortanze | G46: Luogosano | J46: Sedico | K46: Paduli | L46: Calusco d'Adda | M46: Pralungo | N46: Sala Bolognese | O46: Luson/Lüsen | P46: Castrezzato | T46: Montemitro | U46: Grazzanise | V46: San Gregorio di Catania | W46: Montepaone | X46: Lama dei Peligni | Y46: Cermenate | Z46: Cosenza | AA46: Genivolta | AC46: Castagnito | AH46: San Giovanni Rotondo | AJ46: Morolo | AK46: Propata | AN46: Pornassio | AO46: Sant'Angelo del Pesco | AP46: Gagliano Aterno | AS46: Melpignano | AT46: Malgrate | AV46: Salerano sul Lambro | AX46: Sant'Angelo in Pontano | AY46: Redondesco | BB46: Malvagna | BC46: Cornaredo | BD46: Spilamberto | BE46: Seveso | BF46: Massa Lubrense | BG46: Invorio | BH46: Oniferi | BI46: Oristano | BJ46: Loreggia | BK46: Lascari | BM46: Chignolo Po | BN46: Sant'Anatolia di Narco | BO46: Tavoleto | BP46: Vicoli | BQ46: Zerba | BT46: Travesio | BU46: Marsico Nuovo | BY46: Marina di Gioiosa Ionica | CA46: Morro Reatino | CC46: Gavignano | CD46: Taglio di Po | CE46: Conca dei Marini | CF46: Martis | CG46: Ortovero | CJ46: Novate Mezzola | CK46: Nuragus | CM46: Tortoreto | CO46: Cafasse | CQ46: Cembra Lisignago | CR46: Montebelluna | CT46: Gonars | CU46: Nus | CV46: Castiglione Olona | CX46: Montescheno | CY46: Motta de' Conti | CZ46: Malcesine | DA46: Vallelonga | DB46: Laghi | DC46: Ronciglione
B47: Castellar Guidobono | C47: Staffolo | F47: Cortazzone | G47: Manocalzati | J47: Selva di Cadore | K47: Pago Veiano | L47: Calvenzano | M47: Pray | N47: San Benedetto Val di Sambro | O47: Magrè sulla strada del vino/Margreid an der Weinstraße | P47: Cazzago San Martino | T47: Montenero di Bisaccia | U47: Gricignano di Aversa | V47: San Michele di Ganzaria | W47: Motta Santa Lucia | X47: Lanciano | Y47: Cernobbio | Z47: Cropalati | AA47: Gerre de' Caprioli | AC47: Casteldelfino | AH47: San Marco in Lamis | AJ47: Paliano | AK47: Rapallo | AN47: Prelà | AO47: Sant'Elena Sannita | AP47: Gioia dei Marsi | AS47: Miggiano | AT47: Mandello del Lario | AV47: San Fiorano | AX47: Sarnano | AY47: Rivarolo Mantovano | BB47: Mandanici | BC47: Corsico | BD47: Vignola | BE47: Sovico | BF47: Massa di Somma | BG47: Landiona | BH47: Orani | BI47: Palmas Arborea | BJ47: Lozzo Atestino | BK47: Lercara Friddi | BM47: Cigognola | BN47: Scheggia e Pascelupo | BO47: Tavullia | BP47: Villa Celiera | BQ47: Ziano Piacentino | BT47: Vajont | BU47: Marsicovetere | BY47: Maropati | CA47: Nespolo | CC47: Genazzano | CD47: Trecenta | CE47: Controne | CF47: Monteleone Rocca Doria | CG47: Osiglia | CJ47: Pedesina | CK47: Nurallao | CM47: Tossicia | CO47: Caluso | CQ47: Cimone | CR47: Morgano | CT47: Grimacco | CU47: Ollomont | CV47: Castronno | CX47: Nonio | CY47: Olcenengo | CZ47: Marano di Valpolicella | DA47: Vazzano | DB47: Lastebasse | DC47: San Lorenzo Nuovo
B48: Castellazzo Bormida | C48: Trecastelli | F48: Cortiglione | G48: Marzano di Nola | J48: Seren del Grappa | K48: Pannarano | L48: Camerata Cornello | M48: Quaregna Cerreto | N48: San Giorgio di Piano | O48: Malles Venosta/Mals | P48: Cedegolo | T48: Montorio nei Frentani | U48: Letino | V48: San Pietro Clarenza | W48: Nocera Terinese | X48: Lentella | Y48: Cirimido | Z48: Crosia | AA48: Gombito | AC48: Castelletto Stura | AH48: San Marco la Catola | AJ48: Pastena | AK48: Recco | AN48: Ranzo | AO48: Santa Maria del Molise | AP48: Goriano Sicoli | AS48: Minervino di Lecce | AT48: Margno | AV48: San Martino in Strada | AX48: Sefro | AY48: Rodigo | BB48: Mazzarrà Sant'Andrea | BC48: Cuggiono | BD48: Zocca | BE48: Sulbiate | BF48: Melito di Napoli | BG48: Lesa | BH48: Orgosolo | BI48: Pau | BJ48: Maserà di Padova | BK48: Marineo | BM48: Cilavegna | BN48: Scheggino | BO48: Terre Roveresche | BT48: Valvasone Arzene | BU48: Maschito | BY48: Martone | CA48: Orvinio | CC48: Genzano di Roma | CD48: Villadose | CE48: Contursi Terme | CF48: Monti | CG48: Pallare | CJ48: Piantedo | CK48: Nuraminis | CM48: Valle Castellana | CO48: Cambiano | CQ48: Cinte Tesino | CR48: Moriago della Battaglia | CT48: Latisana | CU48: Oyace | CV48: Cavaria con Premezzo | CX48: Oggebbio | CY48: Oldenico | CZ48: Mezzane di Sotto | DA48: Vibo Valentia | DB48: Longare | DC48: Soriano nel Cimino
B49: Castelletto Merli | F49: Cossombrato | G49: Melito Irpino | J49: Setteville | K49: Paolisi | L49: Canonica d'Adda | M49: Ronco Biellese | N49: San Giovanni in Persiceto | O49: Marebbe/Enneberg | P49: Cellatica | T49: Morrone del Sannio | U49: Liberi | V49: Sant'Agata li Battiati | W49: Olivadi | X49: Lettopalena | Y49: Claino con Osteno | Z49: Diamante | AA49: Grontardo | AC49: Castelletto Uzzone | AH49: San Nicandro Garganico | AJ49: Patrica | AK49: Rezzoaglio | AN49: Rezzo | AO49: Scapoli | AP49: Introdacqua | AS49: Monteroni di Lecce | AT49: Merate | AV49: San Rocco al Porto | AX49: Serrapetrona | AY49: Roncoferraro | BB49: Merì | BC49: Cusago | BE49: Triuggio | BF49: Meta | BG49: Maggiora | BH49: Orosei | BI49: Paulilatino | BJ49: Masi | BK49: Mezzojuso | BM49: Codevilla | BN49: Sellano | BO49: Urbania | BT49: Vito d'Asio | BU49: Melfi | BY49: Melicucco | CA49: Paganico Sabino | CC49: Gerano | CD49: Villamarzana | CE49: Corbara | CF49: Mores | CG49: Piana Crixia | CJ49: Piateda | CK49: Nurri | CO49: Campiglione Fenile | CQ49: Cis | CR49: Motta di Livenza | CT49: Lauco | CU49: Perloz | CV49: Cazzago Brabbia | CX49: Omegna | CY49: Palazzolo Vercellese | CZ49: Minerbe | DA49: Zaccanopoli | DB49: Lonigo | DC49: Sutri
B50: Castelletto Monferrato | F50: Costigliole d'Asti | G50: Mercogliano | J50: Sospirolo | K50: Paupisi | L50: Capizzone | M50: Roppolo | N50: San Lazzaro di Savena | O50: Marlengo/Marling | P50: Cerveno | T50: Oratino | U50: Lusciano | V50: Sant'Alfio | W50: Palermiti | X50: Liscia | Y50: Colonno | Z50: Dipignano | AA50: Grumello Cremonese ed Uniti | AC50: Castellinaldo d'Alba | AH50: San Paolo di Civitate | AJ50: Pescosolido | AK50: Ronco Scrivia | AN50: Riva Ligure | AO50: Sessano del Molise | AP50: L'Aquila | AS50: Montesano Salentino | AT50: Missaglia | AV50: Sant'Angelo Lodigiano | AX50: Serravalle di Chienti | AY50: Roverbella | BB50: Messina | BC50: Cusano Milanino | BE50: Usmate Velate | BF50: Monte di Procida | BG50: Mandello Vitta | BH50: Orotelli | BI50: Pompu | BJ50: Massanzago | BK50: Misilmeri | BM50: Colli Verdi | BN50: Sigillo | BO50: Urbino | BT50: Vivaro | BU50: Missanello | BY50: Melicuccà | CA50: Pescorocchiano | CC50: Gorga | CD50: Villanova Marchesana | CE50: Corleto Monforte | CF50: Muros | CG50: Pietra Ligure | CJ50: Piuro | CK50: Nuxis | CO50: Candia Canavese | CQ50: Civezzano | CR50: Nervesa della Battaglia | CT50: Lestizza | CU50: Pollein | CV50: Cislago | CX50: Ornavasso | CY50: Pertengo | CZ50: Montecchia di Crosara | DA50: Zambrone | DB50: Lugo di Vicenza | DC50: Tarquinia
B51: Castelletto d'Erro | F51: Cunico | G51: Mirabella Eclano | J51: Soverzene | K51: Pesco Sannita | L51: Capriate San Gervasio | M51: Rosazza | N51: San Pietro in Casale | O51: Martello/Martell | P51: Ceto | T51: Palata | U51: Macerata Campania | V51: Santa Maria di Licodia | W51: Pentone | X51: Miglianico | Y51: Colverde | Z51: Domanico | AA51: Gussola | AC51: Castellino Tanaro | AH51: San Severo | AJ51: Picinisco | AK51: Rondanina | AN51: Rocchetta Nervina | AO51: Sesto Campano | AP51: Lecce nei Marsi | AS51: Morciano di Leuca | AT51: Moggio | AV51: Santo Stefano Lodigiano | AX51: Tolentino | AY51: Sabbioneta | BB51: Milazzo | BC51: Dairago | BE51: Varedo | BF51: Mugnano di Napoli | BG51: Marano Ticino | BH51: Ortueri | BI51: Riola Sardo | BJ51: Megliadino San Vitale | BK51: Monreale | BM51: Confienza | BN51: Spello | BO51: Vallefoglia | BT51: Zoppola | BU51: Moliterno | BY51: Melito di Porto Salvo | CA51: Petrella Salto | CC51: Grottaferrata | CD51: Villanova del Ghebbo | CE51: Cuccaro Vetere | CF51: Nughedu San Nicolò | CG51: Plodio | CJ51: Poggiridenti | CK51: Orroli | CO51: Candiolo | CQ51: Cles | CR51: Oderzo | CT51: Lignano Sabbiadoro | CU51: Pont-Saint-Martin | CV51: Cittiglio | CX51: Pallanzeno | CY51: Pezzana | CZ51: Monteforte d'Alpone | DA51: Zungri | DB51: Lusiana Conco | DC51: Tessennano
B52: Castelletto d'Orba | F52: Dusino San Michele | G52: Montaguto | J52: Sovramonte | K52: Pietraroja | L52: Caprino Bergamasco | M52: Sagliano Micca | N52: Sant'Agata Bolognese | O52: Meltina/Mölten | P52: Cevo | T52: Petacciato | U52: Maddaloni | V52: Santa Venerina | W52: Petrizzi | X52: Montazzoli | Y52: Como | Z52: Fagnano Castello | AA52: Isola Dovarese | AC52: Castelmagno | AH52: Sant'Agata di Puglia | AJ52: Pico | AK52: Rossiglione | AN52: San Bartolomeo al Mare | AO52: Vastogirardi | AP52: Luco dei Marsi | AS52: Muro Leccese | AT52: Molteno | AV52: Secugnago | AX52: Treia | AY52: San Benedetto Po | BB52: Militello Rosmarino | BC52: Dresano | BE52: Vedano al Lambro | BF52: Napoli | BG52: Massino Visconti | BH52: Orune | BI52: Ruinas | BJ52: Merlara | BK52: Montelepre | BM52: Copiano | BN52: Spoleto | BU52: Montemilone | BY52: Molochio | CA52: Poggio Bustone | CC52: Guidonia Montecelio | CE52: Eboli | CF52: Nule | CG52: Pontinvrea | CJ52: Ponte in Valtellina | CK52: Ortacesus | CO52: Canischio | CQ52: Comano Terme | CR52: Ormelle | CT52: Lusevera | CU52: Pontboset | CV52: Clivio | CX52: Piedimulera | CY52: Pila | CZ52: Mozzecane | DB52: Malo | DC52: Tuscania
B53: Castelnuovo Bormida | F53: Ferrere | G53: Montecalvo Irpino | J53: Taibon Agordino | K53: Pietrelcina | L53: Caravaggio | M53: Sala Biellese | N53: Sasso Marconi | O53: Merano/Meran | P53: Chiari | T53: Petrella Tifernina | U53: Marcianise | V53: Scordia | W53: Petronà | X53: Montebello sul Sangro | Y53: Corrido | Z53: Falconara Albanese | AA53: Izano | AC53: Castelnuovo di Ceva | AH53: Serracapriola | AJ53: Piedimonte San Germano | AK53: Rovegno | AN53: San Biagio della Cima | AO53: Venafro | AP53: Lucoli | AS53: Nardò | AT53: Monte Marenzo | AV53: Senna Lodigiana | AX53: Urbisaglia | AY53: San Giacomo delle Segnate | BB53: Mirto | BC53: Gaggiano | BE53: Veduggio con Colzano | BF53: Nola | BG53: Meina | BH53: Osidda | BI53: Sagama | BJ53: Mestrino | BK53: Montemaggiore Belsito | BM53: Corana | BN53: Todi | BU53: Montemurro | BY53: Monasterace | CA53: Poggio Catino | CC53: Jenne | CE53: Felitto | CF53: Nulvi | CG53: Quiliano | CJ53: Postalesio | CK53: Pabillonis | CO53: Cantalupa | CQ53: Commezzadura | CR53: Orsago | CT53: Magnano in Riviera | CU53: Pontey | CV53: Cocquio-Trevisago | CX53: Pieve Vergonte | CY53: Piode | CZ53: Negrar di Valpolicella | DB53: Marano Vicentino | DC53: Valentano
B54: Castelnuovo Scrivia | F54: Fontanile | G54: Montefalcione | J54: Tambre | K54: Ponte | L54: Carobbio degli Angeli | M54: Salussola | N54: Valsamoggia | O54: Monguelfo-Tesido/Welsberg-Taisten | P54: Cigole | T54: Pietracatella | U54: Marzano Appio | V54: Trecastagni | W54: Pianopoli | X54: Monteferrante | Y54: Cremia | Z54: Figline Vegliaturo | AA54: Madignano | AC54: Castiglione Falletto | AH54: Stornara | AJ54: Piglio | AK54: San Colombano Certenoli | AN54: San Lorenzo al Mare | AP54: Magliano de' Marsi | AS54: Neviano | AT54: Montevecchia | AV54: Somaglia | AX54: Ussita | AY54: San Giorgio Bigarello | BB54: Mistretta | BC54: Garbagnate Milanese | BE54: Verano Brianza | BF54: Ottaviano | BG54: Mezzomerico | BH54: Osini | BI54: Samugheo | BJ54: Monselice | BK54: Palazzo Adriano | BM54: Cornale e Bastida | BN54: Torgiano | BU54: Muro Lucano | BY54: Montebello Jonico | CA54: Poggio Mirteto | CC54: Labico | CE54: Fisciano | CF54: Olbia | CG54: Rialto | CJ54: Prata Camportaccio | CK54: Pauli Arbarei | CO54: Cantoira | CQ54: Contà | CR54: Paese | CT54: Majano | CU54: Pré-Saint-Didier | CV54: Comabbio | CX54: Premeno | CY54: Postua | CZ54: Nogara | DB54: Marostica | DC54: Vallerano
B55: Castelspina | F55: Frinco | G55: Monteforte Irpino | J55: Val di Zoldo | K55: Pontelandolfo | L55: Carona | M55: Sandigliano | N55: Vergato | O55: Montagna sulla strada del vino/Montan an der Weinstraße | P55: Cimbergo | T55: Pietracupa | U55: Mignano Monte Lungo | V55: Tremestieri Etneo | W55: Platania | X55: Montelapiano | Y55: Cucciago | Z55: Firmo | AA55: Malagnino | AC55: Castiglione Tinella | AH55: Stornarella | AJ55: Pignataro Interamna | AK55: Sant'Olcese | AN55: Sanremo | AP55: Massa d'Albe | AS55: Nociglia | AT55: Monticello Brianza | AV55: Sordio | AX55: Valfornace | AY55: San Giovanni del Dosso | BB55: Moio Alcantara | BC55: Gessate | BE55: Villasanta | BF55: Palma Campania | BG55: Miasino | BH55: Ottana | BI55: San Nicolò d'Arcidano | BJ55: Montagnana | BK55: Palermo | BM55: Corteolona e Genzone | BN55: Trevi | BU55: Nemoli | BY55: Motta San Giovanni | CA55: Poggio Moiano | CC55: Ladispoli | CE55: Furore | CF55: Olmedo | CG55: Roccavignale | CJ55: Rasura | CK55: Perdaxius | CO55: Caprie | CQ55: Croviana | CR55: Pederobba | CT55: Malborghetto Valbruna | CU55: Quart | CV55: Comerio | CX55: Premia | CY55: Prarolo | CZ55: Nogarole Rocca | DB55: Monte di Malo | DC55: Vasanello
B56: Cavatore | F56: Grana Monferrato | G56: Montefredane | J56: Vallada Agordina | K56: Puglianello | L56: Carvico | M56: Sordevolo | N56: Zola Predosa | O56: Moso in Passiria/Moos in Passeier | P56: Cividate Camuno | T56: Portocannone | U56: Mondragone | V56: Valverde | W56: San Floro | X56: Montenerodomo | Y56: Cusino | Z56: Fiumefreddo Bruzio | AA56: Martignana di Po | AC56: Castino | AH56: Torremaggiore | AJ56: Pofi | AK56: Santa Margherita Ligure | AN56: Santo Stefano al Mare | AP56: Molina Aterno | AS56: Novoli | AT56: Morterone | AV56: Tavazzano con Villavesco | AX56: Visso | AY56: San Martino dall'Argine | BB56: Monforte San Giorgio | BC56: Gorgonzola | BE56: Vimercate | BF56: Piano di Sorrento | BG56: Momo | BH56: Ovodda | BI56: San Vero Milis | BJ56: Montegrotto Terme | BK56: Partinico | BM56: Corvino San Quirico | BN56: Tuoro sul Trasimeno | BU56: Noepoli | BY56: Oppido Mamertina | CA56: Poggio Nativo | CC56: Lanuvio | CE56: Futani | CF56: Oschiri | CG56: Sassello | CJ56: Rogolo | CK56: Pimentel | CO56: Caravino | CQ56: Dambel | CR56: Pieve del Grappa | CT56: Manzano | CU56: Rhêmes-Notre-Dame | CV56: Cremenaga | CX56: Premosello-Chiovenda | CY56: Quarona | CZ56: Oppeano | DB56: Montebello Vicentino | DC56: Vejano
B57: Cella Monte | F57: Grazzano Badoglio | G57: Montefusco | J57: Valle di Cadore | K57: Reino | L57: Casazza | M57: Sostegno | O57: Nalles/Nals | P57: Coccaglio | T57: Provvidenti | U57: Orta di Atella | V57: Viagrande | W57: San Mango d'Aquino | X57: Monteodorisio | Y57: Dizzasco | Z57: Francavilla Marittima | AA57: Monte Cremasco | AC57: Cavallerleone | AH57: Troia | AJ57: Pontecorvo | AK57: Santo Stefano d'Aveto | AN57: Seborga | AP57: Montereale | AS57: Ortelle | AT57: Nibionno | AV57: Terranova dei Passerini | AY57: Schivenoglia | BB57: Mongiuffi Melia | BC57: Grezzago | BF57: Pimonte | BG57: Nebbiuno | BH57: Perdasdefogu | BI57: Santa Giusta | BJ57: Noventa Padovana | BK57: Petralia Soprana | BM57: Costa de' Nobili | BN57: Umbertide | BU57: Oppido Lucano | BY57: Palizzi | CA57: Poggio San Lorenzo | CC57: Lariano | CE57: Giffoni Sei Casali | CF57: Osilo | CG57: Savona | CJ57: Samolaco | CK57: Piscinas | CO57: Carema | CQ57: Denno | CR57: Pieve di Soligo | CT57: Marano Lagunare | CU57: Rhêmes-Saint-Georges | CV57: Crosio della Valle | CX57: Quarna Sopra | CY57: Quinto Vercellese | CZ57: Palù | DB57: Montecchio Maggiore | DC57: Vetralla
B58: Cereseto | F58: Incisa Scapaccino | G58: Montella | J58: Vigo di Cadore | K58: San Bartolomeo in Galdo | L58: Casirate d'Adda | M58: Strona | O58: Naturno/Naturns | P58: Collebeato | T58: Riccia | U58: Parete | V58: Vizzini | W58: San Pietro Apostolo | X58: Mozzagrogna | Y58: Domaso | Z58: Frascineto | AA58: Montodine | AC58: Cavallermaggiore | AH58: Vico del Gargano | AJ58: Posta Fibreno | AK58: Savignone | AN58: Soldano | AP58: Morino | AS58: Otranto | AT58: Oggiono | AV58: Turano Lodigiano | AY58: Sermide e Felonica | BB58: Montagnareale | BC58: Gudo Visconti | BF58: Poggiomarino | BG58: Nibbiola | BH58: Posada | BI58: Santu Lussurgiu | BJ58: Ospedaletto Euganeo | BK58: Petralia Sottana | BM58: Cozzo | BN58: Valfabbrica | BU58: Palazzo San Gervasio | BY58: Palmi | CA58: Posta | CC58: Licenza | CE58: Giffoni Valle Piana | CF58: Ossi | CG58: Spotorno | CJ58: San Giacomo Filippo | CK58: Portoscuso | CO58: Carignano | CQ58: Dimaro Folgarida | CR58: Ponte di Piave | CT58: Martignacco | CU58: Roisan | CV58: Cuasso al Monte | CX58: Quarna Sotto | CY58: Rassa | CZ58: Pastrengo | DB58: Montecchio Precalcino | DC58: Vignanello
B59: Cerreto Grue | F59: Isola d'Asti | G59: Montemarano | J59: Vodo Cadore | K59: San Giorgio La Molara | L59: Casnigo | M59: Tavigliano | O59: Naz-Sciaves/Natz-Schabs | P59: Collio | T59: Ripabottoni | U59: Pastorano | V59: Zafferana Etnea | W59: San Pietro a Maida | X59: Orsogna | Y59: Dongo | Z59: Fuscaldo | AA59: Moscazzano | AC59: Celle di Macra | AH59: Vieste | AJ59: Ripi | AK59: Serra Riccò | AN59: Taggia | AP59: Navelli | AS59: Palmariggi | AT59: Olgiate Molgora | AV59: Valera Fratta | AY59: Serravalle a Po | BB59: Montalbano Elicona | BC59: Inveruno | BF59: Pollena Trocchia | BG59: Novara | BH59: Sarule | BI59: Scano di Montiferro | BJ59: Padova | BK59: Piana degli Albanesi | BM59: Cura Carpignano | BN59: Vallo di Nera | BU59: Paterno | BY59: Pazzano | CA59: Pozzaglia Sabina | CC59: Magliano Romano | CE59: Gioi | CF59: Ozieri | CG59: Stella | CJ59: Sernio | CK59: Sadali | CO59: Carmagnola | CQ59: Drena | CR59: Ponzano Veneto | CT59: Mereto di Tomba | CU59: Saint-Christophe | CV59: Cugliate-Fabiasco | CX59: Re | CY59: Rimella | CZ59: Pescantina | DB59: Montegalda | DC59: Villa San Giovanni in Tuscia
B60: Cerrina Monferrato | F60: Loazzolo | G60: Montemiletto | J60: Voltago Agordino | K60: San Giorgio del Sannio | L60: Cassiglio | M60: Ternengo | O60: Nova Levante/Welschnofen | P60: Cologne | T60: Ripalimosani | U60: Piana di Monte Verna | W60: San Sostene | X60: Ortona | Y60: Dosso del Liro | Z60: Grimaldi | AA60: Motta Baluffi | AC60: Centallo | AH60: Volturara Appula | AJ60: Rocca d'Arce | AK60: Sestri Levante | AN60: Terzorio | AP60: Ocre | AS60: Parabita | AT60: Olginate | AV60: Villanova del Sillaro | AY60: Solferino | BB60: Motta Camastra | BC60: Inzago | BF60: Pomigliano d'Arco | BG60: Oleggio | BH60: Silanus | BI60: Sedilo | BJ60: Pernumia | BK60: Polizzi Generosa | BM60: Dorno | BN60: Valtopina | BU60: Pescopagano | BY60: Placanica | CA60: Rieti | CC60: Mandela | CE60: Giungano | CF60: Padria | CG60: Stellanello | CJ60: Sondalo | CK60: Samassi | CO60: Casalborgone | CQ60: Dro | CR60: Portobuffolè | CT60: Moggio Udinese | CU60: Saint-Denis | CV60: Cunardo | CX60: San Bernardino Verbano | CY60: Rive | CZ60: Peschiera del Garda | DB60: Montegaldella | DC60: Viterbo
B61: Coniolo | F61: Maranzana | G61: Monteverde | J61: Zoppè di Cadore | K61: San Leucio del Sannio | L61: Castel Rozzone | M61: Tollegno | O61: Nova Ponente/Deutschnofen | P61: Comezzano-Cizzago | T61: Roccavivara | U61: Piedimonte Matese | W61: San Vito sullo Ionio | X61: Paglieta | Y61: Erba | Z61: Grisolia | AA61: Offanengo | AC61: Ceresole Alba | AH61: Volturino | AJ61: Roccasecca | AK61: Sori | AN61: Triora | AP61: Ofena | AS61: Patù | AT61: Oliveto Lario | AV61: Zelo Buon Persico | AY61: Sustinente | BB61: Motta d'Affermo | BC61: Lacchiarella | BF61: Pompei | BG61: Oleggio Castello | BH61: Sindia | BI61: Seneghe | BJ61: Piacenza d'Adige | BK61: Pollina | BM61: Ferrera Erbognone | BU61: Picerno | BY61: Platì | CA61: Rivodutri | CC61: Manziana | CE61: Ispani | CF61: Padru | CG61: Testico | CJ61: Sondrio | CK61: Samatzai | CO61: Cascinette d'Ivrea | CQ61: Fai della Paganella | CR61: Possagno | CT61: Moimacco | CU61: Saint-Marcel | CV61: Curiglia con Monteviasco | CX61: Santa Maria Maggiore | CY61: Roasio | CZ61: Povegliano Veronese | DB61: Monteviale | DC61: Vitorchiano
B62: Conzano | F62: Maretto | G62: Montoro | K62: San Lorenzello | L62: Castelli Calepio | M62: Torrazzo | O62: Ora/Auer | P62: Concesio | T62: Rotello | U62: Pietramelara | W62: Sant'Andrea Apostolo dello Ionio | X62: Palena | Y62: Eupilio | Z62: Guardia Piemontese | AA62: Olmeneta | AC62: Cerretto Langhe | AH62: Zapponeta | AJ62: San Biagio Saracinisco | AK62: Tiglieto | AN62: Vallebona | AP62: Opi | AS62: Poggiardo | AT62: Osnago | AY62: Suzzara | BB62: Naso | BC62: Lainate | BF62: Portici | BG62: Orta San Giulio | BH62: Siniscola | BI62: Senis | BJ62: Piazzola sul Brenta | BK62: Prizzi | BM62: Filighera | BU62: Pietragalla | BY62: Polistena | CA62: Rocca Sinibalda | CC62: Marano Equo | CE62: Laureana Cilento | CF62: Palau | CG62: Toirano | CJ62: Spriana | CK62: San Basilio | CO62: Caselette | CQ62: Fiavè | CR62: Povegliano | CT62: Montenars | CU62: Saint-Nicolas | CV62: Cuveglio | CX62: Stresa | CY62: Ronsecco | CZ62: Pressana | DB62: Monticello Conte Otto
B63: Costa Vescovato | F63: Moasca | G63: Morra De Sanctis | K63: San Lorenzo Maggiore | L63: Castione della Presolana | M63: Valdengo | O63: Ortisei/St. Ulrich | P63: Corte Franca | T63: Salcito | U63: Pietravairano | W63: Santa Caterina dello Ionio | X63: Palmoli | Y63: Faggeto Lario | Z63: Lago | AA63: Ostiano | AC63: Cervasca | AJ63: San Donato Val di Comino | AK63: Torriglia | AN63: Vallecrosia | AP63: Oricola | AS63: Porto Cesareo | AT63: Paderno d'Adda | AY63: Viadana | BB63: Nizza di Sicilia | BC63: Legnano | BF63: Pozzuoli | BG63: Paruzzaro | BH63: Sorgono | BI63: Sennariolo | BJ63: Piombino Dese | BK63: Roccamena | BM63: Fortunago | BU63: Pietrapertosa | BY63: Portigliola | CA63: Roccantica | CC63: Marcellina | CE63: Laurino | CF63: Pattada | CG63: Tovo San Giacomo | CJ63: Talamona | CK63: San Gavino Monreale | CO63: Caselle Torinese | CQ63: Fierozzo | CR63: Preganziol | CT63: Mortegliano | CU63: Saint-Oyen | CV63: Cuvio | CX63: Toceno | CY63: Rossa | CZ63: Rivoli Veronese | DB63: Montorso Vicentino
B64: Cremolino | F64: Mombaldone | G64: Moschiano | K64: San Lupo | L64: Castro | M64: Valdilana | O64: Parcines/Partschins | P64: Corteno Golgi | T64: San Biase | U64: Pignataro Maggiore | W64: Satriano | X64: Palombaro | Y64: Faloppio | Z64: Laino Borgo | AA64: Paderno Ponchielli | AC64: Cervere | AJ64: San Giorgio a Liri | AK64: Tribogna | AN64: Vasia | AP64: Ortona dei Marsi | AS64: Presicce-Acquarica | AT64: Pagnona | AY64: Villimpenta | BB64: Novara di Sicilia | BC64: Liscate | BF64: Procida | BG64: Pella | BH64: Talana | BI64: Siamaggiore | BJ64: Piove di Sacco | BK64: Roccapalumba | BM64: Frascarolo | BU64: Pignola | BY64: Reggio di Calabria | CA64: Salisano | CC64: Marino | CE64: Laurito | CF64: Perfugas | CG64: Urbe | CJ64: Tartano | CK64: San Giovanni Suergiu | CO64: Castagneto Po | CQ64: Folgaria | CR64: Quinto di Treviso | CT64: Moruzzo | CU64: Saint-Pierre | CV64: Daverio | CX64: Trarego Viggiona | CY64: Rovasenda | CZ64: Ronco all'Adige | DB64: Mussolente
B65: Denice | F65: Mombaruzzo | G65: Mugnano del Cardinale | K65: San Marco dei Cavoti | L65: Cavernago | M65: Vallanzengo | O65: Perca/Percha | P65: Corzano | T65: San Felice del Molise | U65: Pontelatone | W65: Sellia | X65: Pennadomo | Y65: Fenegrò | Z65: Laino Castello | AA65: Palazzo Pignano | AC65: Ceva | AJ65: San Giovanni Incarico | AK65: Uscio | AN65: Ventimiglia | AP65: Ortucchio | AS65: Racale | AT65: Parlasco | AY65: Volta Mantovana | BB65: Oliveri | BC65: Locate di Triulzi | BF65: Qualiano | BG65: Pettenasco | BH65: Tertenia | BI65: Siamanna | BJ65: Polverara | BK65: San Cipirello | BM65: Galliavola | BU65: Potenza | BY65: Riace | CA65: Scandriglia | CC65: Mazzano Romano | CE65: Laviano | CF65: Ploaghe | CG65: Vado Ligure | CJ65: Teglio | CK65: San Nicolò Gerrei | CO65: Castagnole Piemonte | CQ65: Fornace | CR65: Refrontolo | CT65: Muzzana del Turgnano | CU65: Saint-Rhémy-en-Bosses | CV65: Dumenza | CX65: Trasquera | CY65: Salasco | CZ65: Roncà | DB65: Nanto
B66: Dernice | F66: Mombercelli | G66: Nusco | K66: San Martino Sannita | L66: Cazzano Sant'Andrea | M66: Valle San Nicolao | O66: Plaus/Plaus | P66: Darfo Boario Terme | T66: San Giacomo degli Schiavoni | U66: Portico di Caserta | W66: Sellia Marina | X66: Pennapiedimonte | Y66: Figino Serenza | Z66: Lappano | AA66: Pandino | AC66: Cherasco | AJ66: San Vittore del Lazio | AK66: Valbrevenna | AN66: Vessalico | AP66: Ovindoli | AS66: Ruffano | AT66: Pasturo | BB66: Pace del Mela | BC66: Magenta | BF66: Quarto | BG66: Pisano | BH66: Teti | BI66: Siapiccia | BJ66: Ponso | BK66: San Giuseppe Jato | BM66: Gambarana | BU66: Rapolla | BY66: Rizziconi | CA66: Selci | CC66: Mentana | CE66: Lustra | CF66: Porto Torres | CG66: Varazze | CJ66: Tirano | CK66: San Sperate | CO66: Castellamonte | CQ66: Frassilongo | CR66: Resana | CT66: Nimis | CU66: Saint-Vincent | CV66: Duno | CX66: Trontano | CY66: Sali Vercellese | CZ66: Roverchiara | DB66: Nogarole Vicentino
B67: Fabbrica Curone | F67: Monale | G67: Ospedaletto d'Alpinolo | K67: San Nazzaro | L67: Cenate Sopra | M67: Veglio | O67: Ponte Gardena/Waidbruck | P67: Dello | T67: San Giovanni in Galdo | U67: Prata Sannita | W67: Serrastretta | X67: Perano | Y67: Fino Mornasco | Z67: Lattarico | AA67: Persico Dosimo | AC67: Chiusa di Pesio | AJ67: Sant'Ambrogio sul Garigliano | AK67: Vobbia | AN67: Villa Faraldi | AP67: Pacentro | AS67: Salice Salentino | AT67: Perledo | BB67: Pagliara | BC67: Magnago | BF67: Roccarainola | BG67: Pogno | BH67: Tiana | BI67: Simala | BJ67: Ponte San Nicolò | BK67: San Mauro Castelverde | BM67: Gambolò | BU67: Rapone | BY67: Roccaforte del Greco | CA67: Stimigliano | CC67: Monte Compatri | CE67: Magliano Vetere | CF67: Pozzomaggiore | CG67: Vendone | CJ67: Torre di Santa Maria | CK67: San Vito | CO67: Castelnuovo Nigra | CQ67: Garniga Terme | CR67: Revine Lago | CT67: Osoppo | CU67: Sarre | CV67: Fagnano Olona | CX67: Valle Cannobina | CY67: Saluggia | CZ67: Roveredo di Guà | DB67: Nove
B68: Felizzano | F68: Monastero Bormida | G68: Pago del Vallo di Lauro | K68: San Nicola Manfredi | L68: Cenate Sotto | M68: Verrone | O68: Postal/Burgstall | P68: Desenzano del Garda | T68: San Giuliano del Sannio | U68: Pratella | W68: Sersale | X68: Pietraferrazzana | Y68: Garzeno | Z68: Longobardi | AA68: Pescarolo ed Uniti | AC68: Cigliè | AJ68: Sant'Andrea del Garigliano | AK68: Zoagli | AP68: Pereto | AS68: Salve | AT68: Pescate | BB68: Patti | BC68: Marcallo con Casone | BF68: San Gennaro Vesuviano | BG68: Pombia | BH68: Tonara | BI68: Simaxis | BJ68: Pontelongo | BK68: Santa Cristina Gela | BM68: Garlasco | BU68: Rionero in Vulture | BY68: Roccella Ionica | CA68: Tarano | CC68: Monte Porzio Catone | CE68: Maiori | CF68: Putifigari | CG68: Vezzi Portio | CJ68: Tovo di Sant'Agata | CK68: Sanluri | CO68: Castiglione Torinese | CQ68: Giovo | CR68: Riese Pio X | CT68: Ovaro | CU68: Torgnon | CV68: Ferno | CX68: Valstrona | CY68: San Germano Vercellese | CZ68: Roverè Veronese | DB68: Noventa Vicentina
B69: Fraconalto | F69: Moncalvo | G69: Parolise | K69: San Salvatore Telesino | L69: Cene | M69: Vigliano Biellese | O69: Prato allo Stelvio/Prad am Stilfserjoch | P69: Edolo | T69: San Giuliano di Puglia | U69: Presenzano | W69: Settingiano | X69: Pizzoferrato | Y69: Gera Lario | Z69: Longobucco | AA69: Pessina Cremonese | AC69: Cissone | AJ69: Sant'Apollinare | AP69: Pescasseroli | AS69: San Cassiano | AT69: Premana | BB69: Pettineo | BC69: Masate | BF69: San Giorgio a Cremano | BG69: Prato Sesia | BH69: Torpè | BI69: Sini | BJ69: Pozzonovo | BK69: Santa Flavia | BM69: Gerenzago | BU69: Ripacandida | BY69: Roghudi | CA69: Toffia | CC69: Monteflavio | CE69: Mercato San Severino | CF69: Romana | CG69: Villanova d'Albenga | CJ69: Traona | CK69: Sant'Andrea Frius | CO69: Cavagnolo | CQ69: Giustino | CR69: Roncade | CT69: Pagnacco | CU69: Valgrisenche | CV69: Ferrera di Varese | CX69: Vanzone con San Carlo | CY69: San Giacomo Vercellese | CZ69: Salizzole | DB69: Orgiano
B70: Francavilla Bisio | F70: Moncucco Torinese | G70: Paternopoli | K70: Sant'Agata de' Goti | L70: Cerete | M70: Villa del Bosco | O70: Predoi/Prettau | P70: Erbusco | T70: San Martino in Pensilis | U70: Raviscanina | W70: Simeri Crichi | X70: Poggiofiorito | Y70: Grandate | Z70: Lungro | AA70: Piadena Drizzona | AC70: Clavesana | AJ70: Sant'Elia Fiumerapido | AP70: Pescina | AS70: San Cesario di Lecce | AT70: Primaluna | BB70: Piraino | BC70: Mediglia | BF70: San Giuseppe Vesuviano | BG70: Recetto | BH70: Tortolì | BI70: Siris | BJ70: Rovolon | BK70: Sciara | BM70: Giussago | BU70: Rivello | BY70: Rosarno | CA70: Torri in Sabina | CC70: Montelanico | CE70: Minori | CF70: San Teodoro | CG70: Zuccarello | CJ70: Tresivio | CK70: Sant'Anna Arresi | CO70: Cavour | CQ70: Grigno | CR70: Salgareda | CT70: Palazzolo dello Stella | CU70: Valpelline | CV70: Gallarate | CX70: Varzo | CY70: Santhià | CZ70: San Bonifacio | DB70: Pedemonte
B71: Frascaro | F71: Mongardino | G71: Petruro Irpino | K71: Sant'Angelo a Cupolo | L71: Chignolo d'Isola | M71: Villanova Biellese | O71: Proves/Proveis | P71: Esine | T71: San Massimo | U71: Recale | W71: Sorbo San Basile | X71: Pollutri | Y71: Grandola ed Uniti | Z71: Luzzi | AA71: Pianengo | AC71: Corneliano d'Alba | AJ71: Santopadre | AP71: Pescocostanzo | AS71: San Donato di Lecce | AT71: Robbiate | BB71: Raccuja | BC71: Melegnano | BF71: San Paolo Bel Sito | BG71: Romagnano Sesia | BH71: Triei | BI71: Soddì | BJ71: Rubano | BK71: Scillato | BM71: Godiasco Salice Terme | BU71: Roccanova | BY71: Samo | CA71: Torricella in Sabina | CC71: Montelibretti | CE71: Moio della Civitella | CF71: Sant'Antonio di Gallura | CJ71: Val Masino | CK71: Sant'Antioco | CO71: Cercenasco | CQ71: Imer | CR71: San Biagio di Callalta | CT71: Palmanova | CU71: Valsavarenche | CV71: Galliate Lombardo | CX71: Verbania | CY71: Scopa | CZ71: San Giovanni Ilarione | DB71: Pianezze
B72: Frassinello Monferrato | F72: Montabone | G72: Pietradefusi | K72: Sant'Arcangelo Trimonte | L72: Chiuduno | M72: Viverone | O72: Racines/Ratschings | P72: Fiesse | T72: San Polo Matese | U72: Riardo | W72: Soverato | X72: Pretoro | Y72: Gravedona ed Uniti | Z72: Maierà | AA72: Pieranica | AC72: Cortemilia | AJ72: Serrone | AP72: Pettorano sul Gizio | AS72: San Pietro in Lama | AT72: Rogeno | BB72: Reitano | BC72: Melzo | BF72: San Sebastiano al Vesuvio | BG72: Romentino | BH72: Ulassai | BI72: Solarussa | BJ72: Saccolongo | BK72: Sclafani Bagni | BM72: Golferenzo | BU72: Rotonda | BY72: San Ferdinando | CA72: Turania | CC72: Monterotondo | CE72: Montano Antilia | CF72: Santa Maria Coghinas | CJ72: Valdidentro | CK72: Santadi | CO72: Ceres | CQ72: Isera | CR72: San Fior | CT72: Paluzza | CU72: Valtournenche | CV72: Gavirate | CX72: Vignone | CY72: Scopello | CZ72: San Giovanni Lupatoto | DB72: Piovene Rocchette
B73: Frassineto Po | F73: Montafia | G73: Pietrastornina | K73: Santa Croce del Sannio | L73: Cisano Bergamasco | M73: Zimone | O73: Rasun-Anterselva/Rasen-Antholz | P73: Flero | T73: Sant'Angelo Limosano | U73: Rocca d'Evandro | W73: Soveria Mannelli | X73: Quadri | Y73: Griante | Z73: Malito | AA73: Pieve San Giacomo | AC73: Cossano Belbo | AJ73: Settefrati | AP73: Pizzoli | AS73: Sanarica | AT73: Santa Maria Hoè | BB73: Roccafiorita | BC73: Mesero | BF73: San Vitaliano | BG73: San Maurizio d'Opaglio | BH73: Urzulei | BI73: Sorradile | BJ73: San Giorgio delle Pertiche | BK73: Termini Imerese | BM73: Gravellona Lomellina | BU73: Ruoti | BY73: San Giorgio Morgeto | CA73: Vacone | CC73: Montorio Romano | CE73: Monte San Giacomo | CF73: Santa Teresa Gallura | CJ73: Valdisotto | CK73: Sardara | CO73: Ceresole Reale | CQ73: Lavarone | CR73: San Pietro di Feletto | CT73: Pasian di Prato | CU73: Verrayes | CV73: Gazzada Schianno | CX73: Villadossola | CY73: Serravalle Sesia | CZ73: San Martino Buon Albergo | DB73: Pojana Maggiore
B74: Fresonara | F74: Montaldo Scarampi | G74: Prata di Principato Ultra | K74: Sassinoro | L74: Ciserano | M74: Zubiena | O74: Renon/Ritten | P74: Gambara | T74: Sant'Elia a Pianisi | U74: Roccamonfina | W74: Soveria Simeri | X74: Rapino | Y74: Guanzate | Z74: Malvito | AA74: Pieve d'Olmi | AC74: Costigliole Saluzzo | AJ74: Sgurgola | AP74: Poggio Picenze | AS74: Sannicola | AT74: Sirone | BB74: Roccalumera | BC74: Milano | BF74: Sant'Agnello | BG74: San Nazzaro Sesia | BH74: Ussassai | BI74: Suni | BJ74: San Giorgio in Bosco | BK74: Terrasini | BM74: Gropello Cairoli | BU74: Ruvo del Monte | BY74: San Giovanni di Gerace | CA74: Varco Sabino | CC74: Moricone | CE74: Montecorice | CF74: Sassari | CJ74: Valfurva | CK74: Segariu | CO74: Cesana Torinese | CQ74: Lavis | CR74: San Polo di Piave | CT74: Paularo | CU74: Verrès | CV74: Gemonio | CX74: Villette | CY74: Stroppiana | CZ74: San Mauro di Saline | DB74: Posina
B75: Frugarolo | F75: Montechiaro d'Asti | G75: Pratola Serra | K75: Solopaca | L75: Cividate al Piano | M75: Zumaglia | O75: Rifiano/Riffian | P75: Gardone Riviera | T75: Santa Croce di Magliano | U75: Roccaromana | W75: Squillace | X75: Ripa Teatina | Y75: Inverigo | Z75: Mandatoriccio | AA75: Pizzighettone | AC75: Cravanzana | AJ75: Sora | AP75: Prata d'Ansidonia | AS75: Santa Cesarea Terme | AT75: Sirtori | BB75: Roccavaldina | BC75: Morimondo | BF75: Sant'Anastasia | BG75: San Pietro Mosezzo | BH75: Villagrande Strisaili | BI75: Tadasuni | BJ75: San Martino di Lupari | BK75: Torretta | BM75: Inverno e Monteleone | BU75: San Chirico Nuovo | BY75: San Lorenzo | CC75: Morlupo | CE75: Montecorvino Pugliano | CF75: Sedini | CJ75: Verceia | CK75: Selegas | CO75: Chialamberto | CQ75: Ledro | CR75: San Vendemiano | CT75: Pavia di Udine | CU75: Villeneuve | CV75: Gerenzano | CX75: Vogogna | CY75: Tricerro | CZ75: San Pietro di Morubio | DB75: Pove del Grappa
B76: Fubine Monferrato | F76: Montegrosso d'Asti | G76: Quadrelle | K76: Telese Terme | L76: Clusone | O76: Rio di Pusteria/Mühlbach | P76: Gardone Val Trompia | T76: Sepino | U76: Rocchetta e Croce | W76: Stalettì | X76: Rocca San Giovanni | Y76: Laglio | Z76: Mangone | AA76: Pozzaglio ed Uniti | AC76: Crissolo | AJ76: Strangolagalli | AP76: Pratola Peligna | AS76: Scorrano | AT76: Sueglio | BB76: Roccella Valdemone | BC76: Motta Visconti | BF76: Sant'Antimo | BG76: Sillavengo | BI76: Terralba | BJ76: San Pietro Viminario | BK76: Trabia | BM76: Landriano | BU76: San Chirico Raparo | BY76: San Luca | CC76: Nazzano | CE76: Montecorvino Rovella | CF76: Semestene | CJ76: Vervio | CK76: Senorbì | CO76: Chianocco | CQ76: Levico Terme | CR76: San Zenone degli Ezzelini | CT76: Pocenia | CV76: Germignaga | CY76: Trino | CZ76: San Pietro in Cariano | DB76: Pozzoleone
B77: Gabiano | F77: Montemagno Monferrato | G77: Quindici | K77: Tocco Caudio | L77: Colere | O77: Rodengo/Rodeneck | P77: Gargnano | T77: Spinete | U77: Ruviano | W77: Taverna | X77: Roccamontepiano | Y77: Laino | Z77: Marano Marchesato | AA77: Quintano | AC77: Cuneo | AJ77: Supino | AP77: Prezza | AS77: Seclì | AT77: Suello | BB77: Rodì Milici | BC77: Nerviano | BF77: Sant'Antonio Abate | BG77: Sizzano | BI77: Tinnura | BJ77: San Pietro in Gu | BK77: Trappeto | BM77: Langosco | BU77: San Costantino Albanese | BY77: San Pietro di Caridà | CC77: Nemi | CE77: Monteforte Cilento | CF77: Sennori | CJ77: Villa di Chiavenna | CK77: Serdiana | CO77: Chiaverano | CQ77: Livo | CR77: Santa Lucia di Piave | CT77: Pontebba | CV77: Golasecca | CY77: Tronzano Vercellese | CZ77: San Zeno di Montagna | DB77: Quinto Vicentino
B78: Gamalero | F78: Montiglio Monferrato | G78: Rocca San Felice | K78: Torrecuso | L78: Cologno al Serio | O78: Salorno sulla strada del vino/Salurn an der Weinstraße | P78: Gavardo | T78: Tavenna | U78: San Cipriano d'Aversa | W78: Tiriolo | X78: Roccascalegna | Y78: Lambrugo | Z78: Marano Principato | AA78: Ricengo | AC78: Demonte | AJ78: Terelle | AP78: Raiano | AS78: Sogliano Cavour | AT78: Taceno | BB78: Rometta | BC78: Nosate | BF78: Santa Maria la Carità | BG78: Soriso | BI78: Tramatza | BJ78: Sant'Angelo di Piove di Sacco | BK78: Ustica | BM78: Lardirago | BU78: San Fele | BY78: San Procopio | CC78: Nerola | CE78: Montesano sulla Marcellana | CF78: Siligo | CJ78: Villa di Tirano | CK78: Serramanna | CO78: Chieri | CQ78: Lona-Lases | CR78: Sarmede | CT78: Porpetto | CV78: Gorla Maggiore | CY78: Valduggia | CZ78: Sanguinetto | DB78: Recoaro Terme
B79: Garbagna | F79: Moransengo-Tonengo | G79: Roccabascerana | K79: Vitulano | L79: Colzate | O79: San Candido/Innichen | P79: Ghedi | T79: Termoli | U79: San Felice a Cancello | W79: Torre di Ruggiero | X79: Roccaspinalveti | Y79: Lasnigo | Z79: Marzi | AA79: Ripalta Arpina | AC79: Diano d'Alba | AJ79: Torre Cajetani | AP79: Rivisondoli | AS79: Soleto | AT79: Valgreghentino | BB79: San Filippo del Mela | BC79: Novate Milanese | BF79: Saviano | BG79: Sozzago | BI79: Tresnuraghes | BJ79: Sant'Elena | BK79: Valledolmo | BM79: Linarolo | BU79: San Martino d'Agri | BY79: San Roberto | CC79: Nettuno | CE79: Morigerati | CF79: Sorso | CK79: Serrenti | CO79: Chiesanuova | CQ79: Luserna | CR79: Segusino | CT79: Povoletto | CV79: Gorla Minore | CY79: Varallo | CZ79: Sant'Ambrogio di Valpolicella | DB79: Roana
B80: Gavi | F80: Nizza Monferrato | G80: Rotondi | L80: Comun Nuovo | O80: San Genesio Atesino/Jenesien | P80: Gianico | T80: Torella del Sannio | U80: San Gregorio Matese | W80: Vallefiorita | X80: Roio del Sangro | Y80: Lezzeno | Z80: Mendicino | AA80: Ripalta Cremasca | AC80: Dogliani | AJ80: Torrice | AP80: Rocca Pia | AS80: Specchia | AT80: Valmadrera | BB80: San Fratello | BC80: Noviglio | BF80: Scisciano | BG80: Suno | BI80: Ulà Tirso | BJ80: Sant'Urbano | BK80: Ventimiglia di Sicilia | BM80: Lirio | BU80: San Paolo Albanese | BY80: Sant'Agata del Bianco | CC80: Olevano Romano | CE80: Nocera Inferiore | CF80: Stintino | CK80: Serri | CO80: Chiomonte | CQ80: Madruzzo | CR80: Sernaglia della Battaglia | CT80: Pozzuolo del Friuli | CV80: Gornate Olona | CY80: Vercelli | CZ80: Sant'Anna d'Alfaedo | DB80: Romano d'Ezzelino
B81: Giarole | F81: Olmo Gentile | G81: Salza Irpina | L81: Corna Imagna | O81: San Leonardo in Passiria/St. Leonhard in Passeier | P81: Gottolengo | T81: Toro | U81: San Marcellino | W81: Zagarise | X81: Rosello | Y81: Limido Comasco | Z81: Mongrassano | AA81: Ripalta Guerina | AC81: Dronero | AJ81: Trevi nel Lazio | AP81: Rocca di Botte | AS81: Spongano | AT81: Valvarrone | BB81: San Marco d'Alunzio | BC81: Opera | BF81: Serrara Fontana | BG81: Terdobbiate | BI81: Uras | BJ81: Santa Caterina d'Este | BK81: Vicari | BM81: Lomello | BU81: San Severino Lucano | BY81: Sant'Alessio in Aspromonte | CC81: Palestrina | CE81: Nocera Superiore | CF81: Telti | CK81: Setzu | CO81: Chiusa di San Michele | CQ81: Malé | CR81: Silea | CT81: Pradamano | CV81: Grantola | CY81: Villarboit | CZ81: Selva di Progno | DB81: Rossano Veneto
B82: Gremiasco | F82: Passerano Marmorito | G82: San Mango sul Calore | L82: Cornalba | O82: San Lorenzo di Sebato/St. Lorenzen | P82: Gussago | T82: Trivento | U82: San Marco Evangelista | X82: San Buono | Y82: Lipomo | Z82: Montalto Uffugo | AA82: Rivarolo del Re ed Uniti | AC82: Elva | AJ82: Trivigliano | AP82: Rocca di Cambio | AS82: Squinzano | AT82: Varenna | BB82: San Pier Niceto | BC82: Ossona | BF82: Somma Vesuviana | BG82: Tornaco | BI82: Usellus | BJ82: Santa Giustina in Colle | BK82: Villabate | BM82: Lungavilla | BU82: Sant'Angelo Le Fratte | BY82: Sant'Eufemia d'Aspromonte | CC82: Palombara Sabina | CE82: Novi Velia | CF82: Tempio Pausania | CK82: Seui | CO82: Chivasso | CQ82: Massimeno | CR82: Spresiano | CT82: Prato Carnico | CV82: Inarzo | CY82: Villata | CZ82: Soave | DB82: Rosà
B83: Grognardo | F83: Penango | G83: San Martino Valle Caudina | L83: Cortenuova | O83: San Martino in Badia/St. Martin in Thurn | P83: Idro | T83: Tufara | U83: San Nicola la Strada | X83: San Giovanni Lipioni | Y83: Livo | Z83: Montegiordano | AA83: Rivolta d'Adda | AC83: Entracque | AJ83: Vallecorsa | AP83: Rocca di Mezzo | AS83: Sternatia | AT83: Vercurago | BB83: San Piero Patti | BC83: Ozzero | BF83: Sorrento | BG83: Trecate | BI83: Villa Sant'Antonio | BJ83: Saonara | BK83: Villafrati | BM83: Magherno | BU83: Sant'Arcangelo | BY83: Sant'Ilario dello Ionio | CC83: Percile | CE83: Ogliastro Cilento | CF83: Tergu | CK83: Seulo | CO83: Ciconio | CQ83: Mazzin | CR83: Susegana | CT83: Precenicco | CV83: Induno Olona | CY83: Vocca | CZ83: Sommacampagna | DB83: Rotzo
B84: Grondona | F84: Piea | G84: San Michele di Serino | L84: Costa Serina | O84: San Martino in Passiria/St. Martin in Passeier | P84: Incudine | T84: Ururi | U84: San Pietro Infine | X84: San Giovanni Teatino | Y84: Locate Varesino | Z84: Morano Calabro | AA84: Robecco d'Oglio | AC84: Envie | AJ84: Vallemaio | AP84: Roccacasale | AS84: Supersano | AT84: Verderio | BB84: San Salvatore di Fitalia | BC84: Paderno Dugnano | BF84: Striano | BG84: Vaprio d'Agogna | BI84: Villa Verde | BJ84: Selvazzano Dentro | BM84: Marcignago | BU84: Sarconi | BY84: Santa Cristina d'Aspromonte | CC84: Pisoniano | CE84: Olevano sul Tusciano | CF84: Thiesi | CK84: Siddi | CO84: Cintano | CQ84: Mezzana | CR84: Tarzo | CT84: Premariacco | CV84: Ispra | CZ84: Sona | DB84: Salcedo
B85: Guazzora | F85: Pino d'Asti | G85: San Nicola Baronia | L85: Costa Valle Imagna | O85: San Pancrazio/St. Pankraz | P85: Irma | T85: Vinchiaturo | U85: San Potito Sannitico | X85: San Martino sulla Marrucina | Y85: Lomazzo | Z85: Mormanno | AA85: Romanengo | AC85: Farigliano | AJ85: Vallerotonda | AP85: Roccaraso | AS85: Surano | AT85: Viganò | BB85: San Teodoro | BC85: Pantigliate | BF85: Terzigno | BG85: Varallo Pombia | BI85: Villanova Truschedu | BJ85: Solesino | BM85: Marzano | BU85: Sasso di Castalda | BY85: Santo Stefano in Aspromonte | CC85: Poli | CE85: Oliveto Citra | CF85: Tissi | CK85: Siliqua | CO85: Cinzano | CQ85: Mezzano | CR85: Trevignano | CT85: Preone | CV85: Jerago con Orago | CZ85: Sorgà | DB85: San Pietro Mussolino
B86: Isola Sant'Antonio | F86: Piovà Massaia | G86: San Potito Ultra | L86: Costa Volpino | O86: Santa Cristina Valgardena/St. Christina in Gröden | P86: Iseo | U86: San Prisco | X86: San Salvo | Y86: Longone al Segrino | Z86: Mottafollone | AA86: Salvirola | AC86: Faule | AJ86: Veroli | AP86: San Benedetto dei Marsi | AS86: Surbo | BB86: Sant'Agata di Militello | BC86: Parabiago | BF86: Torre Annunziata | BG86: Vespolate | BI86: Villaurbana | BJ86: Stanghella | BM86: Mede | BU86: Satriano di Lucania | BY86: Scido | CC86: Pomezia | CE86: Omignano | CF86: Torralba | CK86: Silius | CO86: Ciriè | CQ86: Mezzocorona | CR86: Treviso | CT86: Prepotto | CV86: Lavena Ponte Tresa | CZ86: Terrazzo | DB86: San Vito di Leguzzano
B87: Lerma | F87: Portacomaro | G87: San Sossio Baronia | L87: Costa di Mezzate | O87: Sarentino/Sarntal | P87: Isorella | U87: San Tammaro | X87: San Vito Chietino | Y87: Luisago | Z87: Nocara | AA87: San Bassano | AC87: Feisoglio | AJ87: Vicalvi | AP87: San Benedetto in Perillis | AS87: Taurisano | BB87: Sant'Alessio Siculo | BC87: Paullo | BF87: Torre del Greco | BG87: Vicolungo | BI87: Zeddiani | BJ87: Teolo | BM87: Menconico | BU87: Savoia di Lucania | BY87: Scilla | CC87: Ponzano Romano | CE87: Orria | CF87: Trinità d'Agultu e Vignola | CK87: Siurgus Donigala | CO87: Claviere | CQ87: Mezzolombardo | CR87: Valdobbiadene | CT87: Pulfero | CV87: Laveno-Mombello | CZ87: Torri del Benaco | DB87: Sandrigo
B88: Lu e Cuccaro Monferrato | F88: Quaranti | G88: Sant'Andrea di Conza | L88: Covo | O88: Scena/Schenna | P88: Lavenone | U88: Sant'Angelo d'Alife | X88: Sant'Eusanio del Sangro | Y88: Lurago Marinone | Z88: Oriolo | AA88: San Daniele Po | AC88: Fossano | AJ88: Vico nel Lazio | AP88: San Demetrio ne' Vestini | AS88: Taviano | BB88: Sant'Angelo di Brolo | BC88: Pero | BF88: Trecase | BG88: Vinzaglio | BI88: Zerfaliu | BJ88: Terrassa Padovana | BM88: Mezzana Bigli | BU88: Senise | BY88: Seminara | CC88: Riano | CE88: Ottati | CF88: Tula | CK88: Soleminis | CO88: Coassolo Torinese | CQ88: Moena | CR88: Vazzola | CT88: Ragogna | CV88: Leggiuno | CZ88: Tregnago | DB88: Santorso
B89: Malvicino | F89: Refrancore | G89: Sant'Angelo a Scala | L89: Credaro | O89: Selva dei Molini/Mühlwald | P89: Leno | U89: Sant'Arpino | X89: Santa Maria Imbaro | Y89: Lurago d'Erba | Z89: Orsomarso | AA89: San Giovanni in Croce | AC89: Frabosa Soprana | AJ89: Villa Latina | AP89: San Pio delle Camere | AS89: Tiggiano | BB89: Santa Domenica Vittoria | BC89: Peschiera Borromeo | BF89: Tufino | BJ89: Tombolo | BM89: Mezzana Rabattone | BU89: Spinoso | BY89: Serrata | CC89: Rignano Flaminio | CE89: Padula | CF89: Uri | CK89: Suelli | CO89: Coazze | CQ89: Molveno | CR89: Vedelago | CT89: Ravascletto | CV89: Lonate Ceppino | CZ89: Trevenzuolo | DB89: Sarcedo
B90: Masio | F90: Revigliasco d'Asti | G90: Sant'Angelo all'Esca | L90: Curno | O90: Selva di Val Gardena/Wolkenstein in Gröden | P90: Limone sul Garda | U90: Santa Maria Capua Vetere | X90: Scerni | Y90: Lurate Caccivio | Z90: Paludi | AA90: San Martino del Lago | AC90: Frabosa Sottana | AJ90: Villa Santa Lucia | AP90: San Vincenzo Valle Roveto | AS90: Trepuzzi | BB90: Santa Lucia del Mela | BC90: Pessano con Bornago | BF90: Vico Equense | BJ90: Torreglia | BM90: Mezzanino | BU90: Teana | BY90: Siderno | CC90: Riofreddo | CE90: Pagani | CF90: Usini | CK90: Teulada | CO90: Collegno | CQ90: Mori | CR90: Vidor | CT90: Raveo | CV90: Lonate Pozzolo | CZ90: Valeggio sul Mincio | DB90: Sarego
B91: Melazzo | F91: Roatto | G91: Sant'Angelo dei Lombardi | L91: Cusio | O91: Senale-San Felice/Unsere Liebe Frau im Walde-St. Felix | P91: Lodrino | U91: Santa Maria a Vico | X91: Schiavi di Abruzzo | Y91: Magreglio | Z91: Panettieri | AA91: Scandolara Ravara | AC91: Frassino | AJ91: Villa Santo Stefano | AP91: Sant'Eusanio Forconese | AS91: Tricase | BB91: Santa Marina Salina | BC91: Pieve Emanuele | BF91: Villaricca | BJ91: Trebaseleghe | BM91: Miradolo Terme | BU91: Terranova di Pollino | BY91: Sinopoli | CC91: Rocca Canterano | CE91: Palomonte | CF91: Valledoria | CK91: Tratalias | CO91: Colleretto Castelnuovo | CQ91: Nago-Torbole | CR91: Villorba | CT91: Reana del Rojale | CV91: Lozza | CZ91: Velo Veronese | DB91: Schiavon
B92: Merana | F92: Robella | G92: Santa Lucia di Serino | L92: Dalmine | O92: Senales/Schnals | P92: Lograto | U92: Santa Maria la Fossa | X92: Taranta Peligna | Y92: Mariano Comense | Z92: Paola | AA92: Scandolara Ripa d'Oglio | AC92: Gaiola | AJ92: Viticuso | AP92: Sante Marie | AS92: Tuglie | BB92: Santa Teresa di Riva | BC92: Pioltello | BF92: Visciano | BJ92: Tribano | BM92: Montalto Pavese | BU92: Tito | BY92: Staiti | CC92: Rocca Priora | CE92: Pellezzano | CF92: Viddalba | CK92: Tuili | CO92: Colleretto Giacosa | CQ92: Nogaredo | CR92: Vittorio Veneto | CT92: Remanzacco | CV92: Luino | CZ92: Verona | DB92: Schio
B93: Mirabello Monferrato | F93: Rocca d'Arazzo | G93: Santa Paolina | L93: Dossena | O93: Sesto/Sexten | P93: Lonato del Garda | U93: Sessa Aurunca | X93: Tollo | Y93: Maslianico | Z93: Papasidero | AA93: Sergnano | AC93: Gambasca | AP93: Santo Stefano di Sessanio | AS93: Ugento | BB93: Santo Stefano di Camastra | BC93: Pogliano Milanese | BF93: Volla | BJ93: Urbana | BM93: Montebello della Battaglia | BU93: Tolve | BY93: Stignano | CC93: Rocca Santo Stefano | CE93: Perdifumo | CF93: Villanova Monteleone | CK93: Turri | CO93: Condove | CQ93: Nomi | CR93: Volpago del Montello | CT93: Resia | CV93: Luvinate | CZ93: Veronella | DB93: Solagna
B94: Molare | F94: Roccaverano | G94: Santo Stefano del Sole | L94: Endine Gaiano | O94: Silandro/Schlanders | P94: Longhena | U94: Sparanise | X94: Torino di Sangro | Y94: Menaggio | Z94: Parenti | AA94: Sesto ed Uniti | AC94: Garessio | AP94: Scanno | AS94: Uggiano la Chiesa | BB94: Saponara | BC94: Pozzo d'Adda | BJ94: Veggiano | BM94: Montecalvo Versiggia | BU94: Tramutola | BY94: Stilo | CC94: Rocca di Cave | CE94: Perito | CK94: Ussana | CO94: Corio | CQ94: Novaledo | CR94: Zenson di Piave | CT94: Resiutta | CV94: Maccagno con Pino e Veddasca | CZ94: Vestenanova | DB94: Sossano
B95: Molino dei Torti | F95: Rocchetta Palafea | G95: Savignano Irpino | L95: Entratico | O95: Sluderno/Schluderns | P95: Losine | U95: Succivo | X95: Tornareccio | Y95: Merone | Z95: Paterno Calabro | AA95: Solarolo Rainerio | AC95: Genola | AP95: Scontrone | AS95: Veglie | BB95: Savoca | BC95: Pozzuolo Martesana | BJ95: Vescovana | BM95: Montescano | BU95: Trecchina | BY95: Taurianova | CC95: Rocca di Papa | CE95: Pertosa | CK95: Ussaramanna | CO95: Cossano Canavese | CQ95: Novella | CR95: Zero Branco | CT95: Rigolato | CV95: Malnate | CZ95: Vigasio | DB95: Sovizzo
B96: Mombello Monferrato | F96: Rocchetta Tanaro | G96: Scampitella | L96: Fara Gera d'Adda | O96: Stelvio/Stilfs | P96: Lozio | U96: Teano | X96: Torrebruna | Y96: Moltrasio | Z96: Pedivigliano | AA96: Soncino | AC96: Gorzegno | AP96: Scoppito | AS96: Vernole | BB96: Scaletta Zanclea | BC96: Pregnana Milanese | BJ96: Vigodarzere | BM96: Montesegale | BU96: Trivigno | BY96: Terranova Sappo Minulio | CC96: Roccagiovine | CE96: Petina | CK96: Vallermosa | CO96: Cuceglio | CQ96: Ospedaletto | CT96: Rive d'Arcano | CV96: Marchirolo | CZ96: Villa Bartolomea | DB96: Tezze sul Brenta
B97: Momperone | F97: San Damiano d'Asti | G97: Senerchia | L97: Fara Olivana con Sola | O97: Terento/Terenten | P97: Lumezzane | U97: Teverola | X97: Torrevecchia Teatina | Y97: Monguzzo | Z97: Piane Crati | AA97: Soresina | AC97: Gottasecca | AP97: Scurcola Marsicana | AS97: Zollino | BB97: Sinagra | BC97: Rescaldina | BJ97: Vigonza | BM97: Monticelli Pavese | BU97: Vaglio Basilicata | BY97: Varapodio | CC97: Roiate | CE97: Piaggine | CK97: Villacidro | CO97: Cumiana | CQ97: Ossana | CT97: Rivignano Teor | CV97: Marnate | CZ97: Villafranca di Verona | DB97: Thiene
B98: Moncestino | F98: San Giorgio Scarampi | G98: Serino | L98: Filago | O98: Terlano/Terlan | P98: Maclodio | U98: Tora e Piccilli | X98: Torricella Peligna | Y98: Montano Lucino | Z98: Pietrafitta | AA98: Sospiro | AC98: Govone | AP98: Secinaro | BB98: Spadafora | BC98: Rho | BJ98: Villa Estense | BM98: Montù Beccaria | BU98: Venosa | BY98: Villa San Giovanni | CC98: Roma | CE98: Pisciotta | CK98: Villamar | CO98: Cuorgnè | CQ98: Palù del Fersina | CT98: Ronchis | CV98: Marzio | CZ98: Zevio | DB98: Tonezza del Cimone
B99: Mongiardino Ligure | F99: San Martino Alfieri | G99: Sirignano | L99: Fino del Monte | O99: Termeno sulla strada del vino/Tramin an der Weinstraße | P99: Magasa | U99: Trentola Ducenta | X99: Treglio | Y99: Montemezzo | Z99: Pietrapaola | AA99: Spinadesco | AC99: Grinzane Cavour | AP99: Sulmona | BB99: Taormina | BC99: Robecchetto con Induno | BJ99: Villa del Conte | BM99: Mornico Losana | BU99: Vietri di Potenza | CC99: Roviano | CE99: Polla | CK99: Villamassargia | CO99: Druento | CQ99: Panchià | CT99: Ruda | CV99: Masciago Primo | CZ99: Zimella | DB99: Torrebelvicino
B100: Monleale | F100: San Marzano Oliveto | G100: Solofra | L100: Fiorano al Serio | O100: Tesimo/Tisens | P100: Mairano | U100: Vairano Patenora | X100: Tufillo | Y100: Montorfano | Z100: Plataci | AA100: Spineda | AC100: Guarene | AP100: Tagliacozzo | BB100: Terme Vigliatore | BC100: Robecco sul Naviglio | BJ100: Villafranca Padovana | BM100: Mortara | BU100: Viggianello | CC100: Sacrofano | CE100: Pollica | CK100: Villanova Tulo | CO100: Exilles | CQ100: Peio | CT100: San Daniele del Friuli | CV100: Mercallo | DB100: Torri di Quartesolo
...

Sheet GeoMappe
A1: Regione | B1: NomeIntervalloRegione | D1: Provincia | E1: NomeIntervalloProvincia
A2: Abruzzo | B2: r_Abruzzo | D2: Agrigento | E2: p_Agrigento
A3: Basilicata | B3: r_Basilicata | D3: Alessandria | E3: p_Alessandria
A4: Calabria | B4: r_Calabria | D4: Ancona | E4: p_Ancona
A5: Campania | B5: r_Campania | D5: Arezzo | E5: p_Arezzo
A6: Emilia-Romagna | B6: r_Emilia_Romagna | D6: Ascoli Piceno | E6: p_Ascoli_Piceno
A7: Friuli-Venezia Giulia | B7: r_Friuli_Venezia_Giulia | D7: Asti | E7: p_Asti
A8: Lazio | B8: r_Lazio | D8: Avellino | E8: p_Avellino
A9: Liguria | B9: r_Liguria | D9: Bari | E9: p_Bari
A10: Lombardia | B10: r_Lombardia | D10: Barletta-Andria-Trani | E10: p_Barletta_Andria_Trani
A11: Marche | B11: r_Marche | D11: Belluno | E11: p_Belluno
A12: Molise | B12: r_Molise | D12: Benevento | E12: p_Benevento
... A21: Veneto | B21: r_Veneto | D21: Campobasso | E21: p_Campobasso
D22: Caserta | E22: p_Caserta
D23: Catania | E23: p_Catania
D24: Catanzaro | E24: p_Catanzaro
D25: Chieti | E25: p_Chieti
D26: Como | E26: p_Como
D27: Cosenza | E27: p_Cosenza
D28: Cremona | E28: p_Cremona
D29: Crotone | E29: p_Crotone
D30: Cuneo | E30: p_Cuneo
D31: Enna | E31: p_Enna
D32: Fermo | E32: p_Fermo
D33: Ferrara | E33: p_Ferrara
... D108: Viterbo | E108: p_Viterbo
